Workbook

Sheet report
A1: № | B1: Наименование | C1: Регистрационный номер | D1: Возраст компании, лет | E1: Вид деятельности/отрасль | F1: 2020, Налог на прибыль, RUB | G1: 2021, Налог на прибыль, RUB | H1: 2022, Налог на прибыль, RUB | I1: 2023, Налог на прибыль, RUB | J1: 2024, Налог на прибыль, RUB | K1: 2020, НДС, RUB | L1: 2021, НДС, RUB | M1: 2022, НДС, RUB | N1: 2023, НДС, RUB | O1: 2024, НДС, RUB | P1: 2020, Основные средства , RUB | Q1: 2021, Основные средства , RUB | R1: 2022, Основные средства , RUB | S1: 2023, Основные средства , RUB | T1: 2024, Основные средства , RUB | U1: 2020, Доходные вложения в материальные ценности, RUB | V1: 2021, Доходные вложения в материальные ценности, RUB | W1: 2022, Доходные вложения в материальные ценности, RUB | X1: 2023, Доходные вложения в материальные ценности, RUB | Y1: 2024, Доходные вложения в материальные ценности, RUB | Z1: 2020, Долгосрочные финансовые вложения, RUB | AA1: 2021, Долгосрочные финансовые вложения, RUB | AB1: 2022, Долгосрочные финансовые вложения, RUB | AC1: 2023, Долгосрочные финансовые вложения, RUB | AD1: 2024, Долгосрочные финансовые вложения, RUB | AE1: 2020, Прочие внеоборотные активы, RUB | AF1: 2021, Прочие внеоборотные активы, RUB | AG1: 2022, Прочие внеоборотные активы, RUB | AH1: 2023, Прочие внеоборотные активы, RUB | AI1: 2024, Прочие внеоборотные активы, RUB | AJ1: 2020, Внеоборотные активы, RUB | AK1: 2021, Внеоборотные активы, RUB | AL1: 2022, Внеоборотные активы, RUB | AM1: 2023, Внеоборотные активы, RUB | AN1: 2024, Внеоборотные активы, RUB | AO1: 2020, Запасы, RUB | AP1: 2021, Запасы, RUB | AQ1: 2022, Запасы, RUB | AR1: 2023, Запасы, RUB | AS1: 2024, Запасы, RUB | AT1: 2020, Дебиторская задолженность, RUB | AU1: 2021, Дебиторская задолженность, RUB | AV1: 2022, Дебиторская задолженность, RUB | AW1: 2023, Дебиторская задолженность, RUB | AX1: 2024, Дебиторская задолженность, RUB | AY1: 2020, Краткосрочные финансовые вложения, RUB | AZ1: 2021, Краткосрочные финансовые вложения, RUB | BA1: 2022, Краткосрочные финансовые вложения, RUB | BB1: 2023, Краткосрочные финансовые вложения, RUB | BC1: 2024, Краткосрочные финансовые вложения, RUB | BD1: 2020, Денежные средства и денежные эквиваленты, RUB | BE1: 2021, Денежные средства и денежные эквиваленты, RUB | BF1: 2022, Денежные средства и денежные эквиваленты, RUB | BG1: 2023, Денежные средства и денежные эквиваленты, RUB | BH1: 2024, Денежные средства и денежные эквиваленты, RUB | BI1: 2020, Прочие оборотные активы, RUB | BJ1: 2021, Прочие оборотные активы, RUB | BK1: 2022, Прочие оборотные активы, RUB | BL1: 2023, Прочие оборотные активы, RUB | BM1: 2024, Прочие оборотные активы, RUB | BN1: 2020, Оборотные активы, RUB | BO1: 2021, Оборотные активы, RUB | BP1: 2022, Оборотные активы, RUB | BQ1: 2023, Оборотные активы, RUB | BR1: 2024, Оборотные активы, RUB | BS1: 2020, Активы всего, RUB | BT1: 2021, Активы всего, RUB | BU1: 2022, Активы всего, RUB | BV1: 2023, Активы всего, RUB | BW1: 2024, Активы всего, RUB | BX1: 2020, Уставный капитал , RUB | BY1: 2021, Уставный капитал , RUB | BZ1: 2022, Уставный капитал , RUB | CA1: 2023, Уставный капитал , RUB | CB1: 2024, Уставный капитал , RUB | CC1: 2020, Переоценка внеоборотных активов, RUB | CD1: 2021, Переоценка внеоборотных активов, RUB | CE1: 2022, Переоценка внеоборотных активов, RUB | CF1: 2023, Переоценка внеоборотных активов, RUB | CG1: 2024, Переоценка внеоборотных активов, RUB | CH1: 2020, Нераспределенная прибыль (непокрытый убыток), RUB | CI1: 2021, Нераспределенная прибыль (непокрытый убыток), RUB | CJ1: 2022, Нераспределенная прибыль (непокрытый убыток), RUB | CK1: 2023, Нераспределенная прибыль (непокрытый убыток), RUB | CL1: 2024, Нераспределенная прибыль (непокрытый убыток), RUB | CM1: 2020, Капитал и резервы, RUB | CN1: 2021, Капитал и резервы, RUB | CO1: 2022, Капитал и резервы, RUB | CP1: 2023, Капитал и резервы, RUB | CQ1: 2024, Капитал и резервы, RUB | CR1: 2020, Заёмные средства (долгосрочные), RUB | CS1: 2021, Заёмные средства (долгосрочные), RUB | CT1: 2022, Заёмные средства (долгосрочные), RUB | CU1: 2023, Заёмные средства (долгосрочные), RUB | CV1: 2024, Заёмные средства (долгосрочные), RUB | CW1: 2020, Прочие долгосрочные обязательства, RUB | CX1: 2021, Прочие долгосрочные обязательства, RUB | CY1: 2022, Прочие долгосрочные обязательства, RUB | CZ1: 2023, Прочие долгосрочные обязательства, RUB | DA1: 2024, Прочие долгосрочные обязательства, RUB | DB1: 2020, Долгосрочные обязательства, RUB | DC1: 2021, Долгосрочные обязательства, RUB | DD1: 2022, Долгосрочные обязательства, RUB | DE1: 2023, Долгосрочные обязательства, RUB | DF1: 2024, Долгосрочные обязательства, RUB | DG1: 2020, Заёмные средства (краткосрочные), RUB | DH1: 2021, Заёмные средства (краткосрочные), RUB | DI1: 2022, Заёмные средства (краткосрочные), RUB | DJ1: 2023, Заёмные средства (краткосрочные), RUB | DK1: 2024, Заёмные средства (краткосрочные), RUB | DL1: 2020, Кредиторская задолженность, RUB | DM1: 2021, Кредиторская задолженность, RUB | DN1: 2022, Кредиторская задолженность, RUB | DO1: 2023, Кредиторская задолженность, RUB | DP1: 2024, Кредиторская задолженность, RUB | DQ1: 2020, Доходы будущих периодов , RUB | DR1: 2021, Доходы будущих периодов , RUB | DS1: 2022, Доходы будущих периодов , RUB | DT1: 2023, Доходы будущих периодов , RUB | DU1: 2024, Доходы будущих периодов , RUB | DV1: 2020, Прочие краткосрочные обязательства, RUB | DW1: 2021, Прочие краткосрочные обязательства, RUB | DX1: 2022, Прочие краткосрочные обязательства, RUB | DY1: 2023, Прочие краткосрочные обязательства, RUB | DZ1: 2024, Прочие краткосрочные обязательства, RUB | EA1: 2020, Краткосрочные обязательства, RUB | EB1: 2021, Краткосрочные обязательства, RUB | EC1: 2022, Краткосрочные обязательства, RUB | ED1: 2023, Краткосрочные обязательства, RUB | EE1: 2024, Краткосрочные обязательства, RUB | EF1: 2020, Выручка, RUB | EG1: 2021, Выручка, RUB | EH1: 2022, Выручка, RUB | EI1: 2023, Выручка, RUB | EJ1: 2024, Выручка, RUB | EK1: 2020, Себестоимость продаж, RUB | EL1: 2021, Себестоимость продаж, RUB | EM1: 2022, Себестоимость продаж, RUB | EN1: 2023, Себестоимость продаж, RUB | EO1: 2024, Себестоимость продаж, RUB | EP1: 2020, Коммерческие расходы, RUB | EQ1: 2021, Коммерческие расходы, RUB | ER1: 2022, Коммерческие расходы, RUB | ES1: 2023, Коммерческие расходы, RUB | ET1: 2024, Коммерческие расходы, RUB | EU1: 2020, Управленческие расходы, RUB | EV1: 2021, Управленческие расходы, RUB | EW1: 2022, Управленческие расходы, RUB | EX1: 2023, Управленческие расходы, RUB | EY1: 2024, Управленческие расходы, RUB | EZ1: 2020, Доходы от участия в других организациях, RUB | FA1: 2021, Доходы от участия в других организациях, RUB | FB1: 2022, Доходы от участия в других организациях, RUB | FC1: 2023, Доходы от участия в других организациях, RUB | FD1: 2024, Доходы от участия в других организациях, RUB | FE1: 2020, Проценты к получению, RUB | FF1: 2021, Проценты к получению, RUB | FG1: 2022, Проценты к получению, RUB | FH1: 2023, Проценты к получению, RUB | FI1: 2024, Проценты к получению, RUB | FJ1: 2020, Проценты к уплате, RUB | FK1: 2021, Проценты к уплате, RUB | FL1: 2022, Проценты к уплате, RUB | FM1: 2023, Проценты к уплате, RUB | FN1: 2024, Проценты к уплате, RUB | FO1: 2020, Прочие доходы, RUB | FP1: 2021, Прочие доходы, RUB | FQ1: 2022, Прочие доходы, RUB | FR1: 2023, Прочие доходы, RUB | FS1: 2024, Прочие доходы, RUB | FT1: 2020, Прочие расходы, RUB | FU1: 2021, Прочие расходы, RUB | FV1: 2022, Прочие расходы, RUB | FW1: 2023, Прочие расходы, RUB | FX1: 2024, Прочие расходы, RUB | FY1: 2020, Налог на прибыль, RUB | FZ1: 2021, Налог на прибыль, RUB | GA1: 2022, Налог на прибыль, RUB | GB1: 2023, Налог на прибыль, RUB | GC1: 2024, Налог на прибыль, RUB | GD1: 2020, Чистая прибыль (убыток), RUB | GE1: 2021, Чистая прибыль (убыток), RUB | GF1: 2022, Чистая прибыль (убыток), RUB | GG1: 2023, Чистая прибыль (убыток), RUB | GH1: 2024, Чистая прибыль (убыток), RUB
A2: 1 | B2: 2-ПУ УРАЛХИММОНТАЖ, АО | C2: 1045900831745 | D2: 29 | E2: Деятельность агентов по оптовой торговле строительными материалами | G2: 4031193 | K2: 4881 | L2: 4166663 | P2: 22272000 | AJ2: 44886000 | AO2: 417794000 | AT2: 95009000 | AU2: 125140000 | AV2: 83551000 | AW2: 83551000 | AX2: 39051000 | BD2: 15538000 | BE2: 14552000 | BF2: 9969000 | BG2: 8556000 | BH2: 6402000 | BN2: 528365000 | BO2: 139692000 | BP2: 93520000 | BQ2: 92107000 | BR2: 45453000 | BS2: 573251000 | BT2: 139692000 | BU2: 93520000 | BV2: 92107000 | BW2: 45453000 | BX2: 244000 | BY2: 244000 | BZ2: 244000 | CA2: 244000 | CB2: 244000 | CC2: 3011000 | CD2: 3011000 | CE2: 3011000 | CF2: 3011000 | CG2: 3011000 | CH2: -179987000 | CI2: -137724000 | CJ2: -139396000 | CK2: -139396000 | CL2: -139396000 | CM2: -176720000 | CN2: -134457000 | CO2: -136129000 | CP2: -136129000 | CQ2: -136129000 | DB2: 419000 | DG2: 3188000 | DL2: 743965000 | DM2: 271750000 | DN2: 227250000 | DO2: 225837000 | DP2: 179183000 | EA2: 749552000 | EB2: 274149000 | EC2: 229649000 | ED2: 228236000 | EE2: 181582000 | EF2: 498000 | EK2: 2091000 | EU2: 2395000 | FO2: 12224000 | FT2: 1980000 | FU2: 1621000 | FV2: 1672000 | FY2: -1722000 | GD2: 4490000 | GE2: -1621000 | GF2: -1672000
A3: 2 | B3: 529 ВСУ, ОАО | C3: 1090506000430 | D3: 31 | E3: Строительство жилых и нежилых зданий
A4: 3 | B4: АГКА-2, ООО | C4: 1115904013884 | D4: 14 | E4: Строительство жилых и нежилых зданий | F4: 6366 | G4: 2953 | K4: 509957 | L4: 275016 | AT4: 13129000 | BD4: 214000 | BN4: 13343000 | BS4: 13343000 | BX4: 10000 | CH4: 10654000 | CM4: 10664000 | DL4: 2679000 | EA4: 2679000 | EF4: 12939000 | EK4: 7399000 | FY4: -1108000 | GD4: 4432000
A5: 4 | B5: АГРОСЕПЫЧ, ООО | C5: 1095933000404 | D5: 16 | E5: Разведение молочного крупного рогатого скота, производство сырого молока | K5: 1871915 | L5: 837696 | M5: 474043 | N5: 557558 | P5: 145248000 | Q5: 139450000 | R5: 39450000 | S5: 37369000 | T5: 1729000 | AE5: 395000 | AJ5: 145643000 | AK5: 139450000 | AL5: 39450000 | AM5: 37369000 | AN5: 1729000 | AO5: 97044000 | AP5: 86265000 | AQ5: 37090000 | AR5: 20135000 | AT5: 52891000 | AU5: 6886000 | AV5: 4250000 | AW5: 4058000 | AZ5: 90000 | BD5: 129000 | BE5: 4897000 | BF5: 39000 | BI5: 23000 | BN5: 150207000 | BO5: 98138000 | BP5: 41379000 | BQ5: 24193000 | BS5: 295850000 | BT5: 237588000 | BU5: 80829000 | BV5: 61562000 | BW5: 1729000 | BX5: 1730000 | BY5: 1730000 | BZ5: 1730000 | CA5: 1730000 | CB5: 1729000 | CC5: 10000 | CD5: 10000 | CE5: 10000 | CF5: 10000 | CH5: 40964000 | CI5: 38451000 | CJ5: 35389000 | CK5: 33294000 | CM5: 88692000 | CN5: 86179000 | CO5: 63117000 | CP5: 61022000 | CQ5: 1729000 | CR5: 2409000 | CS5: 1509000 | CT5: 1509000 | DB5: 2409000 | DC5: 1509000 | DD5: 1509000 | DG5: 63168000 | DH5: 63934000 | DI5: 13934000 | DL5: 115901000 | DM5: 63954000 | DN5: 257000 | DO5: 540000 | DQ5: 25680000 | DR5: 22012000 | DS5: 2012000 | EA5: 204749000 | EB5: 149900000 | EC5: 16203000 | ED5: 540000 | EF5: 142462000 | EG5: 127106000 | EH5: 73187000 | EI5: 27932000 | EK5: 153041000 | EL5: 143906000 | EM5: 76047000 | EN5: 29663000 | FJ5: 8432000 | FK5: 2090000 | FO5: 22842000 | FP5: 21920000 | FT5: 16961000 | FU5: 5543000 | FV5: 202000 | FW5: 364000 | GD5: -13130000 | GE5: -2513000 | GF5: -3062000 | GG5: -2095000
A6: 5 | B6: АК БАНК, АО | C6: 1026300005170 | D6: 31 | E6: Денежное посредничество прочее
A7: 6 | B7: АЛЬЯНССЕТЬСТРОЙ, АО | C7: 1115904009880 | D7: 14 | E7: Строительство коммунальных объектов для обеспечения электроэнергией и телекоммуникациями | H7: 2938453 | I7: 3277318 | K7: 2746725 | L7: 2685779 | M7: 4360900 | P7: 77566000 | Q7: 67792000 | R7: 60290000 | S7: 57862000 | T7: 289000 | AJ7: 99174000 | AK7: 89795000 | AL7: 82270000 | AM7: 79819000 | AN7: 22244000 | AO7: 212209000 | AP7: 226034000 | AQ7: 226034000 | AR7: 223949000 | AS7: 223949000 | AT7: 91702000 | AU7: 89118000 | AV7: 107194000 | AW7: 72035000 | AX7: 13317000 | BF7: 286000 | BG7: 23093000 | BH7: 27251000 | BI7: 2105000 | BJ7: 1476000 | BK7: 1476000 | BL7: 1476000 | BM7: 1476000 | BN7: 307197000 | BO7: 317899000 | BP7: 336261000 | BQ7: 321824000 | BR7: 267264000 | BS7: 406371000 | BT7: 407694000 | BU7: 418531000 | BV7: 401643000 | BW7: 289508000 | BX7: 10000000 | BY7: 10000000 | BZ7: 10000000 | CA7: 10000000 | CB7: 10000000 | CH7: -64752000 | CI7: -86226000 | CJ7: -64035000 | CK7: -77096000 | CL7: -129701000 | CM7: -54252000 | CN7: -75726000 | CO7: -53535000 | CP7: -66596000 | CQ7: -119201000 | CW7: 1123000 | CX7: 1123000 | DB7: 3673000 | DC7: 3686000 | DD7: 2563000 | DE7: 2563000 | DF7: 2563000 | DG7: 12359000 | DH7: 12353000 | DI7: 12353000 | DJ7: 12353000 | DK7: 12353000 | DL7: 444591000 | DM7: 467381000 | DN7: 457150000 | DO7: 453323000 | DP7: 393793000 | EA7: 456950000 | EB7: 479734000 | EC7: 469503000 | ED7: 465676000 | EE7: 406146000 | EF7: 71835000 | EG7: 1145000 | EK7: 85733000 | EU7: 51679000 | EV7: 23897000 | EW7: 10117000 | EX7: 6140000 | EY7: 4098000 | FE7: 378000 | FJ7: 897000 | FO7: 22490000 | FP7: 7031000 | FQ7: 44789000 | FR7: 3000000 | FS7: 9268000 | FT7: 57894000 | FU7: 3927000 | FV7: 6840000 | FW7: 9921000 | FX7: 57775000 | FY7: 20176000 | GA7: -5642000 | GD7: -84328000 | GE7: -19648000 | GF7: 22190000 | GG7: -13061000 | GH7: -52605000
A8: 7 | B8: АНТЕЙ, ООО | C8: 1085916000477 | D8: 17 | E8: Управление эксплуатацией жилого фонда за вознаграждение или на договорной основе | P8: 1496000 | Q8: 7205000 | R8: 6909000 | AJ8: 1496000 | AK8: 7205000 | AL8: 6909000 | AO8: 2205000 | AP8: 608000 | AQ8: 500000 | AR8: 233000 | AS8: 233000 | AT8: 38472000 | AU8: 14456000 | AV8: 7610000 | AW8: 17806000 | AX8: 14298000 | BD8: 17451000 | BE8: 12106000 | BF8: 1009000 | BG8: 307000 | BH8: 1062000 | BN8: 58128000 | BO8: 27170000 | BP8: 9119000 | BQ8: 18346000 | BR8: 15593000 | BS8: 59624000 | BT8: 34375000 | BU8: 16028000 | BV8: 18346000 | BW8: 15593000 | BX8: 15000 | BY8: 15000 | BZ8: 15000 | CA8: 15000 | CB8: 15000 | CH8: 25831000 | CI8: -2719000 | CJ8: -9356000 | CK8: 6816000 | CL8: -722000 | CM8: 25846000 | CN8: -2704000 | CO8: -9341000 | CP8: 6831000 | CQ8: -707000 | CW8: 20550000 | DB8: 20550000 | DL8: 13228000 | DM8: 25791000 | DN8: 24330000 | DO8: 11515000 | DP8: 16300000 | DW8: 11288000 | DX8: 1039000 | EA8: 13228000 | EB8: 37079000 | EC8: 25369000 | ED8: 11515000 | EE8: 16300000 | EF8: 111609000 | EG8: 32742000 | EH8: 7778000 | EI8: 3700000 | EK8: 94923000 | EL8: 28040000 | EM8: 15221000 | EN8: 11887000 | EO8: 688000 | FO8: 168000 | FP8: 1626000 | FQ8: 2486000 | FR8: 19356000 | FS8: 11000 | FT8: 596000 | FU8: 26201000 | FV8: 545000 | FW8: 8256000 | FX8: 6749000 | FY8: -1413000 | FZ8: -1087000 | GA8: -123000 | GB8: -123000 | GC8: -113000 | GD8: 14845000 | GE8: -20960000 | GF8: -5625000 | GG8: 2790000 | GH8: -7539000
A9: 8 | B9: АРАЛТАУ-ЗЛАТО, ООО | C9: 1105902004064 | D9: 15 | E9: Добыча руд и песков драгоценных металлов и руд редких металлов | F9: 1486860 | G9: 476 | J9: 167992 | AU9: 50000 | AV9: 3000 | AW9: 199000 | AX9: 232000 | BD9: 1535000 | BE9: 784000 | BF9: 414000 | BG9: 1306000 | BN9: 1535000 | BO9: 834000 | BP9: 417000 | BQ9: 1505000 | BR9: 232000 | BS9: 1535000 | BT9: 834000 | BU9: 417000 | BV9: 1505000 | BW9: 232000 | BX9: 1018000 | BY9: 1018000 | BZ9: 1018000 | CA9: 1018000 | CB9: 1018000 | CH9: -386000 | CI9: -1094000 | CJ9: -1523000 | CK9: -6651000 | CL9: -7054000 | CM9: 632000 | CN9: -76000 | CO9: -505000 | CP9: -5633000 | CQ9: -6036000 | DL9: 903000 | DM9: 910000 | DN9: 922000 | DO9: 7138000 | DP9: 6268000 | EA9: 903000 | EB9: 910000 | EC9: 922000 | ED9: 7138000 | EE9: 6268000 | EU9: 306000 | EV9: 315000 | EW9: 42000 | EX9: 73000 | EY9: 182000 | FM9: 6641000 | FO9: 3720000 | FR9: 3229000 | FS9: 196000 | FT9: 460000 | FU9: 393000 | FV9: 383000 | FW9: 1447000 | FX9: 402000 | FY9: -465000 | GB9: -168000 | GD9: 2475000 | GE9: -708000 | GF9: -429000 | GG9: -5128000 | GH9: -403000
A10: 9 | B10: АРСИЭНТЕК, ООО | C10: 1137746779213 | D10: 12 | E10: Деятельность по предоставлению услуг телефонной связи | K10: 1603164 | L10: 1246348 | M10: 918660
A11: 10 | B11: АРТ-ПЕРМЬ, ООО | C11: 1165958121340 | D11: 8 | E11: Деятельность зрелищно-развлекательная прочая, не включенная в другие группировки | AX11: 10000000 | BR11: 10000000 | BW11: 10000000 | CQ11: 10000000
A12: 11 | B12: АТК, ООО | C12: 1125904005974 | D12: 13 | E12: Аренда и лизинг сельскохозяйственных машин и оборудования | P12: 9324000 | R12: 9324000 | S12: 51025000 | T12: 51024000 | AJ12: 9324000 | AL12: 9324000 | AM12: 51025000 | AN12: 51024000 | AO12: 632000 | AQ12: 632000 | AR12: 632000 | AT12: 42683000 | AV12: 42683000 | AW12: 42683000 | AX12: 42683000 | BD12: 17000 | BF12: 17000 | BG12: 3530000 | BH12: 1017000 | BI12: 100000 | BK12: 100000 | BL12: 100000 | BM12: 100000 | BN12: 43432000 | BP12: 43432000 | BQ12: 46945000 | BR12: 43800000 | BS12: 52756000 | BU12: 52756000 | BV12: 97970000 | BW12: 94824000 | BX12: 10000 | BZ12: 10000 | CA12: 10000 | CB12: 10000 | CH12: -21513000 | CJ12: -21513000 | CK12: -223653000 | CL12: -226798000 | CM12: -21503000 | CO12: -21503000 | CP12: -176942000 | CQ12: -180087000 | CU12: 274794000 | CV12: 274793000 | DE12: 274912000 | DF12: 274911000 | DG12: 68751000 | DI12: 68751000 | DL12: 5508000 | DN12: 5508000 | EA12: 74259000 | EC12: 74259000 | EK12: 16000 | EU12: 1770000 | FT12: 7000 | GD12: -1793000
A13: 12 | B13: АШАТЛИ-МОЛОКО, ООО | C13: 1115951000076 | D13: 14 | E13: Производство молочной продукции | F13: 180000 | H13: 418 | K13: 1318023 | L13: 3140000 | N13: 8772 | O13: 324840 | P13: 5370000 | Q13: 5211000 | R13: 5211000 | U13: 1000 | AJ13: 5630000 | AK13: 5211000 | AL13: 5211000 | AO13: 117299000 | AP13: 9222000 | AQ13: 9222000 | AT13: 221006000 | AU13: 9993000 | AV13: 9993000 | AW13: 558775000 | AX13: 558552000 | BD13: 5000 | BG13: 64000 | BI13: 1723000 | BN13: 342206000 | BO13: 19811000 | BP13: 19811000 | BQ13: 558839000 | BR13: 558552000 | BS13: 347836000 | BT13: 25022000 | BU13: 25022000 | BV13: 558839000 | BW13: 558552000 | BX13: 10000 | BY13: 10000 | BZ13: 10000 | CA13: 10000 | CH13: 48872000 | CI13: 11310000 | CJ13: 11310000 | CK13: 21353000 | CM13: 48882000 | CN13: 11320000 | CO13: 11320000 | CP13: 21363000 | CQ13: -254641000 | DB13: 106000 | DG13: 312000 | DL13: 298536000 | DM13: 13702000 | DN13: 13702000 | DO13: 537476000 | DP13: 813193000 | EA13: 298848000 | EB13: 13702000 | EC13: 13702000 | ED13: 537476000 | EE13: 813193000 | EF13: 410640000 | EG13: 373997000 | EK13: 373837000 | EL13: 401691000 | EP13: 416000 | EQ13: 410000 | EU13: 27391000 | EV13: 1608000 | FO13: 182000 | FP13: 72000 | FT13: 2164000 | FU13: 7922000 | FX13: 335000 | FY13: -106000 | GD13: 6908000 | GE13: -37562000 | GH13: -335000
A14: 13 | B14: БИОНИКА, ООО | C14: 1065902055020 | D14: 19 | E14: Деятельность ресторанов и кафе с полным ресторанным обслуживанием, кафетериев, ресторанов быстрого питания и самообслуживания | BD14: 1000 | BN14: 1000 | BS14: 1000 | BX14: 10000 | CH14: -803000 | CM14: -793000 | DL14: 794000 | EA14: 794000
A15: 14 | B15: БСК, ООО | C15: 1025901712352 | D15: 23 | E15: Производство прочих отделочных и завершающих работ | F15: 71334 | G15: 235352 | K15: 1612770 | L15: 1883051 | N15: 80621 | P15: 194000 | AJ15: 194000 | AO15: 123000 | AP15: 46000 | AT15: 10358000 | AU15: 845000 | AV15: 2699000 | AW15: 1754000 | AX15: 2815000 | BD15: 169000 | BE15: 20000 | BF15: 1161000 | BG15: 159000 | BH15: 776000 | BN15: 10650000 | BO15: 911000 | BP15: 3860000 | BQ15: 1913000 | BR15: 3591000 | BS15: 10844000 | BT15: 911000 | BU15: 3860000 | BV15: 1913000 | BW15: 3591000 | CM15: 3811000 | CN15: 610000 | CO15: -3000000 | CP15: -8973000 | CQ15: -3528000 | DL15: 7033000 | DM15: 301000 | DN15: 6860000 | DO15: 10886000 | DP15: 7119000 | EA15: 7033000 | EB15: 301000 | EC15: 6860000 | ED15: 10886000 | EE15: 7119000 | EF15: 13019000 | EG15: 8442000 | EH15: 2278000 | EI15: 419000 | EK15: 11699000 | EL15: 8123000 | EM15: 2121000 | EN15: 652000 | EO15: 523000 | FO15: 94000 | FS15: 6203000 | FT15: 214000 | FU15: 3493000 | FV15: 3767000 | FW15: 5740000 | FX15: 5680000 | FY15: 240000 | FZ15: 47000 | GD15: 960000 | GE15: -3221000 | GF15: -3610000 | GG15: -5973000
A16: 15 | B16: БСП, ООО | C16: 1085907002697 | D16: 16 | E16: Предоставление услуг по бурению, связанному с добычей нефти, газа и газового конденсата | O16: 943343 | S16: 10892000 | T16: 1035000 | AM16: 10892000 | AN16: 1035000 | AW16: 888701000 | AX16: 9500000 | BH16: 7195000 | BQ16: 888701000 | BR16: 16695000 | BV16: 899593000 | BW16: 17730000 | CP16: 624167000 | CQ16: -318466000 | DO16: 275426000 | DP16: 335830000 | DZ16: 366000 | ED16: 275426000 | EE16: 336196000 | EI16: 12856000 | EJ16: 2197000 | EN16: 15128000 | EO16: 16468000 | FS16: 10015000 | FW16: 2479000 | FX16: 938377000 | GG16: -4751000 | GH16: -942633000
A17: 16 | B17: БУЭСМ, ООО | C17: 1026600834479 | D17: 22 | E17: Строительство жилых и нежилых зданий | F17: 4703 | G17: 92273 | K17: 3521622 | L17: 97020 | N17: 31099 | O17: 45774 | P17: 152000 | Q17: 201000 | AJ17: 152000 | AK17: 201000 | AO17: 17768000 | AP17: 86870000 | AT17: 16542000 | AU17: 20531000 | BD17: 12879000 | BI17: 2503000 | BJ17: 3972000 | BN17: 49692000 | BO17: 111712000 | BS17: 49844000 | BT17: 111914000 | BX17: 10000 | BY17: 10000 | CH17: 1993000 | CI17: 2586000 | CM17: 2003000 | CN17: 2596000 | DG17: 2700000 | DH17: 16199000 | DL17: 45141000 | DM17: 93118000 | EA17: 47841000 | EB17: 109317000 | EF17: 5397000 | EG17: 31348000 | EK17: 5536000 | EL17: 29384000 | EU17: 3018000 | FJ17: 1000 | FK17: 1399000 | FO17: 8643000 | FT17: 5051000 | FU17: 918000 | FY17: -89000 | FZ17: 16000 | GD17: 345000 | GE17: -759000
A18: 17 | B18: ВЕЛИКОЛЕНСКОЕ, ООО | C18: 1025901892455 | D18: 30 | E18: Животноводство | K18: 1053761 | M18: 1695299 | P18: 104525000 | Q18: 77248000 | R18: 67425000 | S18: 67813000 | T18: 60278000 | Z18: 60000 | AA18: 60000 | AB18: 60000 | AC18: 60000 | AD18: 60000 | AE18: 4076000 | AF18: 4076000 | AG18: 3869000 | AH18: 3869000 | AI18: 3869000 | AJ18: 108661000 | AK18: 81384000 | AL18: 71354000 | AM18: 71742000 | AN18: 64207000 | AO18: 116271000 | AP18: 77831000 | AQ18: 64182000 | AR18: 50545000 | AS18: 32418000 | AT18: 5849000 | AU18: 6299000 | AV18: 9547000 | AW18: 7711000 | AX18: 7820000 | BD18: 10000 | BE18: 2980000 | BF18: 135000 | BG18: 163000 | BH18: 66000 | BI18: 957000 | BJ18: 1387000 | BK18: 957000 | BL18: 957000 | BM18: 957000 | BN18: 123087000 | BO18: 88497000 | BP18: 74821000 | BQ18: 59376000 | BR18: 41261000 | BS18: 231748000 | BT18: 169881000 | BU18: 146175000 | BV18: 131118000 | BW18: 105468000 | BX18: 10000 | BY18: 10000 | BZ18: 10000 | CA18: 10000 | CB18: 10000 | CC18: 5522000 | CD18: 5522000 | CE18: 5522000 | CF18: 5522000 | CG18: 5522000 | CH18: 84551000 | CI18: 32797000 | CJ18: 10823000 | CK18: -8903000 | CL18: -54390000 | CM18: 138217000 | CN18: 86463000 | CO18: 64489000 | CP18: 44763000 | CQ18: -724000 | DG18: 2048000 | DH18: 2075000 | DI18: 2075000 | DJ18: 2075000 | DK18: 2075000 | DL18: 91483000 | DM18: 81343000 | DN18: 79611000 | DO18: 84280000 | DP18: 104117000 | EA18: 93531000 | EB18: 83418000 | EC18: 81686000 | ED18: 86355000 | EE18: 106192000 | EF18: 79364000 | EG18: 57568000 | EH18: 48791000 | EI18: 60449000 | EJ18: 53594000 | EK18: 134823000 | EL18: 105382000 | EM18: 76646000 | EN18: 72171000 | EO18: 91580000 | FJ18: 95000 | FK18: 27000 | FO18: 12010000 | FP18: 26833000 | FQ18: 22473000 | FR18: 3167000 | FS18: 4420000 | FT18: 11227000 | FU18: 30746000 | FV18: 15893000 | FW18: 11171000 | FX18: 11921000 | GD18: -54771000 | GE18: -51754000 | GF18: -21275000 | GG18: -19726000 | GH18: -45487000
A19: 18 | B19: ВЕМСЕЙ, ООО | C19: 1157847079940 | D19: 10 | E19: Торговля розничная одеждой в специализированных магазинах | F19: 137359 | G19: 109900 | H19: 41221 | I19: 549539 | J19: 30863 | K19: 24443877 | L19: 43222813 | M19: 37342870 | N19: 18968706 | O19: 6590111 | P19: 496000 | Q19: 432000 | AJ19: 652000 | AK19: 2923000 | AL19: 3953000 | AM19: 2938000 | AN19: 3064000 | AO19: 634520000 | AP19: 443883000 | AQ19: 71992000 | AR19: 37221000 | AS19: 29783000 | AT19: 65258000 | AU19: 209011000 | AV19: 263000000 | AW19: 257268000 | AX19: 193444000 | AY19: 2983000 | AZ19: 6130000 | BA19: 8762000 | BB19: 8661000 | BC19: 8802000 | BD19: 9170000 | BE19: 2858000 | BF19: 3558000 | BG19: 5195000 | BH19: 458000 | BI19: 39000 | BJ19: 14000 | BM19: 1045000 | BN19: 711970000 | BO19: 661896000 | BP19: 347312000 | BQ19: 308345000 | BR19: 233532000 | BS19: 712622000 | BT19: 664819000 | BU19: 351265000 | BV19: 311282000 | BW19: 236595000 | BX19: 30000 | BY19: 30000 | BZ19: 30000 | CA19: 30000 | CB19: 30000 | CH19: 40071000 | CI19: 35145000 | CJ19: 1113000 | CK19: 2763000 | CL19: 3496000 | CM19: 40101000 | CN19: 35175000 | CO19: 1143000 | CP19: 2793000 | CQ19: 3526000 | DB19: 21000 | DC19: 142000 | DF19: 15000 | DG19: 5074000 | DH19: 3427000 | DI19: 7410000 | DJ19: 33587000 | DK19: 5864000 | DL19: 667219000 | DM19: 625868000 | DN19: 342506000 | DO19: 274902000 | DP19: 227191000 | DQ19: 207000 | DR19: 207000 | DS19: 207000 | EA19: 672500000 | EB19: 629502000 | EC19: 350123000 | ED19: 308489000 | EE19: 233055000 | EF19: 314616000 | EG19: 370254000 | EH19: 185892000 | EI19: 46513000 | EJ19: 26263000 | EK19: 205525000 | EL19: 322434000 | EM19: 160555000 | EN19: 43639000 | EO19: 10704000 | EP19: 136706000 | EQ19: 154549000 | ER19: 84362000 | ES19: 38783000 | ET19: 24548000 | FJ19: 105000 | FK19: 41000 | FO19: 45294000 | FP19: 114977000 | FQ19: 273160000 | FR19: 61753000 | FS19: 23463000 | FT19: 17324000 | FU19: 14308000 | FV19: 244919000 | FW19: 21498000 | FX19: 13666000 | FY19: -29000 | FZ19: 2214000 | GA19: 1707000 | GB19: -1191000 | GC19: -91000 | GD19: -250000 | GE19: -4925000 | GF19: -33136000 | GG19: 2172000 | GH19: 731000
A20: 19 | B20: ВЕСТКРАУНД, ООО | C20: 1155958076218 | D20: 10 | E20: Строительство автомобильных дорог и автомагистралей | G20: 425990 | L20: 999989 | M20: 13694 | P20: 3482000 | Q20: 2370000 | Z20: 19000 | AA20: 19000 | AJ20: 3501000 | AK20: 2389000 | AO20: 30835000 | AT20: 44545000 | AU20: 28830000 | AW20: 87109000 | AX20: 87109000 | BD20: 49000 | BE20: 1393000 | BG20: 71000 | BN20: 75429000 | BO20: 30223000 | BQ20: 87180000 | BR20: 87109000 | BS20: 78929000 | BT20: 32611000 | BV20: 87180000 | BW20: 87109000 | CM20: 7969000 | CN20: -18724000 | CP20: -132191000 | CQ20: -132262000 | CW20: 411000 | CX20: 411000 | DB20: 411000 | DC20: 411000 | DG20: 7666000 | DH20: 12737000 | DL20: 62883000 | DM20: 38187000 | DO20: 219371000 | DP20: 219371000 | EA20: 70549000 | EB20: 50924000 | ED20: 219371000 | EE20: 219371000 | EF20: 179332000 | EG20: 35387000 | EK20: 156342000 | EL20: 80269000 | FJ20: 13604000 | FK20: 1684000 | FO20: 2785000 | FP20: 56949000 | FT20: 2754000 | FU20: 36917000 | FW20: 203000 | FY20: 7032000 | FZ20: 158000 | GD20: 2385000 | GE20: -26692000 | GG20: -203000
A21: 20 | B21: ВИБКОМ, ООО | C21: 1065904113197 | D21: 19 | E21: Деятельность ресторанов и услуги по доставке продуктов питания | Q21: 9121000 | R21: 8401000 | AK21: 9121000 | AL21: 8401000 | AO21: 1949000 | AP21: 1854000 | AQ21: 2006000 | AU21: 1051000 | AV21: 126000 | BD21: 115000 | BE21: 57000 | BF21: 15000 | BI21: 9852000 | BJ21: 1278000 | BK21: 3852000 | BN21: 11916000 | BO21: 4240000 | BP21: 5999000 | BS21: 11916000 | BT21: 13361000 | BU21: 14400000 | BX21: 10000 | BY21: 10000 | BZ21: 10000 | CH21: 10138000 | CI21: 11314000 | CJ21: 11388000 | CM21: 10148000 | CN21: 11324000 | CO21: 11398000 | CQ21: -3715000 | DG21: 1000000 | DH21: 1911000 | DI21: 3002000 | DL21: 768000 | DM21: 126000 | DP21: 3715000 | EA21: 1768000 | EB21: 2037000 | EC21: 3002000 | EE21: 3715000 | EF21: 7229000 | EG21: 10884000 | EH21: 7652000 | EK21: 8630000 | EL21: 10599000 | EM21: 7327000 | FL21: 9000 | FO21: 428000 | FP21: 1103000 | FQ21: 288000 | FT21: 64000 | FU21: 95000 | FV21: 452000 | FX21: 96000 | FY21: -72000 | FZ21: -117000 | GA21: -78000 | GD21: -1109000 | GE21: 1176000 | GF21: 74000 | GH21: -96000
A22: 21 | B22: ВЛБАНК (АО) | C22: 1063800023572 | D22: 19 | E22: Денежное посредничество прочее
A23: 22 | B23: ВНЕШПРОМБАНК, ООО | C23: 1027700514049 | D23: 30 | E23: Денежное посредничество прочее
A24: 23 | B24: ВОЛГА, ООО | C24: 5177746098844 | D24: 8 | E24: Торговля розничная большим товарным ассортиментом с преобладанием непродовольственных товаров в неспециализированных магазинах | F24: 222000 | G24: 23305756 | K24: 2031396 | L24: 11507825 | M24: 2027 | N24: 37 | P24: 1291000 | Q24: 111000 | AE24: 17000 | AF24: 1197000 | AJ24: 3870000 | AK24: 115273000 | AM24: 1100000 | AO24: 664425000 | AP24: 423415000 | AR24: 5000 | AS24: 5000 | AT24: 1922091000 | AU24: 1621127000 | AW24: 24000 | AY24: 2240000 | AZ24: 2486000 | BD24: 366000 | BE24: 5550000 | BG24: 101000 | BH24: 107000 | BJ24: 28602000 | BN24: 2625770000 | BO24: 2086572000 | BQ24: 130000 | BR24: 112000 | BS24: 2629640000 | BT24: 2201844000 | BV24: 1230000 | BW24: 112000 | BX24: 20000 | BY24: 20000 | CA24: 20000 | CB24: 20000 | CH24: 37932000 | CI24: -226930000 | CK24: -2826678000 | CL24: -2836238000 | CM24: 37952000 | CN24: -226910000 | CP24: -2826658000 | CQ24: -2836218000 | DB24: 137000 | DC24: 22000 | DG24: 439829000 | DH24: 489646000 | DL24: 2147151000 | DM24: 1928670000 | DO24: 2827888000 | DP24: 2836330000 | EA24: 2591552000 | EB24: 2428732000 | ED24: 2827888000 | EE24: 2836330000 | EF24: 1805986000 | EG24: 640098000 | EI24: 92000 | EJ24: 149000 | EK24: 1356738000 | EL24: 503785000 | EN24: 1420000 | EO24: 8518000 | EP24: 407832000 | EQ24: 281605000 | FE24: 190000 | FF24: 246000 | FJ24: 24683000 | FK24: 49817000 | FO24: 204103000 | FP24: 40770000 | FR24: 2000000 | FT24: 175431000 | FU24: 139440000 | FW24: 901000 | FX24: 1191000 | FY24: -9583000 | FZ24: 52606000 | GD24: 36012000 | GE24: -235060000 | GG24: -229000 | GH24: -9560000
A25: 24 | B25: ВОСТОК, ООО СК | C25: 1115904009154 | D25: 14 | E25: Консультирование по вопросам коммерческой деятельности и управления | G25: 2092 | H25: 95094 | K25: 10920016 | P25: 769000 | Q25: 769000 | R25: 769000 | AJ25: 808000 | AK25: 808000 | AL25: 808000 | AT25: 21377000 | AU25: 21377000 | AV25: 1489000 | AW25: 1489000 | AX25: 1489000 | BI25: 27000 | BJ25: 27000 | BK25: 27000 | BN25: 21404000 | BO25: 21404000 | BP25: 1516000 | BQ25: 1489000 | BR25: 1489000 | BS25: 22212000 | BT25: 22212000 | BU25: 2324000 | BV25: 1489000 | BW25: 1489000 | BX25: 10000 | BY25: 10000 | BZ25: 10000 | CA25: 10000 | CB25: 10000 | CH25: -30424000 | CI25: -30424000 | CJ25: -42835000 | CK25: -42835000 | CL25: -42835000 | CM25: -30414000 | CN25: -30414000 | CO25: -42825000 | CP25: -42825000 | CQ25: -42825000 | CW25: 104000 | CX25: 104000 | CY25: 104000 | DB25: 104000 | DC25: 104000 | DD25: 104000 | DG25: 346000 | DH25: 346000 | DL25: 52029000 | DM25: 52029000 | DN25: 44898000 | DO25: 44314000 | DP25: 44314000 | EA25: 52522000 | EB25: 52522000 | EC25: 45045000 | ED25: 44314000 | EE25: 44314000 | EF25: 86481000 | EK25: 93453000 | EU25: 12684000 | FO25: 7971000 | FT25: 47483000 | GD25: -59240000
A26: 25 | B26: ГАЗПРОМ СПЕЦГАЗАВТОТРАНС, ПАО | C26: 1021801586047 | D26: 32 | E26: Строительство инженерных коммуникаций для водоснабжения и водоотведения, газоснабжения | O26: 546090 | P26: 367420000 | Q26: 353701000 | R26: 298856000 | S26: 224123000 | T26: 112842000 | Z26: 6125000 | AA26: 8858000 | AB26: 4736000 | AC26: 4673000 | AD26: 4119000 | AE26: 3000 | AJ26: 885015000 | AK26: 891352000 | AL26: 816537000 | AM26: 675994000 | AN26: 516609000 | AO26: 439645000 | AP26: 445688000 | AQ26: 443054000 | AR26: 435788000 | AS26: 412956000 | AT26: 1228777000 | AU26: 1265599000 | AV26: 1362357000 | AW26: 1798613000 | AX26: 1660245000 | BD26: 55117000 | BE26: 283000 | BF26: 9733000 | BG26: 4162000 | BH26: 2579000 | BI26: 4979000 | BJ26: 4980000 | BK26: 4980000 | BL26: 4980000 | BM26: 4979000 | BN26: 1730283000 | BO26: 1718310000 | BP26: 1821877000 | BQ26: 2245295000 | BR26: 2080776000 | BS26: 2615298000 | BT26: 2609662000 | BU26: 2638414000 | BV26: 2921289000 | BW26: 2597385000 | BX26: 977000 | BY26: 977000 | BZ26: 977000 | CA26: 977000 | CB26: 977000 | CC26: 425740000 | CD26: 417614000 | CE26: 326775000 | CF26: 286040000 | CG26: 163399000 | CH26: -2445078000 | CI26: -2508018000 | CJ26: -2800056000 | CK26: -2344725000 | CL26: -2000784000 | CM26: -1472257000 | CN26: -1543323000 | CO26: -1926200000 | CP26: -1511604000 | CQ26: -1290304000 | DB26: 36318000 | DC26: 36604000 | DD26: 28904000 | DE26: 23238000 | DF26: 16353000 | DG26: 297268000 | DH26: 307908000 | DI26: 318548000 | DJ26: 329188000 | DK26: 270624000 | DL26: 3734172000 | DM26: 3791148000 | DN26: 4201778000 | DO26: 4064303000 | DP26: 3585076000 | EA26: 4051237000 | EB26: 4116381000 | EC26: 4535710000 | ED26: 4409655000 | EE26: 3871336000 | EF26: 319294000 | EG26: 119395000 | EH26: 171801000 | EI26: 30107000 | EJ26: 6124000 | EK26: 421764000 | EL26: 158353000 | EM26: 95185000 | EN26: 75580000 | EU26: 81594000 | EV26: 66180000 | EW26: 69427000 | EX26: 51367000 | EY26: 121350000 | EZ26: 279000 | FA26: 230000 | FB26: 934000 | FJ26: 10640000 | FK26: 10640000 | FL26: 10640000 | FM26: 10640000 | FO26: 50773000 | FP26: 39541000 | FQ26: 322160000 | FR26: 908756000 | FS26: 583635000 | FT26: 26081000 | FU26: 12102000 | FV26: 220469000 | FW26: 260369000 | FX26: 139882000 | FY26: 34254000 | FZ26: 17044000 | GA26: -20071000 | GB26: -126297000 | GC26: -78886000 | GD26: -307791000 | GE26: -71066000 | GF26: -382876000 | GG26: 414586000 | GH26: 226364000
A27: 26 | B27: ГЕОСТРОЙ, ООО | C27: 1037739931008 | D27: 21 | E27: Создание геодезической, нивелирной, гравиметрической сетей | F27: 544 | G27: 258985 | H27: 181 | K27: 1659456 | L27: 17058842 | M27: 1101006 | Q27: 31840000 | R27: 4113000 | S27: 2211000 | AK27: 31840000 | AL27: 4113000 | AM27: 2211000 | AU27: 420000 | AV27: 33866000 | AW27: 6164000 | AX27: 79710000 | BE27: 81000 | BF27: 4143000 | BG27: 5384000 | BH27: 6028000 | BO27: 501000 | BP27: 38009000 | BQ27: 11548000 | BR27: 85738000 | BT27: 32341000 | BU27: 42121000 | BV27: 13758000 | BW27: 85738000 | BY27: 10000 | BZ27: 10000 | CA27: 10000 | CB27: 10000 | CI27: -57662000 | CJ27: -47274000 | CK27: -54707000 | CL27: 13300000 | CN27: -57652000 | CO27: -47264000 | CP27: -54697000 | CQ27: 13310000 | DM27: 89993000 | DN27: 89385000 | DO27: 68455000 | DP27: 72428000 | EB27: 89993000 | EC27: 89385000 | ED27: 68455000 | EE27: 72428000
A28: 27 | B28: ГИДРОТЕПЛОСТРОЙ, ООО | C28: 1165958100703 | D28: 9 | E28: Строительство жилых и нежилых зданий | I28: 273659 | J28: 27220 | K28: 5852 | L28: 6113 | N28: 536 | O28: 72578 | P28: 3628000 | Q28: 2267000 | R28: 907000 | AJ28: 3670000 | AK28: 2303000 | AL28: 937000 | AO28: 2342000 | AP28: 5000 | AT28: 2535000 | AU28: 3869000 | AV28: 3142000 | BI28: 128000 | BN28: 5303000 | BO28: 3937000 | BP28: 3205000 | BS28: 8973000 | BT28: 6240000 | BU28: 4142000 | BX28: 10000 | BY28: 10000 | BZ28: 10000 | CH28: -3837000 | CI28: -5321000 | CJ28: -7417000 | CM28: -3827000 | CN28: -5311000 | CO28: -7407000 | CP28: -7671000 | CR28: 1747000 | CS28: 2312000 | CT28: 2312000 | DB28: 1747000 | DC28: 2312000 | DD28: 2312000 | DL28: 11053000 | DM28: 9239000 | DN28: 9237000 | DO28: 7671000 | EA28: 11053000 | EB28: 9239000 | EC28: 9237000 | ED28: 7671000 | EF28: 1461000 | EG28: 2327000 | EK28: 1119000 | EL28: 2336000 | EM28: 1730000 | EP28: 2000 | EU28: 2372000 | EV28: 1470000 | FO28: 2549000 | FT28: 922000 | FV28: 366000 | FW28: 264000 | FY28: -18000 | FZ28: -5000 | GD28: -423000 | GE28: -1484000 | GF28: -2096000 | GG28: -264000
A29: 28 | B29: ГЛАСИС ПЕРМЬ, ООО | C29: 1085902009313 | D29: 17 | E29: Торговля автомобильными деталями, узлами и принадлежностями | P29: 1098000 | Q29: 751000 | R29: 73000 | AJ29: 1098000 | AK29: 751000 | AL29: 73000 | AQ29: 150000 | AT29: 6911000 | AU29: 11908000 | AV29: 13847000 | BD29: 138000 | BE29: 498000 | BF29: 365000 | BN29: 7049000 | BO29: 12406000 | BP29: 14362000 | BS29: 8147000 | BT29: 13157000 | BU29: 14435000 | CM29: 1795000 | CN29: 3503000 | CO29: 5482000 | CR29: 98000 | CS29: 1500000 | CT29: 3349000 | DB29: 98000 | DC29: 1500000 | DD29: 3349000 | DH29: 5061000 | DI29: 2889000 | DL29: 6254000 | DM29: 3093000 | DN29: 2715000 | EA29: 6254000 | EB29: 8154000 | EC29: 5604000 | EF29: 8464000 | EG29: 13152000 | EH29: 7768000 | EK29: 7205000 | EL29: 9149000 | EM29: 5604000 | FK29: 285000 | FL29: 175000 | FO29: 3044000 | FP29: 255000 | FQ29: 150000 | FT29: 2238000 | FU29: 1176000 | FV29: 675000 | FY29: 565000 | FZ29: 1089000 | GA29: 212000 | GD29: 1500000 | GE29: 1708000 | GF29: 1252000
A30: 29 | B30: ГОДОВАЛОВ, ООО | C30: 1065908029615 | D30: 18 | E30: Торговля оптовая фармацевтической продукцией | P30: 72041000 | Q30: 52973000 | R30: 89410000 | S30: 12870000 | T30: 12870000 | Z30: 878761000 | AA30: 899286000 | AB30: 920895000 | AC30: 67938000 | AD30: 71677000 | AJ30: 950802000 | AK30: 952259000 | AL30: 1010305000 | AM30: 80808000 | AN30: 84547000 | AO30: 6148227000 | AP30: 5999859000 | AQ30: 6028868000 | AR30: 15816000 | AS30: 15816000 | AT30: 2673379000 | AU30: 3233937000 | AV30: 5335774000 | AW30: 5062119000 | AX30: 5038140000 | BD30: 3402000 | BE30: 1892000 | BF30: 79059000 | BG30: 4015000 | BH30: 610000 | BL30: 187000 | BM30: 143000 | BN30: 8834501000 | BO30: 9272043000 | BP30: 11529586000 | BQ30: 5090073000 | BR30: 5062645000 | BS30: 9785303000 | BT30: 10224302000 | BU30: 12539891000 | BV30: 5170881000 | BW30: 5147192000 | BX30: 200000 | BY30: 200000 | BZ30: 200000 | CA30: 200000 | CB30: 200000 | CH30: 1230753000 | CI30: 1428233000 | CJ30: 1636796000 | CK30: -3501497000 | CL30: -3518048000 | CM30: 1230953000 | CN30: 1428433000 | CO30: 1636996000 | CP30: -3501297000 | CQ30: -3517848000 | CR30: 3302000 | CS30: 1849000 | CT30: 1870000 | CU30: 4086864000 | CV30: 4086684000 | DB30: 3302000 | DC30: 1849000 | DD30: 1870000 | DE30: 4086864000 | DF30: 4086684000 | DG30: 2774000000 | DH30: 3304063000 | DI30: 4452075000 | DL30: 5777048000 | DM30: 5489957000 | DN30: 6448950000 | DO30: 4585314000 | DP30: 4578356000 | EA30: 8551048000 | EB30: 8794020000 | EC30: 10901025000 | ED30: 4585314000 | EE30: 4578356000 | EF30: 20322825000 | EG30: 17415422000 | EH30: 17414894000 | EI30: 7384425000 | EJ30: 242000 | EK30: 19891083000 | EL30: 16919131000 | EM30: 16655535000 | EN30: 7323049000 | EP30: 889453000 | EQ30: 794697000 | ER30: 776373000 | ES30: 558244000 | ET30: 20864000 | FE30: 22173000 | FF30: 21191000 | FG30: 21936000 | FH30: 4791000 | FI30: 3739000 | FJ30: 237808000 | FK30: 277905000 | FL30: 539048000 | FM30: 269187000 | FO30: 1193766000 | FP30: 1166975000 | FQ30: 1028320000 | FR30: 507121000 | FS30: 1115000 | FT30: 268982000 | FU30: 360848000 | FV30: 245209000 | FW30: 729924000 | FX30: 781000 | FY30: -65844000 | FZ30: -53527000 | GA30: -49999000 | GD30: 185594000 | GE30: 197480000 | GF30: 198986000 | GG30: -5138293000 | GH30: -16549000
A31: 30 | B31: ГОРНОЗАВОДСК-ВОДОСНАБЖЕНИЕ, ООО | C31: 1195958008070 | D31: 6 | E31: Забор, очистка и распределение воды | F31: 72154 | K31: 2156725 | L31: 213320 | M31: 32994 | P31: 693000 | Q31: 296000 | AJ31: 1433000 | AK31: 296000 | AO31: 327000 | AP31: 362000 | AQ31: 122000 | AR31: 122000 | AS31: 12000 | AT31: 7914000 | AU31: 10762000 | AV31: 7437000 | AW31: 7919000 | AX31: 4165000 | BD31: 693000 | BE31: 315000 | BF31: 1649000 | BG31: 434000 | BH31: 48000 | BI31: 101000 | BJ31: 54000 | BN31: 9034000 | BO31: 11493000 | BP31: 9208000 | BQ31: 8475000 | BR31: 4225000 | BS31: 10467000 | BT31: 11789000 | BU31: 9208000 | BV31: 8475000 | BW31: 4225000 | BX31: 10000 | BY31: 10000 | BZ31: 10000 | CA31: 10000 | CB31: 10000 | CH31: -2958000 | CI31: -7802000 | CJ31: -8074000 | CK31: -10126000 | CL31: -14376000 | CM31: -2948000 | CN31: -7792000 | CO31: -8064000 | CP31: -10116000 | CQ31: -14366000 | CW31: 535000 | CX31: 258000 | DB31: 535000 | DC31: 258000 | DL31: 12467000 | DM31: 19187000 | DN31: 17272000 | DO31: 18591000 | DP31: 18591000 | DW31: 136000 | EA31: 12879000 | EB31: 19323000 | EC31: 17272000 | ED31: 18591000 | EE31: 18591000 | EF31: 41701000 | EG31: 21913000 | EH31: 6326000 | EK31: 43102000 | EL31: 26708000 | EM31: 6481000 | EV31: 438000 | EW31: 524000 | EX31: 533000 | FO31: 335000 | FP31: 369000 | FQ31: 482000 | FR31: 507000 | FS31: 2777000 | FT31: 137000 | FU31: 195000 | FV31: 75000 | FX31: 7027000 | FY31: -258000 | GD31: -962000 | GE31: -4844000 | GF31: -272000 | GG31: -26000 | GH31: -4250000
A32: 31 | B32: ГОРЫ, ООО | C32: 1055907103603 | D32: 19 | E32: Животноводство | H32: 82829 | J32: 29502 | K32: 1376647 | L32: 195199 | M32: 1072090 | N32: 196029 | P32: 42270000 | Q32: 36546000 | R32: 81670000 | S32: 39714000 | T32: 38376000 | Z32: 33000 | AJ32: 42303000 | AK32: 36546000 | AL32: 81670000 | AM32: 39714000 | AN32: 38376000 | AO32: 47024000 | AP32: 22054000 | AQ32: 940000 | AR32: 3624000 | AS32: 3624000 | AT32: 138488000 | AU32: 142099000 | AW32: 115116000 | AX32: 115116000 | AY32: 23130000 | AZ32: 23257000 | BD32: 4000 | BE32: 517000 | BF32: 841000 | BG32: 87000 | BI32: 15000 | BJ32: 32000 | BN32: 208887000 | BO32: 187960000 | BP32: 1781000 | BQ32: 118827000 | BR32: 118740000 | BS32: 251190000 | BT32: 224505000 | BU32: 83451000 | BV32: 158541000 | BW32: 157116000 | BX32: 18460000 | BY32: 18460000 | BZ32: 18460000 | CH32: 87764000 | CI32: 65475000 | CJ32: -251841000 | CM32: 106224000 | CN32: 83935000 | CO32: -233381000 | CP32: -158290000 | CQ32: -158172000 | CR32: 1000 | CS32: 1000 | DB32: 1000 | DC32: 1000 | DG32: 33765000 | DH32: 34274000 | DL32: 111199000 | DM32: 106295000 | DN32: 316749000 | DO32: 316749000 | DP32: 315206000 | DX32: 83000 | DY32: 82000 | DZ32: 82000 | EA32: 144964000 | EB32: 140569000 | EC32: 316832000 | ED32: 316831000 | EE32: 315288000 | EF32: 58846000 | EG32: 66305000 | EH32: 28485000 | EI32: 1200000 | EJ32: 1338000 | EK32: 62781000 | EL32: 79636000 | EM32: 20653000 | EV32: 4780000 | EW32: 9134000 | FJ32: 859000 | FK32: 1326000 | FO32: 7879000 | FP32: 8912000 | FQ32: 2014000 | FT32: 10132000 | FU32: 11753000 | FV32: 2316000 | FW32: 1844000 | FX32: 1190000 | GA32: -83000 | GC32: 30000 | GD32: -7047000 | GE32: -22278000 | GF32: -1687000 | GG32: -644000 | GH32: 118000
A33: 32 | B33: ГОСЗЕМКАДАСТРСЪЕМКА -ВИСХАГИ, АО | C33: 1127747072023 | D33: 31 | E33: Деятельность геодезическая и картографическая | I33: 3010667 | J33: 70053348 | N33: 34896060 | O33: 2141707 | P33: 486406000 | Q33: 452039000 | R33: 419622000 | S33: 10641000 | T33: 6033000 | AJ33: 558509000 | AK33: 524142000 | AL33: 419622000 | AM33: 10641000 | AN33: 6033000 | AO33: 45067000 | AP33: 1986000 | AQ33: 1857000 | AT33: 92211000 | AU33: 82000000 | AV33: 18678000 | AW33: 1157000 | AX33: 6088000 | BD33: 1843000 | BE33: 161000 | BG33: 152000 | BH33: 4071000 | BI33: 111132000 | BJ33: 116988000 | BL33: 313810000 | BM33: 26264000 | BN33: 250253000 | BO33: 201135000 | BP33: 20535000 | BQ33: 315119000 | BR33: 36423000 | BS33: 808762000 | BT33: 725277000 | BU33: 440157000 | BV33: 325760000 | BW33: 42456000 | BX33: 1214571000 | BY33: 1214571000 | BZ33: 1214571000 | CA33: 1214571000 | CB33: 1214571000 | CH33: -1819547000 | CI33: -1817304000 | CJ33: -1816019000 | CK33: -1752629000 | CL33: -1783438000 | CM33: -601939000 | CN33: -599696000 | CO33: -598411000 | CP33: -535021000 | CQ33: -565830000 | CR33: 171000 | CS33: 171000 | CT33: 273330000 | CU33: 309630000 | CV33: 277487000 | DB33: 288000 | DC33: 288000 | DD33: 273447000 | DE33: 309630000 | DF33: 277487000 | DG33: 273158000 | DH33: 273158000 | DL33: 1136958000 | DM33: 1051230000 | DN33: 763945000 | DO33: 547255000 | DP33: 326462000 | DQ33: 11000 | DR33: 11000 | EA33: 1410413000 | EB33: 1324685000 | EC33: 765121000 | ED33: 551151000 | EE33: 330799000 | EF33: 167000 | EG33: 28080000 | EH33: 16390000 | EI33: 15261000 | EJ33: 10909000 | EL33: 36527000 | EU33: 83644000 | EV33: 73851000 | EW33: 51431000 | EX33: 35416000 | EY33: 26182000 | FE33: 38000 | FO33: 57557000 | FP33: 105466000 | FQ33: 376846000 | FR33: 304201000 | FS33: 87249000 | FT33: 39796000 | FU33: 20364000 | FV33: 340241000 | FW33: 100130000 | FX33: 25609000 | FZ33: -561000 | GB33: -43612000 | GC33: -10742000 | GD33: -108176000 | GE33: 2243000 | GF33: 1285000 | GG33: 140304000 | GH33: 35625000
A34: 33 | B34: ГРУППА КОМПАНИЙ СВЯЗНОЙ, АО | C34: 1047796913735 | D34: 20 | E34: Деятельность агентов по оптовой торговле радио- и телеаппаратурой, техническими носителями информации | K34: 652000 | L34: 722855 | M34: 1334921 | N34: 165861 | O34: 397232 | Z34: 159856000 | AA34: 155855000 | AB34: 155855000 | AG34: 79000 | AH34: 71000 | AI34: 65000 | AJ34: 159883000 | AK34: 155861000 | AL34: 156517000 | AM34: 3535000 | AN34: 7059000 | AT34: 1030190000 | AU34: 2403716000 | AV34: 2536844000 | AW34: 1557753000 | AX34: 1557972000 | BD34: 11692000 | BE34: 2784000 | BF34: 44000 | BG34: 4000 | BH34: 334000 | BL34: 3000 | BN34: 1041882000 | BO34: 2406500000 | BP34: 2536888000 | BQ34: 1557760000 | BR34: 1558350000 | BS34: 1201765000 | BT34: 2562361000 | BU34: 2693405000 | BV34: 1561295000 | BW34: 1565409000 | BX34: 1105000000 | BY34: 1105000000 | BZ34: 1105000000 | CA34: 1105000000 | CB34: 1105000000 | CH34: -493911000 | CI34: -504832000 | CJ34: -507192000 | CK34: -3564012000 | CL34: -1094041000 | CM34: 611089000 | CN34: 600168000 | CO34: 597808000 | CP34: -2459012000 | CQ34: 10959000 | CT34: 2622000 | CU34: 8381000 | CV34: 10307000 | DD34: 2622000 | DE34: 8497000 | DF34: 10528000 | DJ34: 7278000 | DK34: 205940000 | DL34: 590676000 | DM34: 1962193000 | DN34: 2092975000 | DO34: 4004532000 | DP34: 1337982000 | EA34: 590676000 | EB34: 1962193000 | EC34: 2092975000 | ED34: 4011810000 | EE34: 1543922000 | EF34: 4149000 | EG34: 3297000 | EH34: 2731000 | EI34: 2804000 | EJ34: 2042000 | EK34: 16493000 | EL34: 14374000 | EM34: 10429000 | EN34: 16013000 | EY34: 640000 | FA34: 10000 | FE34: 1090000 | FF34: 420000 | FG34: 234000 | FH34: 11000 | FL34: 22000 | FM34: 1007000 | FN34: 11968000 | FO34: 1068000 | FP34: 70000 | FQ34: 5914000 | FR34: 1007000 | FS34: 2520937000 | FT34: 433000 | FU34: 341000 | FV34: 1368000 | FW34: 3046386000 | FX34: 43826000 | FY34: -4000 | FZ34: -3000 | GA34: 583000 | GB34: 2764000 | GC34: 2638000 | GD34: -10623000 | GE34: -10921000 | GF34: -2360000 | GG34: -3056820000 | GH34: 2469183000
A35: 34 | B35: ГУБАХАХЛЕБ, ООО | C35: 1025901778660 | D35: 32 | E35: Производство хлеба и мучных кондитерских изделий, тортов и пирожных недлительного хранения | H35: 33535 | I35: 1272361 | K35: 9225063 | L35: 9920667 | M35: 10363824 | N35: 12256848 | O35: 12540922 | P35: 17859000 | Q35: 18951000 | R35: 18439000 | S35: 7032000 | T35: 5000000 | AJ35: 19166000 | AK35: 20194000 | AL35: 19825000 | AM35: 8652000 | AN35: 13646000 | AO35: 17782000 | AP35: 23633000 | AQ35: 21195000 | AR35: 17384000 | AS35: 6572000 | AT35: 15230000 | AU35: 17533000 | AV35: 17823000 | AW35: 21236000 | AX35: 9860000 | BB35: 11840000 | BD35: 680000 | BE35: 531000 | BF35: 952000 | BG35: 4503000 | BH35: 5000 | BI35: 62000 | BJ35: 992000 | BK35: 1374000 | BL35: 1416000 | BM35: 1536000 | BN35: 33754000 | BO35: 42701000 | BP35: 41353000 | BQ35: 56517000 | BR35: 18023000 | BS35: 52920000 | BT35: 62895000 | BU35: 61178000 | BV35: 65169000 | BW35: 31669000 | BX35: 109000 | BY35: 109000 | BZ35: 109000 | CA35: 109000 | CB35: 109000 | CH35: 13319000 | CI35: 7503000 | CJ35: 11112000 | CK35: 20728000 | CL35: -10709000 | CM35: 13480000 | CN35: 7664000 | CO35: 19773000 | CP35: 20889000 | CQ35: -10548000 | CS35: 1000000 | CT35: 1000000 | DB35: 1251000 | DC35: 2251000 | DD35: 1251000 | DE35: -98000 | DG35: 17133000 | DH35: 21535000 | DI35: 20350000 | DK35: 600000 | DL35: 16644000 | DM35: 30308000 | DN35: 18827000 | DO35: 37492000 | DP35: 41617000 | DV35: 2274000 | DY35: 6886000 | EA35: 38189000 | EB35: 52980000 | EC35: 40154000 | ED35: 44378000 | EE35: 42217000 | EF35: 216598000 | EG35: 214968000 | EH35: 250085000 | EI35: 225730000 | EJ35: 196323000 | EK35: 157762000 | EL35: 156090000 | EM35: 168221000 | EN35: 151356000 | EO35: 127467000 | EP35: 50217000 | EQ35: 48146000 | ER35: 65227000 | ES35: 78154000 | ET35: 90199000 | EU35: 17516000 | EV35: 17876000 | EW35: 19346000 | EX35: 19516000 | EY35: 19123000 | FG35: 1676000 | FH35: 70000 | FJ35: 440000 | FK35: 402000 | FL35: 491000 | FO35: 208000 | FP35: 89000 | FQ35: 715000 | FR35: 37618000 | FS35: 5492000 | FT35: 652000 | FU35: 754000 | FV35: 2903000 | FW35: 13624000 | FX35: 1207000 | GA35: 463000 | GB35: -370000 | GC35: 7491000 | GD35: -9781000 | GE35: -8211000 | GF35: -3249000 | GG35: 398000 | GH35: -28690000
A36: 35 | B36: ГЭКОМ, ООО | C36: 1145958052371 | D36: 11 | E36: Производство пара и горячей воды (тепловой энергии) | F36: 2035788 | K36: 4131155 | L36: 1579268 | M36: 55237 | N36: 972978 | P36: 247619000 | Q36: 191808000 | R36: 139776000 | S36: 85782000 | T36: 18233000 | AE36: 33000 | AJ36: 263700000 | AK36: 235144000 | AL36: 214133000 | AM36: 174215000 | AN36: 159813000 | AO36: 1349000 | AP36: 6232000 | AQ36: 9154000 | AR36: 9551000 | AS36: 12243000 | AT36: 72924000 | AU36: 66020000 | AV36: 82965000 | AW36: 88021000 | AX36: 104238000 | BD36: 3456000 | BE36: 45000 | BF36: 451000 | BG36: 2317000 | BH36: 911000 | BI36: 37871000 | BJ36: 26517000 | BK36: 15063000 | BL36: 5207000 | BM36: 3070000 | BN36: 121042000 | BO36: 108948000 | BP36: 114679000 | BQ36: 117507000 | BR36: 123157000 | BS36: 384741000 | BT36: 344092000 | BU36: 328812000 | BV36: 291722000 | BW36: 282970000 | BX36: 20000 | BY36: 20000 | BZ36: 20000 | CA36: 20000 | CB36: 20000 | CH36: -44549000 | CI36: -147258000 | CJ36: -265903000 | CK36: -334990000 | CL36: -430391000 | CM36: -44529000 | CN36: -147238000 | CO36: -265883000 | CP36: -334970000 | CQ36: -430371000 | CW36: 209070000 | CX36: 138362000 | CY36: 69876000 | CZ36: 12514000 | DB36: 212195000 | DC36: 143281000 | DD36: 76325000 | DE36: 18331000 | DF36: 960000 | DG36: 60220000 | DH36: 49690000 | DI36: 50603000 | DJ36: 53670000 | DK36: 56738000 | DL36: 156856000 | DM36: 298359000 | DN36: 467767000 | DO36: 554691000 | DP36: 655643000 | EA36: 217076000 | EB36: 348049000 | EC36: 518370000 | ED36: 608361000 | EE36: 712381000 | EF36: 244739000 | EG36: 255891000 | EH36: 258582000 | EI36: 307611000 | EJ36: 324873000 | EK36: 274263000 | EL36: 308378000 | EM36: 326204000 | EN36: 339553000 | EO36: 347822000 | EU36: 33392000 | EV36: 41399000 | EW36: 47627000 | EX36: 27723000 | EY36: 26732000 | FE36: 2000 | FJ36: 2524000 | FK36: 3724000 | FL36: 3095000 | FM36: 3068000 | FN36: 3068000 | FO36: 2398000 | FP36: 10691000 | FQ36: 28236000 | FR36: 29873000 | FS36: 30007000 | FT36: 2600000 | FU36: 41244000 | FV36: 56149000 | FW36: 50585000 | FX36: 133445000 | FY36: 12932000 | FZ36: 25489000 | GA36: 29441000 | GB36: 14384000 | GC36: 58003000 | GD36: -52709000 | GE36: -102684000 | GF36: -116829000 | GG36: -69061000 | GH36: -98184000
A37: 36 | B37: ДАРХАН-РЭЙЛ, ООО | C37: 1195958007893 | D37: 6 | E37: Транспортная обработка грузов | F37: 1723843 | G37: 1260939 | I37: 616096 | J37: 274662 | K37: 7406228 | L37: 12603288 | M37: 8634950 | N37: 12941598 | O37: 4755802 | P37: 29698000 | Q37: 51507000 | R37: 34104000 | S37: 39432000 | T37: 133332000 | AB37: 3000 | AJ37: 29698000 | AK37: 51507000 | AL37: 34107000 | AM37: 39432000 | AN37: 133332000 | AO37: 505000 | AP37: 104000 | AQ37: 94000 | AR37: 48000 | AS37: 210000 | AT37: 12233000 | AU37: 13023000 | AV37: 20933000 | AW37: 24929000 | AX37: 24759000 | BD37: 277000 | BE37: 265000 | BF37: 373000 | BG37: 75000 | BH37: 893000 | BI37: 3534000 | BJ37: 7465000 | BK37: 772000 | BL37: 224000 | BM37: 67000 | BN37: 16575000 | BO37: 20868000 | BP37: 22172000 | BQ37: 25276000 | BR37: 25929000 | BS37: 46273000 | BT37: 72375000 | BU37: 56279000 | BV37: 64708000 | BW37: 159261000 | BX37: 300000 | BY37: 750000 | BZ37: 750000 | CA37: 750000 | CB37: 750000 | CH37: 5348000 | CI37: -140000 | CJ37: -7968000 | CK37: -5172000 | CL37: 9954000 | CM37: 5648000 | CN37: 610000 | CO37: -7218000 | CP37: -4422000 | CQ37: 10704000 | CV37: 9387000 | CW37: 16576000 | CX37: 43844000 | CY37: 30944000 | CZ37: 30519000 | DA37: 125891000 | DB37: 16576000 | DC37: 43844000 | DD37: 30944000 | DE37: 30519000 | DF37: 135278000 | DG37: 14395000 | DH37: 19196000 | DI37: 16301000 | DJ37: 17438000 | DK37: 5291000 | DL37: 9652000 | DM37: 8726000 | DN37: 15209000 | DO37: 19488000 | DP37: 6303000 | EA37: 24048000 | EB37: 27921000 | EC37: 32553000 | ED37: 38611000 | EE37: 13279000 | EF37: 132408000 | EG37: 127412000 | EH37: 125394000 | EI37: 107752000 | EJ37: 147259000 | EK37: 89138000 | EL37: 97109000 | EM37: 106792000 | EN37: 90610000 | EO37: 117854000 | EU37: 29341000 | EV37: 33830000 | EW37: 16114000 | EX37: 13149000 | EY37: 24971000 | FH37: 108000 | FJ37: 963000 | FK37: 1175000 | FL37: 1323000 | FM37: 2638000 | FN37: 1982000 | FO37: 11000 | FP37: 5139000 | FQ37: 7931000 | FR37: 2932000 | FS37: 20041000 | FT37: 1312000 | FU37: 5942000 | FV37: 17064000 | FW37: 6916000 | FX37: 5767000 | FY37: -1783000 | GB37: -275000 | GC37: -1677000 | GD37: 9882000 | GE37: -5505000 | GF37: -7968000 | GG37: -2796000 | GH37: 15049000
A38: 37 | B38: ДЕРЖАВА, ООО | C38: 1125948000870 | D38: 13 | E38: Деятельность сухопутного пассажирского транспорта: перевозки пассажиров в городском и пригородном сообщении | F38: 3564 | G38: 202585 | K38: 3621 | L38: 56155 | P38: 35544000 | AJ38: 35544000 | AO38: 569000 | AT38: 7337000 | AY38: 480000 | BD38: 1000 | BI38: 4408000 | BN38: 13730000 | BS38: 49274000 | BX38: 10000 | CC38: 10694000 | CH38: 97000 | CM38: 10801000 | CR38: 873000 | CW38: 25086000 | DB38: 25959000 | DG38: 1000 | DL38: 12513000 | EA38: 12514000 | EF38: 19487000 | EK38: 19039000 | FO38: 1885000 | FT38: 1811000 | FY38: -27000 | GD38: 495000
A39: 38 | B39: ДИЛ-БАНК (ООО) | C39: 1027739007218 | D39: 23 | E39: Денежное посредничество прочее
A40: 39 | B40: ДОМ НА НОРИЛЬСКОЙ, ЖСК | C40: 1155958079023 | D40: 10 | E40: Управление эксплуатацией жилого фонда за вознаграждение или на договорной основе | Q40: 39744000 | R40: 39744000 | AK40: 39744000 | AL40: 39744000 | AO40: 34616000 | AT40: 13496000 | AU40: 13496000 | AV40: 12511000 | AW40: 12511000 | AX40: 12511000 | BN40: 48112000 | BO40: 13496000 | BP40: 12511000 | BQ40: 12511000 | BR40: 12511000 | BS40: 48112000 | BT40: 53240000 | BU40: 52255000 | BV40: 12511000 | BW40: 12511000 | CD40: 5128000 | CH40: -87698000 | CI40: -83796000 | CJ40: -221452000 | CK40: -261792000 | CL40: -261792000 | CM40: 41558000 | CN40: 48298000 | CO40: 50432000 | CP40: 10095000 | CQ40: 9801000 | DL40: 6554000 | DM40: 4563000 | DW40: 379000 | DX40: 1823000 | DY40: 2416000 | DZ40: 2710000 | EA40: 6554000 | EB40: 4942000 | EC40: 1823000 | ED40: 2416000 | EE40: 2710000 | FP40: 3902000 | FV40: 144918000 | FW40: 40340000 | GE40: 3902000 | GF40: -144918000 | GG40: -40340000
A41: 40 | B41: ДОМКОМ, ООО УК | C41: 1065906034897 | D41: 18 | E41: Управление эксплуатацией жилого фонда за вознаграждение или на договорной основе | F41: 213023 | G41: 361469 | I41: 82484 | J41: 78307 | K41: 21868779 | L41: 6229481 | M41: 1882441 | O41: 53441 | AO41: 2000 | AP41: 14000 | AT41: 50798000 | AU41: 62549000 | AV41: 46980000 | AW41: 34234000 | AX41: 26050000 | BD41: 37003000 | BE41: 131000 | BF41: 519000 | BG41: 488000 | BH41: 1301000 | BN41: 87803000 | BO41: 62694000 | BP41: 47499000 | BQ41: 34722000 | BR41: 27351000 | BS41: 87803000 | BT41: 62694000 | BU41: 47499000 | BV41: 34722000 | BW41: 27351000 | BY41: 160000 | BZ41: 160000 | CA41: 160000 | CB41: 160000 | CI41: 560000 | CJ41: 560000 | CK41: -9405000 | CL41: -15365000 | CM41: -7969000 | CN41: 720000 | CO41: 720000 | CP41: -9245000 | CQ41: -15205000 | CR41: 5000000 | CS41: 5000000 | CT41: 5000000 | DB41: 5000000 | DC41: 5000000 | DD41: 5000000 | DL41: 47342000 | DM41: 12091000 | DN41: 41779000 | DO41: 43967000 | DP41: 42556000 | DV41: 43430000 | DW41: 44883000 | EA41: 90772000 | EB41: 56974000 | EC41: 41779000 | ED41: 43967000 | EE41: 42556000 | EF41: 115998000 | EG41: 85622000 | EK41: 100954000 | EL41: 62571000 | FO41: 33510000 | FP41: 2063000 | FT41: 55671000 | FU41: 14375000 | FW41: 9405000 | FX41: 5960000 | FY41: 212000 | FZ41: -2052000 | GD41: -7329000 | GE41: 8687000 | GG41: -9405000 | GH41: -5960000
A42: 41 | B42: ДОРОЖНОЕ, ООО | C42: 1025902376213 | D42: 29 | E42: Строительство жилых и нежилых зданий | AT42: 6399000 | AU42: 6239000 | AV42: 6263000 | AW42: 6064000 | AX42: 6028000 | BD42: 10000 | BE42: 9000 | BF42: 4000 | BG42: 5000 | BN42: 6409000 | BO42: 6248000 | BP42: 6267000 | BQ42: 6069000 | BR42: 6028000 | BS42: 6409000 | BT42: 6248000 | BU42: 6267000 | BV42: 6069000 | BW42: 6028000 | CL42: -19060000 | CM42: 6335000 | CN42: 6144000 | CO42: 5893000 | CP42: 5711000 | CQ42: -19060000 | DL42: 74000 | DM42: 104000 | DN42: 374000 | DO42: 358000 | DP42: 25088000 | EA42: 74000 | EB42: 104000 | EC42: 374000 | ED42: 358000 | EE42: 25088000 | EG42: 600000 | EH42: 600000 | EI42: 622000 | EK42: 681000 | EL42: 694000 | EM42: 812000 | EN42: 750000 | EY42: 987000 | FO42: 4000 | FS42: 805000 | FT42: 321000 | FU42: 97000 | FV42: 33000 | FW42: 49000 | FY42: 4000 | GA42: 6000 | GB42: 6000 | GD42: -1002000 | GE42: -191000 | GF42: -251000 | GG42: -183000 | GH42: -182000
A43: 42 | B43: ДОРТЕХИНЖИНИРИНГ, ООО | C43: 1135903006370 | D43: 11 | E43: Деятельность вспомогательная, связанная с автомобильным транспортом | G43: 9371699 | K43: 97443186 | L43: 154732211 | M43: 46151362 | N43: 63737 | P43: 435415000 | Q43: 463280000 | R43: 197001000 | S43: 146710000 | T43: 652440000 | AE43: 42001000 | AF43: 26666000 | AG43: 7494000 | AJ43: 506844000 | AK43: 543663000 | AL43: 439466000 | AM43: 332662000 | AN43: 652440000 | AO43: 46542000 | AP43: 52041000 | AQ43: 107426000 | AR43: 74876000 | AT43: 289242000 | AU43: 510957000 | AV43: 52332000 | AW43: 11872000 | AY43: 284488000 | AZ43: 100735000 | BD43: 29339000 | BE43: 5059000 | BF43: 22948000 | BG43: 19263000 | BH43: 19263000 | BI43: 1483000 | BJ43: 13343000 | BK43: 1403000 | BL43: 2652000 | BN43: 660296000 | BO43: 688468000 | BP43: 188840000 | BQ43: 113394000 | BR43: 19263000 | BS43: 1167140000 | BT43: 1232131000 | BU43: 628306000 | BV43: 446056000 | BW43: 671703000 | BX43: 10000 | BY43: 10000 | BZ43: 10000 | CA43: 10000 | CB43: 10000 | CC43: 320050000 | CD43: 451202000 | CE43: 289943000 | CF43: 289943000 | CG43: 289943000 | CH43: -138781000 | CI43: -262137000 | CJ43: -863815000 | CK43: -1092041000 | CL43: 380715000 | CM43: 181279000 | CN43: 189075000 | CO43: -573862000 | CP43: -802088000 | CQ43: 670668000 | CR43: 5732000 | DA43: 1035000 | DB43: 10701000 | DC43: 2059000 | DD43: 114000 | DF43: 1035000 | DG43: 360916000 | DH43: 389589000 | DI43: 398183000 | DJ43: 405943000 | DL43: 614017000 | DM43: 651376000 | DN43: 803871000 | DO43: 842197000 | EA43: 975160000 | EB43: 1040997000 | EC43: 1202054000 | ED43: 1248144000 | EF43: 1065179000 | EG43: 1179624000 | EH43: 819814000 | EI43: 363392000 | EJ43: 12372000 | EK43: 898462000 | EL43: 1110541000 | EM43: 883497000 | EN43: 428389000 | EO43: 7770000 | EU43: 101633000 | EV43: 110639000 | EW43: 131795000 | EX43: 110061000 | EY43: 59398000 | FE43: 28189000 | FF43: 52842000 | FG43: 42785000 | FH43: 17993000 | FI43: 10284000 | FJ43: 27974000 | FK43: 49739000 | FL43: 31617000 | FM43: 7760000 | FO43: 35504000 | FP43: 74252000 | FQ43: 121544000 | FR43: 67375000 | FS43: 4411000 | FT43: 236844000 | FU43: 169416000 | FV43: 810073000 | FW43: 84027000 | FX43: 8709000 | FY43: -299000 | FZ43: 26921000 | GA43: 117687000 | GB43: -48906000 | GC43: -28158000 | GD43: -140413000 | GE43: -125198000 | GF43: -767351000 | GG43: -239250000 | GH43: -77068000
A44: 43 | B44: ДОРТРАНССТРОЙ, ООО | C44: 1065918011213 | D44: 19 | E44: Деятельность автомобильного грузового транспорта и услуги по перевозкам | F44: 111091 | I44: 346308 | K44: 10010769 | L44: 5049735 | M44: 29045 | N44: 516709 | P44: 36586000 | Q44: 26832000 | R44: 13839000 | T44: 2289000 | AB44: 8132000 | AJ44: 37809000 | AK44: 34043000 | AL44: 21971000 | AN44: 2289000 | AO44: 45345000 | AP44: 20570000 | AQ44: 14530000 | AT44: 10785000 | AU44: 16717000 | AV44: 21295000 | AX44: 4985000 | BD44: 1756000 | BE44: 18000 | BF44: 8442000 | BH44: 1087000 | BI44: 20000 | BJ44: 6067000 | BN44: 57994000 | BO44: 50988000 | BP44: 44267000 | BR44: 6072000 | BS44: 95803000 | BT44: 85030000 | BU44: 66238000 | BW44: 8361000 | BX44: 30000 | BY44: 30000 | CH44: -58083000 | CI44: -88220000 | CM44: -58053000 | CN44: -88190000 | CO44: -102870000 | CQ44: -38298000 | CR44: 41564000 | CS44: 41564000 | CT44: 41564000 | CW44: 21000 | CX44: 21000 | CY44: 108000 | DB44: 43269000 | DC44: 42595000 | DD44: 41672000 | DL44: 110131000 | DM44: 130529000 | DN44: 127340000 | DP44: 46659000 | DX44: 97000 | EA44: 110587000 | EB44: 130625000 | EC44: 127437000 | EE44: 46659000 | EF44: 168861000 | EG44: 33835000 | EK44: 148441000 | EL44: 75038000 | EM44: 13220000 | EU44: 23836000 | EV44: 4945000 | FO44: 15422000 | FP44: 17152000 | FQ44: 13276000 | FS44: 3212000 | FT44: 11611000 | FU44: 13857000 | FV44: 7025000 | FX44: 3204000 | FY44: -460000 | FZ44: 7862000 | GA44: -1391000 | GC44: 2000 | GD44: -79374000 | GE44: -34991000 | GF44: -5578000 | GH44: 6000
A45: 44 | B45: ДСК, ООО | C45: 1131841003117 | D45: 12 | E45: Деятельность заказчика-застройщика, генерального подрядчика | F45: 169850 | K45: 379968 | L45: 25914 | M45: 5002 | Q45: 917000 | AE45: 149738000 | AJ45: 157844000 | AK45: 9170000 | AL45: 10472000 | AO45: 5907000 | AP45: 2331000 | AQ45: 105000 | AT45: 24055000 | AU45: 19855000 | AV45: 5592000 | BD45: 24000 | BE45: 10000 | BF45: 7000 | BI45: 5000 | BJ45: 4000 | BN45: 30036000 | BO45: 22286000 | BP45: 5807000 | BS45: 187879000 | BT45: 31456000 | BU45: 16279000 | BX45: 22000000 | BY45: 22000000 | BZ45: 22000000 | CH45: -40562000 | CI45: -77181000 | CJ45: -83520000 | CM45: -18562000 | CN45: -55181000 | CO45: -61520000 | CR45: 2467000 | DB45: 2467000 | DG45: 27946000 | DH45: 12930000 | DI45: 2665000 | DL45: 48737000 | DM45: 73373000 | DN45: 75135000 | DQ45: 126950000 | EA45: 203974000 | EB45: 86637000 | EC45: 77800000 | EF45: 7050000 | EG45: 100000 | EH45: 25000 | EK45: 4941000 | EU45: 4996000 | EV45: 4337000 | EW45: 1267000 | FE45: 164000 | FJ45: 481000 | FK45: 604000 | FL45: 594000 | FO45: 7995000 | FP45: 13414000 | FQ45: 53000 | FT45: 13034000 | FU45: 45333000 | FV45: 6777000 | FY45: 1600000 | FZ45: 99000 | GA45: 1471000 | GD45: -6643000 | GE45: -36619000 | GF45: -6339000
A46: 45 | B46: ДСТ, ООО | C46: 1056603672410 | D46: 20 | E46: Обработка и утилизация опасных отходов | F46: 74848 | G46: 9946 | H46: 770 | I46: 12015 | K46: 184920 | L46: 20366 | M46: 96711 | N46: 330062 | Q46: 1000 | R46: 1000 | S46: 1000 | T46: 1000 | AK46: 1000 | AL46: 1000 | AM46: 1000 | AN46: 1000 | AT46: 4850000 | AU46: 3715000 | AV46: 3635000 | AW46: 3675000 | AX46: 3215000 | BD46: 288000 | BE46: 445000 | BF46: 907000 | BG46: 225000 | BH46: 1000 | BN46: 5138000 | BO46: 4160000 | BP46: 4542000 | BQ46: 3900000 | BR46: 3216000 | BS46: 5138000 | BT46: 4162000 | BU46: 4543000 | BV46: 3900000 | BW46: 3217000 | CM46: 714000 | CN46: -69000 | CO46: -67000 | CP46: -317000 | CQ46: -1028000 | DK46: 38000 | DL46: 4424000 | DM46: 4231000 | DN46: 4610000 | DO46: 4217000 | DP46: 4207000 | EA46: 4424000 | EB46: 4231000 | EC46: 4610000 | ED46: 4217000 | EE46: 4245000 | EF46: 1013000 | EG46: 43000 | EH46: 5836000 | EK46: 862000 | EL46: 811000 | EM46: 5546000 | EN46: 223000 | EO46: 138000 | FO46: 2000 | FP46: 5000 | FQ46: 7000 | FR46: 25000 | FT46: 255000 | FU46: 19000 | FV46: 296000 | FW46: 51000 | FX46: 12000 | FY46: 19000 | FZ46: 1000 | GD46: -121000 | GE46: -783000 | GF46: 1000 | GG46: -249000 | GH46: -150000
A47: 46 | B47: ДСТ-СТРОЙ, ООО | C47: 1125903002653 | D47: 13 | E47: Работы строительные специализированные прочие, не включенные в другие группировки | F47: 2353262 | G47: 1711034 | H47: 2531311 | K47: 11934526 | L47: 10439074 | M47: 18029656 | N47: 1050493 | O47: 4458206 | P47: 68214000 | Q47: 43248000 | R47: 29472000 | S47: 1716000 | AJ47: 68214000 | AK47: 43248000 | AL47: 29472000 | AM47: 1716000 | AO47: 377184000 | AP47: 472036000 | AQ47: 4345000 | AT47: 102352000 | AU47: 91462000 | AV47: 60234000 | AW47: 51880000 | AX47: 33032000 | AY47: 4000000 | AZ47: 14300000 | BA47: 14303000 | BB47: 14300000 | BC47: 10300000 | BD47: 9000 | BE47: 20621000 | BF47: 2902000 | BG47: 1780000 | BH47: 5295000 | BI47: 13882000 | BJ47: 14000 | BK47: 12000 | BL47: 34000 | BM47: 34000 | BN47: 504519000 | BO47: 602510000 | BP47: 84884000 | BQ47: 69543000 | BR47: 50210000 | BS47: 572733000 | BT47: 645759000 | BU47: 114356000 | BV47: 71259000 | BW47: 50210000 | BX47: 12000 | BY47: 12000 | BZ47: 12000 | CA47: 12000 | CB47: 12000 | CH47: 35371000 | CI47: 40893000 | CJ47: -443877000 | CK47: -467940000 | CL47: -468411000 | CM47: 35383000 | CN47: 40905000 | CO47: -443865000 | CP47: -467928000 | CQ47: -468399000 | CR47: 57974000 | CS47: 96473000 | CT47: 89217000 | CU47: 56619000 | CV47: 29403000 | CW47: 120816000 | CX47: 15582000 | DB47: 178790000 | DC47: 112055000 | DD47: 89217000 | DE47: 56619000 | DF47: 29403000 | DG47: 176311000 | DH47: 164861000 | DI47: 146170000 | DJ47: 143745000 | DK47: 143745000 | DL47: 182248000 | DM47: 327937000 | DN47: 322834000 | DO47: 338823000 | DP47: 345461000 | EA47: 358560000 | EB47: 492798000 | EC47: 469005000 | ED47: 482568000 | EE47: 489206000 | EF47: 423926000 | EG47: 445677000 | EH47: 358122000 | EI47: 80198000 | EK47: 354131000 | EL47: 388142000 | EM47: 317784000 | EN47: 101215000 | EO47: 238000 | EU47: 69637000 | EV47: 50219000 | EW47: 44506000 | EX47: 22556000 | EY47: 504000 | FF47: 4000 | FG47: 6000 | FJ47: 22440000 | FK47: 19837000 | FL47: 18970000 | FM47: 1910000 | FO47: 104063000 | FP47: 159054000 | FQ47: 60587000 | FR47: 57442000 | FS47: 28081000 | FT47: 73278000 | FU47: 137538000 | FV47: 521656000 | FW47: 36022000 | FX47: 27810000 | FY47: -1752000 | FZ47: -1710000 | GD47: 3982000 | GE47: 5522000 | GF47: -484770000 | GG47: -24063000 | GH47: -471000
A48: 47 | B48: ЖЕМЧУЖИНА, ООО | C48: 1055907098070 | D48: 19 | E48: Покупка и продажа земельных участков | H48: 1201 | J48: 6807 | L48: 228000 | M48: 320000 | O48: 539553 | P48: 49759000 | AJ48: 49759000 | AO48: 984000 | AT48: 16961000 | BN48: 17945000 | BS48: 67704000 | BX48: 10000 | CH48: 56586000 | CM48: 56596000 | DG48: 2813000 | DL48: 8295000 | EA48: 11108000 | EF48: 3834000 | EU48: 4405000 | FO48: 690000 | FY48: -24000 | GD48: 95000
A49: 48 | B49: ЖИЛСТРОЙКОМФОРТ, ООО | C49: 1175958017949 | D49: 8 | E49: Производство пара и горячей воды (тепловой энергии) котельными | L49: 173621 | M49: 43412 | P49: 4203000 | Q49: 3693000 | AJ49: 4203000 | AK49: 3693000 | AP49: 2198000 | AQ49: 377000 | AT49: 16046000 | AU49: 14658000 | AV49: 12788000 | AW49: 10801000 | AX49: 9278000 | BD49: 1747000 | BE49: 2443000 | BF49: 5533000 | BG49: 1973000 | BH49: 1505000 | BN49: 17793000 | BO49: 19299000 | BP49: 18698000 | BQ49: 12774000 | BR49: 10783000 | BS49: 21996000 | BT49: 22992000 | BU49: 18698000 | BV49: 12774000 | BW49: 10783000 | CM49: 1010000 | CN49: -3414000 | CO49: -9041000 | CP49: -11595000 | CQ49: -12148000 | CR49: 16000 | CS49: 16000 | CT49: 16000 | CU49: 16000 | CV49: 16000 | DB49: 16000 | DC49: 16000 | DD49: 16000 | DE49: 16000 | DF49: 16000 | DL49: 20970000 | DM49: 26390000 | DN49: 27723000 | DO49: 24353000 | DP49: 22915000 | EA49: 20970000 | EB49: 26390000 | EC49: 27723000 | ED49: 24353000 | EE49: 22915000 | EF49: 41465000 | EG49: 36536000 | EH49: 35701000 | EK49: 41229000 | EL49: 42476000 | EM49: 37707000 | EN49: 2322000 | FO49: 12000 | FR49: 168000 | FT49: 82000 | FU49: 52000 | FV49: 3224000 | FW49: 376000 | FX49: 538000 | FY49: 261000 | GA49: 289000 | GB49: 24000 | GC49: 15000 | GD49: -95000 | GE49: -5992000 | GF49: -5519000 | GG49: -2554000 | GH49: -553000
A50: 49 | B50: ЖК СБ, ООО | C50: 1135904008239 | D50: 12 | E50: Строительство жилых и нежилых зданий
A51: 50 | B51: ЖКХ ЧЕКМЕНЕВСКОЕ НЫТВЕНСКОГО МУНИЦИПАЛЬНОГО РАЙОНА ПЕРМСКОГО КРАЯ, МУП | C51: 1065916017705 | D51: 19 | E51: Производство пара и горячей воды (тепловой энергии) котельными | Q51: 2173000 | R51: 3433000 | AJ51: 1000 | AK51: 2173000 | AL51: 3433000 | AP51: 25000 | AQ51: 65000 | AT51: 1400000 | AV51: 2093000 | BD51: 22000 | BF51: 47000 | BN51: 1422000 | BO51: 25000 | BP51: 2205000 | BS51: 1423000 | BT51: 2198000 | BU51: 5638000 | BX51: 100000 | BY51: 100000 | CE51: 3737000 | CH51: -1459000 | CI51: -117000 | CJ51: -3283000 | CM51: -1359000 | CN51: 2156000 | CO51: 454000 | DL51: 2782000 | DM51: 42000 | DN51: 5183000 | EA51: 2782000 | EB51: 42000 | EC51: 5183000 | EF51: 763000 | EH51: 6332000 | EK51: 710000 | EM51: 7768000 | EW51: 2048000 | FO51: 166000 | FQ51: 1157000 | FT51: 16000 | FV51: 544000 | GA51: -413000 | GD51: 203000 | GF51: -3284000
A52: 51 | B52: ЖУК, ООО | C52: 1065903038090 | D52: 19 | E52: Управление недвижимым имуществом за вознаграждение или на договорной основе
A53: 52 | B53: ГЭХ, АО | C53: 1167847453751 | D53: 8 | E53: Производство строительных металлических конструкций, изделий и их частей | F53: 140728 | K53: 683778 | L53: 6995 | P53: 52000 | Q53: 13000 | AJ53: 2713000 | AK53: 93000 | AT53: 38950000 | AU53: 37778000 | AY53: 2353000 | AZ53: 3050000 | BI53: 38000 | BJ53: 9000 | BN53: 41357000 | BO53: 40838000 | BS53: 44070000 | BT53: 40931000 | BX53: 10000 | BY53: 10000 | CH53: -5657000 | CI53: -8630000 | CM53: -5647000 | CN53: -8620000 | DB53: 1000 | DL53: 49677000 | DM53: 49512000 | EA53: 49716000 | EB53: 49551000 | EF53: 43793000 | EK53: 21380000 | EP53: 34288000 | EQ53: 724000 | EU53: 1418000 | FO53: 1000 | FP53: 334000 | FT53: 193000 | FU53: 34000 | FY53: 2744000 | FZ53: 80000 | GD53: -10762000 | GE53: -2973000
A54: 53 | B54: ЖЭУ № 1, ООО | C54: 1095911000250 | D54: 16 | E54: Управление недвижимым имуществом за вознаграждение или на договорной основе | AO54: 813000 | AP54: 613000 | AQ54: 457000 | AR54: 941000 | AT54: 20211000 | AU54: 24692000 | AV54: 27641000 | AW54: 23567000 | AX54: 17907000 | BG54: 2000 | BH54: 39000 | BN54: 21024000 | BO54: 25305000 | BP54: 28098000 | BQ54: 24510000 | BR54: 17946000 | BS54: 21024000 | BT54: 25305000 | BU54: 28098000 | BV54: 24510000 | BW54: 17946000 | CB54: 10000 | CL54: -165000 | CM54: 11024000 | CN54: 8524000 | CO54: 6703000 | CP54: 6040000 | CQ54: -155000 | DL54: 10000000 | DM54: 16781000 | DN54: 21395000 | DO54: 18470000 | DP54: 18101000 | EA54: 10000000 | EB54: 16781000 | EC54: 21395000 | ED54: 18470000 | EE54: 18101000 | EF54: 42410000 | EG54: 43195000 | EH54: 41441000 | EI54: 42381000 | EJ54: 7775000 | EK54: 40295000 | EL54: 44511000 | EM54: 43733000 | EN54: 42621000 | EO54: 13210000 | FO54: 3263000 | FP54: 3462000 | FQ54: 2787000 | FT54: 2016000 | FU54: 4214000 | FV54: 1885000 | FX54: 760000 | FY54: 393000 | FZ54: 432000 | GA54: 431000 | GB54: 423000 | GD54: 2969000 | GE54: -2500000 | GF54: -1821000 | GG54: -663000 | GH54: -6195000
A55: 54 | B55: ЗАКАЗЧИК ЖКУ, ООО УК | C55: 1082404001668 | D55: 16 | E55: Управление эксплуатацией жилого фонда за вознаграждение или на договорной основе | K55: 1431 | AO55: 67000 | AT55: 3123000 | AU55: 93386000 | BD55: 270000 | BE55: 4114000 | BN55: 3395000 | BO55: 97500000 | BS55: 3395000 | BT55: 97500000 | BX55: 13000 | BY55: 13000 | CH55: -186261000 | CI55: -90345000 | CM55: -186248000 | CN55: -90332000 | DL55: 183559000 | DM55: 181748000 | DV55: 6070000 | DW55: 6070000 | EA55: 189643000 | EB55: 187832000 | EF55: 26517000 | EK55: 18849000 | EU55: 1353000 | FO55: 20425000 | FP55: 132179000 | FT55: 26550000 | FU55: 36250000 | GD55: 190000 | GE55: 95929000
A56: 55 | B56: ЗАКАМСКАЯ УПРАВЛЯЮЩАЯ КОМПАНИЯ, ООО | C56: 1045901247490 | D56: 21 | E56: Управление недвижимым имуществом за вознаграждение или на договорной основе | CM56: -207619000 | CN56: -209797000 | CO56: -211625000 | CP56: -212881000 | CQ56: -213870000 | DL56: 207619000 | DM56: 209797000 | DN56: 211625000 | DO56: 212881000 | DP56: 213870000 | EA56: 207619000 | EB56: 209797000 | EC56: 211625000 | ED56: 212881000 | EE56: 213870000 | EK56: 2037000 | EL56: 1745000 | EM56: 1414000 | EN56: 856000 | EO56: 592000 | FT56: 2122000 | FU56: 433000 | FV56: 414000 | FW56: 400000 | FX56: 397000 | GD56: -4159000 | GE56: -2178000 | GF56: -1828000 | GG56: -1256000 | GH56: -989000
A57: 56 | B57: ЗЛАТОУСТЬЕ, ООО | C57: 1085948002491 | D57: 16 | E57: Деятельность по предоставлению прочих мест для временного проживания | P57: 23393000 | AJ57: 23393000 | AT57: 4563000 | AX57: 18324000 | BD57: 3506000 | BN57: 8069000 | BR57: 18324000 | BS57: 31462000 | BW57: 18324000 | CM57: 24771000 | CQ57: 16089000 | DG57: 4282000 | DK57: 1715000 | DL57: 2409000 | DP57: 520000 | EA57: 6691000 | EE57: 2235000 | EF57: 631000 | EK57: 3392000 | FJ57: 27000 | FO57: 146000 | FT57: 53000 | FX57: 213000 | FY57: 6000 | GD57: -2701000 | GH57: -213000
A58: 57 | B58: ЗУМК-ИНЖИНИРИНГ, ООО | C58: 1065902054680 | D58: 19 | E58: Деятельность в области архитектуры, связанная с созданием архитектурного объекта | P58: 57106000 | Q58: 49702000 | R58: 43020000 | S58: 34898000 | U58: 69531000 | V58: 47745000 | W58: 26024000 | Z58: 27767000 | AA58: 27767000 | AB58: 25012000 | AC58: 27567000 | AD58: 27567000 | AE58: 856000 | AF58: 856000 | AG58: 856000 | AJ58: 157032000 | AK58: 127800000 | AL58: 96641000 | AM58: 62465000 | AN58: 27567000 | AO58: 96881000 | AP58: 96881000 | AQ58: 96881000 | AR58: 96881000 | AS58: 96881000 | AT58: 462593000 | AU58: 461313000 | AV58: 461313000 | AW58: 461296000 | AX58: 460933000 | BD58: 4031000 | BE58: 3281000 | BF58: 16056000 | BG58: 8330000 | BH58: 11927000 | BN58: 563505000 | BO58: 561475000 | BP58: 574250000 | BQ58: 566507000 | BR58: 569741000 | BS58: 720537000 | BT58: 689275000 | BU58: 670891000 | BV58: 628972000 | BW58: 597308000 | BX58: 69185000 | BY58: 69185000 | BZ58: 69185000 | CH58: -1419948000 | CI58: -1454852000 | CJ58: -1470310000 | CM58: -1260532000 | CN58: -1295436000 | CO58: -1310894000 | CP58: -1346827000 | CQ58: -1377369000 | CZ58: 82836000 | DA58: 82836000 | DB58: 82836000 | DC58: 82836000 | DD58: 82836000 | DE58: 82836000 | DF58: 82836000 | DG58: 697878000 | DH58: 697878000 | DI58: 697878000 | DJ58: 697878000 | DK58: 697510000 | DL58: 1200355000 | DM58: 1203997000 | DN58: 1201071000 | DO58: 1195085000 | DP58: 1194331000 | EA58: 1898233000 | EB58: 1901875000 | EC58: 1898949000 | ED58: 1892963000 | EE58: 1891841000 | EO58: 1456000 | EU58: 4651000 | FO58: 87900000 | FQ58: 25394000 | FR58: 7338000 | FS58: 5849000 | FT58: 1659425000 | FU58: 34904000 | FV58: 40852000 | FW58: 43271000 | FX58: 34935000 | GD58: -1576176000 | GE58: -34904000 | GF58: -15458000 | GG58: -35933000 | GH58: -30542000
A59: 58 | B59: ИЛЬИНСКОЕ МОЛОКО, ПК ОРК | C59: 1175958043502 | D59: 7 | E59: Торговля оптовая молочными продуктами, яйцами и пищевыми маслами и жирами | AT59: 63720000 | AU59: 25981000 | AW59: 1000000 | AX59: 974000 | BD59: 135000 | BE59: 29000 | BN59: 63855000 | BO59: 26010000 | BQ59: 1000000 | BR59: 974000 | BS59: 63855000 | BT59: 26010000 | BV59: 1000000 | BW59: 974000 | BX59: 50000 | BY59: 50000 | BZ59: 50000 | CA59: 50000 | CB59: 50000 | CH59: 157000 | CI59: 186000 | CJ59: -22311000 | CK59: -26036000 | CL59: -26627000 | CM59: 207000 | CN59: 236000 | CO59: -22261000 | CP59: -25986000 | CQ59: -26577000 | DG59: 5000000 | DH59: 3000000 | DL59: 58648000 | DM59: 22774000 | DN59: 22261000 | DO59: 26986000 | DP59: 27551000 | EA59: 63648000 | EB59: 25774000 | EC59: 22261000 | ED59: 26986000 | EE59: 27551000 | EF59: 1400000 | EG59: 1472000 | EK59: 1304000 | EL59: 1436000 | FV59: 380000 | FW59: 625000 | FX59: 490000 | FY59: -19000 | FZ59: -7000 | GD59: 77000 | GE59: 29000 | GF59: -380000 | GG59: -625000 | GH59: -490000
A60: 59 | B60: ИМПЕРИАЛ, ООО | C60: 1135905001528 | D60: 12 | E60: Строительство автомобильных дорог и автомагистралей | F60: 187930 | P60: 26759000 | AJ60: 26759000 | AO60: 158854000 | AT60: 22998000 | AV60: 203384000 | BN60: 181852000 | BP60: 203384000 | BS60: 208611000 | BU60: 203384000 | CM60: 19253000 | CO60: 10000 | DG60: 1227000 | DL60: 188131000 | DN60: 203374000 | EA60: 189358000 | EC60: 203374000 | EF60: 78483000 | EK60: 77338000 | EM60: 188756000 | FJ60: 217000 | FL60: 14379000 | FT60: 82000 | FV60: 239000 | FY60: 169000 | GD60: 677000 | GF60: -203374000
A61: 60 | B61: ИНДУСТРИАЛЬНЫЕ ТЕХНОЛОГИИ, ООО | C61: 1175958030050 | D61: 8 | E61: Строительство жилых и нежилых зданий | G61: 35500 | H61: 395643 | I61: 456904 | J61: 473322 | K61: 4282 | L61: 89640 | M61: 922208 | N61: 706660 | O61: 2838126 | Q61: 513000 | R61: 426000 | S61: 1514000 | T61: 441000 | AK61: 513000 | AL61: 426000 | AM61: 1514000 | AN61: 441000 | AO61: 37000 | AQ61: 19880000 | AR61: 35544000 | AS61: 1000 | AT61: 1104000 | AU61: 9854000 | AV61: 5703000 | AW61: 9897000 | AX61: 804000 | BD61: 123000 | BE61: 726000 | BF61: 877000 | BG61: 226000 | BH61: 1000 | BN61: 1264000 | BO61: 10580000 | BP61: 26460000 | BQ61: 45667000 | BR61: 806000 | BS61: 1264000 | BT61: 11093000 | BU61: 26886000 | BV61: 47181000 | BW61: 1247000 | BX61: 10000 | CH61: 123000 | CM61: 133000 | CN61: 1283000 | CO61: 3666000 | CP61: 5335000 | CQ61: -28123000 | CR61: 798000 | CS61: 859000 | CT61: 7128000 | CU61: 21852000 | CV61: 13741000 | DB61: 798000 | DC61: 859000 | DD61: 7128000 | DE61: 21852000 | DF61: 13741000 | DL61: 333000 | DM61: 8951000 | DN61: 16092000 | DO61: 19994000 | DP61: 15629000 | EA61: 333000 | EB61: 8951000 | EC61: 16092000 | ED61: 19994000 | EE61: 15629000 | EF61: 581000 | EG61: 31542000 | EH61: 26051000 | EI61: 47837000 | EJ61: 25506000 | EK61: 319000 | EL61: 29861000 | EM61: 23759000 | EN61: 43265000 | EO61: 56970000 | EU61: 163000 | FN61: 916000 | FP61: 25000 | FR61: 25000 | FT61: 23000 | FU61: 305000 | FV61: 1105000 | FW61: 2454000 | FX61: 1078000 | FY61: -15000 | FZ61: 251000 | GA61: 294000 | GB61: 474000 | GD61: 61000 | GE61: 1150000 | GF61: 893000 | GG61: 1669000 | GH61: -33458000
A62: 61 | B62: ИНЖСТРОЙКОМ, ООО | C62: 1074312003369 | D62: 17 | E62: Строительство жилых и нежилых зданий | K62: 10342798 | L62: 44000 | P62: 985000 | AJ62: 985000 | AO62: 3026000 | AP62: 3547000 | AQ62: 2964000 | AR62: 2964000 | AT62: 111235000 | AU62: 111235000 | AV62: 3252000 | AW62: 3252000 | AX62: 3064000 | BN62: 114261000 | BO62: 114782000 | BP62: 6216000 | BQ62: 6216000 | BR62: 3064000 | BS62: 115246000 | BT62: 114782000 | BU62: 6216000 | BV62: 6216000 | BW62: 3064000 | CM62: -40662000 | CN62: -41126000 | CO62: -79265000 | CP62: -79265000 | CQ62: -97007000 | CR62: 856000 | CS62: 856000 | DB62: 856000 | DC62: 856000 | DG62: 10491000 | DH62: 10491000 | DL62: 142017000 | DM62: 142017000 | DN62: 85481000 | DO62: 85481000 | DP62: 100071000 | DV62: 2544000 | DW62: 2544000 | EA62: 155052000 | EB62: 155052000 | EC62: 85481000 | ED62: 85481000 | EE62: 100071000 | EF62: 74616000 | EG62: 3528000 | EH62: 583000 | EJ62: 92000 | EK62: 82170000 | EL62: 3987000 | EM62: 38722000 | EO62: 17834000 | FO62: 22000 | FT62: 25186000 | FU62: 5000 | GD62: -32718000 | GE62: -464000 | GF62: -38139000 | GH62: -17742000
A63: 62 | B63: ИНТЕРМИКС МЕТ, ООО | C63: 1037739608411 | D63: 22 | E63: Производство алюминия | I63: 898822 | K63: 532827 | M63: 8476348 | N63: 231324 | P63: 61711000 | V63: 8627000 | AC63: 13000 | AE63: 9326000 | AJ63: 71063000 | AK63: 8718000 | AL63: 1237000 | AM63: 12977000 | AP63: 74820000 | AQ63: 20489000 | AR63: 61311000 | AT63: 422401000 | AU63: 467823000 | AV63: 152057000 | AW63: 709751000 | BE63: 19295000 | BF63: 17229000 | BG63: 2563000 | BH63: 392000 | BI63: 61000 | BJ63: 9000 | BN63: 422519000 | BO63: 561949000 | BP63: 189775000 | BQ63: 773627000 | BR63: 392000 | BS63: 493582000 | BT63: 570667000 | BU63: 191011000 | BV63: 786604000 | BW63: 392000 | BX63: 1000000 | BY63: 1000000 | BZ63: 1000000 | CA63: 1000000 | CB63: 1000000 | CH63: -4890693000 | CI63: -4879651000 | CJ63: -5013694000 | CK63: -4953254000 | CL63: -3832947000 | CM63: -4889693000 | CN63: -4878651000 | CO63: -5012694000 | CP63: -4952254000 | CQ63: -3831947000 | CR63: 13600000 | CS63: 13581000 | CT63: 13479000 | CU63: 13479000 | DB63: 15589000 | DC63: 16324000 | DD63: 17443000 | DE63: 17586000 | DG63: 905267000 | DH63: 905267000 | DI63: 905267000 | DJ63: 905267000 | DL63: 4462418000 | DM63: 4527727000 | DN63: 4280995000 | DO63: 4816006000 | DP63: 3832339000 | EA63: 5367685000 | EB63: 5432993000 | EC63: 5186262000 | ED63: 5721273000 | EE63: 3832339000 | EH63: 366000 | EM63: 293000 | EV63: 80000 | EW63: 9000 | EX63: 351000 | FP63: 3146000 | FQ63: 18017000 | FR63: 5941000 | FU63: 2963000 | FV63: 151292000 | FW63: 7677000 | FZ63: -21000 | GA63: -832000 | GB63: 35000 | GE63: 82000 | GF63: -134043000 | GG63: -2052000
A64: 63 | B64: ИНТРЕЙДЖИЛСТРОЙ, ООО | C64: 1145958035783 | D64: 11 | E64: Строительство жилых и нежилых зданий | H64: 1508098 | J64: 17931 | M64: 15864757 | N64: 9492084 | P64: 9494000 | Q64: 9771000 | R64: 2970000 | S64: 2212000 | T64: 1659000 | AJ64: 9494000 | AK64: 9771000 | AL64: 2970000 | AM64: 2212000 | AN64: 1659000 | AO64: 54068000 | AP64: 39070000 | AQ64: 24697000 | AR64: 48933000 | AS64: 39894000 | AT64: 53492000 | AU64: 53896000 | AV64: 75901000 | AW64: 67410000 | AX64: 113451000 | AY64: 2535000 | BA64: 1000000 | BB64: 500000 | BC64: 1223000 | BD64: 2745000 | BE64: 95000 | BF64: 1474000 | BG64: 3588000 | BH64: 882000 | BI64: 6514000 | BJ64: 4638000 | BL64: 2171000 | BM64: 1304000 | BN64: 119353000 | BO64: 97699000 | BP64: 105221000 | BQ64: 122602000 | BR64: 156757000 | BS64: 128847000 | BT64: 107471000 | BU64: 108191000 | BV64: 124814000 | BW64: 158417000 | BX64: 10000 | BY64: 10000 | BZ64: 10000 | CA64: 10000 | CB64: 10000 | CH64: 57223000 | CI64: 69214000 | CJ64: 61451000 | CK64: 1491000 | CL64: -41383000 | CM64: 57233000 | CN64: 69224000 | CO64: 61461000 | CP64: 1501000 | CQ64: -41373000 | CR64: 12709000 | CS64: 8687000 | CU64: 15039000 | CV64: 16206000 | CW64: 11308000 | CX64: -3124000 | DA64: -732000 | DB64: 24017000 | DC64: 5563000 | DE64: 15039000 | DF64: 15474000 | DL64: 47597000 | DM64: 32684000 | DN64: 46730000 | DO64: 108274000 | DP64: 184316000 | EA64: 47597000 | EB64: 32684000 | EC64: 46730000 | ED64: 108274000 | EE64: 184316000 | EF64: 98500000 | EG64: 221469000 | EH64: 325832000 | EI64: 214938000 | EJ64: 62166000 | EK64: 87035000 | EL64: 204523000 | EM64: 271619000 | EN64: 214386000 | EO64: 60945000 | EU64: 1084000 | EV64: 3200000 | EW64: 2487000 | EX64: 2154000 | EY64: 1211000 | FO64: 2898000 | FP64: 4130000 | FQ64: 4222000 | FR64: 1700000 | FT64: 588000 | FU64: 3489000 | FV64: 4992000 | FY64: -1487000 | FZ64: -1988000 | GA64: -39000 | GB64: -20000 | GD64: 11230000 | GE64: 12399000 | GF64: 43771000 | GG64: 78000 | GH64: 10000
A65: 64 | B65: ИПФ МАЛЫШ, ОАО | C65: 1026102905355 | D65: 31 | E65: Аренда и управление собственным или арендованным нежилым недвижимым имуществом | P65: 3863000 | Q65: 3543000 | R65: 3455000 | S65: 3368000 | T65: 512000 | AJ65: 3863000 | AK65: 3543000 | AL65: 3455000 | AM65: 3368000 | AN65: 512000 | AT65: 22919000 | AU65: 22561000 | AV65: 30578000 | AW65: 26833000 | AX65: 8492000 | AY65: 35057000 | AZ65: 35057000 | BA65: 35057000 | BB65: 35057000 | BD65: 1000 | BE65: 774000 | BF65: 1671000 | BG65: 685000 | BH65: 168494000 | BN65: 57976000 | BO65: 58392000 | BP65: 67306000 | BQ65: 62575000 | BR65: 176986000 | BS65: 61840000 | BT65: 61935000 | BU65: 70761000 | BV65: 65943000 | BW65: 177498000 | BX65: 21038000 | BY65: 21038000 | BZ65: 21038000 | CA65: 21038000 | CB65: 21038000 | CC65: 180000 | CD65: 180000 | CE65: 180000 | CF65: 180000 | CG65: 180000 | CH65: 21604000 | CI65: 18855000 | CJ65: 30122000 | CK65: 25961000 | CL65: 46231000 | CM65: 45177000 | CN65: 42428000 | CO65: 53695000 | CP65: 49534000 | CQ65: 69804000 | DL65: 16173000 | DM65: 18735000 | DN65: 16265000 | DO65: 16340000 | DP65: 107694000 | EA65: 16663000 | EB65: 19507000 | EC65: 17066000 | ED65: 16409000 | EE65: 107694000 | EF65: 23174000 | EG65: 26805000 | EH65: 34855000 | EI65: 41095000 | EJ65: 39460000 | EK65: 15487000 | EL65: 17346000 | EM65: 13745000 | EN65: 27753000 | EO65: 20664000 | EU65: 7023000 | EV65: 7552000 | EW65: 6374000 | EX65: 6428000 | EY65: 5529000 | FG65: 3000 | FI65: 4000 | FO65: 14338000 | FP65: 15266000 | FQ65: 14916000 | FR65: 19351000 | FS65: 112363000 | FT65: 15615000 | FU65: 18942000 | FV65: 17660000 | FW65: 29399000 | FX65: 94383000 | FY65: -657000 | FZ65: -756000 | GA65: -728000 | GB65: -1027000 | GC65: -10981000 | GD65: -1359000 | GE65: -2525000 | GF65: 11267000 | GG65: -4161000 | GH65: 20270000
A66: 65 | B66: ИСКРА-ЭНЕРГЕТИКА, АО | C66: 1025901510117 | D66: 28 | E66: Строительство электростанций | H66: 2295 | K66: 1374623 | L66: 84381 | P66: 718000 | AE66: 15000 | AJ66: 861000 | AK66: 95000 | AL66: 62000 | AM66: 29000 | AO66: 46304000 | AP66: 10990000 | AQ66: 10990000 | AR66: 10990000 | AS66: 10990000 | AT66: 4443000 | AU66: 3866000 | AV66: 3910000 | AW66: 3318000 | BD66: 25178000 | BE66: 1139000 | BF66: 843000 | BG66: 1532000 | BH66: 969000 | BI66: 44000 | BJ66: 4000 | BN66: 75970000 | BO66: 15999000 | BP66: 15743000 | BQ66: 15840000 | BR66: 11959000 | BS66: 76830000 | BT66: 16094000 | BU66: 15805000 | BV66: 15869000 | BW66: 11959000 | BX66: 43186000 | BY66: 43186000 | BZ66: 43186000 | CA66: 43186000 | CB66: 43186000 | CH66: -772100000 | CI66: -792190000 | CJ66: -792114000 | CK66: -720617000 | CL66: -724507000 | CM66: -728914000 | CN66: -749004000 | CO66: -748928000 | CP66: -677431000 | CQ66: -681321000 | DL66: 805222000 | DM66: 765077000 | DN66: 764733000 | DO66: 693300000 | DP66: 693280000 | EA66: 805745000 | EB66: 765098000 | EC66: 764733000 | ED66: 693300000 | EE66: 693280000 | EF66: 2846000 | EU66: 11523000 | EV66: 2985000 | EW66: 1169000 | EX66: 526000 | FO66: 603966000 | FP66: 15902000 | FQ66: 1461000 | FR66: 1037000 | FT66: 89234000 | FU66: 44710000 | FV66: 421000 | FW66: 451000 | FY66: 3427000 | FZ66: -2000 | GD66: 508646000 | GE66: -31848000 | GF66: -129000 | GG66: 60000
A67: 66 | B67: КАМАЭЛЕКТРОМОНТАЖ, ООО | C67: 1065920024103 | D67: 18 | E67: Производство электромонтажных работ | F67: 1153326 | G67: 1049432 | H67: 1166756 | I67: 240843 | K67: 22028858 | L67: 12701428 | M67: 6509355 | N67: 3306067 | P67: 993000 | Q67: 887000 | R67: 785000 | Z67: 3000 | AA67: 3000 | AB67: 3000 | AJ67: 1007000 | AK67: 890000 | AL67: 788000 | AO67: 6862000 | AP67: 2296000 | AQ67: 1273000 | AT67: 263633000 | AU67: 279857000 | AV67: 268396000 | AY67: 113542000 | AZ67: 118002000 | BA67: 118002000 | BD67: 222000 | BE67: 27000 | BF67: 3000 | BI67: 82000 | BJ67: 13000 | BK67: 8000 | BN67: 384341000 | BO67: 400196000 | BP67: 387682000 | BS67: 385348000 | BT67: 401086000 | BU67: 388470000 | BX67: 10000 | BY67: 10000 | BZ67: 10000 | CH67: 21650000 | CI67: 20505000 | CJ67: 23360000 | CM67: 21660000 | CN67: 20515000 | CO67: 23370000 | CR67: 9215000 | CS67: 4749000 | CT67: 4739000 | DB67: 9215000 | DC67: 4749000 | DD67: 4739000 | DG67: 4357000 | DH67: 16916000 | DI67: 7747000 | DL67: 350116000 | DM67: 358907000 | DN67: 352614000 | EA67: 354473000 | EB67: 375822000 | EC67: 360361000 | EF67: 220278000 | EG67: 104175000 | EH67: 31925000 | EK67: 171167000 | EL67: 63181000 | EM67: 7160000 | EU67: 42852000 | EV67: 36759000 | EW67: 18499000 | FE67: 5038000 | FF67: 5667000 | FJ67: 1870000 | FK67: 1864000 | FL67: 960000 | FO67: 17126000 | FP67: 5754000 | FQ67: 7721000 | FT67: 19099000 | FU67: 13739000 | FV67: 9127000 | FY67: -2345000 | FZ67: -1198000 | GA67: -1045000 | GD67: 5109000 | GE67: -1145000 | GF67: 2855000
A68: 67 | B68: КАПИТАЛ ГРУПП, ООО | C68: 1195958004802 | D68: 6 | E68: Денежное посредничество прочее | K68: 5324 | Q68: 85000 | R68: 44000 | S68: 3000 | AK68: 85000 | AL68: 44000 | AM68: 3000 | AO68: 2512000 | AP68: 5499000 | AQ68: 5263000 | AR68: 5263000 | AT68: 11857000 | AU68: 20645000 | AV68: 24005000 | AW68: 23681000 | AY68: 374000 | BD68: 4031000 | BE68: 67000 | BF68: 3000 | BG68: 1000 | BI68: 5436000 | BN68: 24210000 | BO68: 26211000 | BP68: 29271000 | BQ68: 28945000 | BS68: 24210000 | BT68: 26296000 | BU68: 29314000 | BV68: 28947000 | BX68: 1000000 | CH68: -829000 | CM68: 171000 | CN68: -7578000 | CO68: -10555000 | CP68: -10690000 | CR68: 1412000 | CS68: 865000 | CT68: 865000 | CU68: 865000 | DB68: 1412000 | DC68: 865000 | DD68: 865000 | DE68: 865000 | DI68: 511000 | DJ68: 511000 | DL68: 22627000 | DM68: 33010000 | DN68: 38494000 | DO68: 38262000 | EA68: 22627000 | EB68: 33010000 | EC68: 39005000 | ED68: 38773000 | EF68: 19387000 | EG68: 14206000 | EH68: 1469000 | EK68: 15259000 | EL68: 22188000 | EM68: 4121000 | EN68: 142000 | EU68: 3606000 | FO68: 7193000 | FP68: 7099000 | FQ68: 1182000 | FR68: 625000 | FT68: 7648000 | FU68: 7501000 | FV68: 1215000 | FW68: 618000 | FZ68: 260000 | GA68: 290000 | GD68: 67000 | GE68: -8644000 | GF68: -2975000 | GG68: -135000
A69: 68 | B69: КМЗ, ПАО | C69: 1027739700724 | D69: 32 | E69: Производство лифтов, скриповых подъемников, эскалаторов и движущихся пешеходных дорожек | N69: 55231027 | O69: 7536697 | P69: 589997000 | Q69: 494802000 | R69: 422323000 | S69: 387692000 | T69: 10615000 | Z69: 957143000 | AA69: 957141000 | AB69: 939635000 | AC69: 939630000 | AE69: 330530000 | AF69: 328904000 | AG69: 4884000 | AH69: 3496000 | AJ69: 2220827000 | AK69: 2137505000 | AL69: 2574787000 | AM69: 2478170000 | AN69: 1014242000 | AO69: 1673508000 | AP69: 1963695000 | AQ69: 245363000 | AR69: 159076000 | AS69: 7669000 | AT69: 3724817000 | AU69: 3570973000 | AV69: 828243000 | AW69: 269907000 | AX69: 10320000 | AY69: 1169922000 | AZ69: 1416581000 | BA69: 441340000 | BB69: 260340000 | BD69: 985693000 | BE69: 212800000 | BF69: 27516000 | BG69: 15304000 | BH69: 1077222000 | BI69: 45998000 | BJ69: 45070000 | BK69: 45029000 | BL69: 1483000 | BN69: 7600027000 | BO69: 7209119000 | BP69: 1587490000 | BQ69: 706109000 | BR69: 1095211000 | BS69: 9820853000 | BT69: 9346624000 | BU69: 4162277000 | BV69: 3184279000 | BW69: 2109453000 | BX69: 89000 | BY69: 89000 | BZ69: 89000 | CA69: 89000 | CB69: 89000 | CC69: 179462000 | CD69: 179333000 | CE69: 165481000 | CF69: 165475000 | CG69: 6154000 | CH69: 54565000 | CI69: -329752000 | CJ69: -5050335000 | CK69: -6091493000 | CL69: -5369159000 | CM69: 234121000 | CN69: -150326000 | CO69: -4884761000 | CP69: -5925925000 | CQ69: -5362912000 | CR69: 6156293000 | CS69: 6156293000 | DB69: 6328511000 | DC69: 6324402000 | DD69: 56668000 | DE69: 48354000 | DF69: 44448000 | DG69: 1825794000 | DH69: 1798475000 | DI69: 7908589000 | DJ69: 8016737000 | DK69: 6871908000 | DL69: 1347623000 | DM69: 1317181000 | DN69: 1036971000 | DO69: 997694000 | DP69: 556008000 | EA69: 3258221000 | EB69: 3172548000 | EC69: 8990370000 | ED69: 9061850000 | EE69: 7427917000 | EF69: 6781526000 | EG69: 5038130000 | EH69: 2423842000 | EI69: 792282000 | EJ69: 287543000 | EK69: 5122392000 | EL69: 4884794000 | EM69: 2373095000 | EN69: 1144419000 | EO69: 408691000 | EP69: 208641000 | EQ69: 183925000 | ER69: 79464000 | ES69: 43000 | EU69: 446465000 | EV69: 474491000 | EW69: 300405000 | EX69: 258703000 | EY69: 129521000 | EZ69: 833000 | FA69: 479000 | FC69: 809000 | FE69: 166084000 | FF69: 198347000 | FG69: 76150000 | FH69: 52248000 | FI69: 8496000 | FJ69: 800344000 | FK69: 3498000 | FO69: 510310000 | FP69: 307599000 | FQ69: 223599000 | FR69: 441429000 | FS69: 5425388000 | FT69: 1235372000 | FU69: 388839000 | FV69: 4922171000 | FW69: 1085817000 | FX69: 4480512000 | FY69: 68123000 | FZ69: 6676000 | GA69: 903997000 | GB69: 161050000 | GC69: -139690000 | GD69: -286338000 | GE69: -384316000 | GF69: -4047547000 | GG69: -1041164000 | GH69: 563013000
A70: 69 | B70: КОММУНСЕРВИС, МУП ЖКХ | C70: 1021801060984 | D70: 30 | E70: Управление эксплуатацией жилого фонда за вознаграждение или на договорной основе | P70: 941000 | Q70: 557000 | R70: 318000 | Z70: 2000 | AA70: 2000 | AB70: 72000 | AC70: 72000 | AD70: 72000 | AJ70: 943000 | AK70: 559000 | AL70: 390000 | AM70: 72000 | AN70: 72000 | AO70: 846000 | AT70: 4582000 | AU70: 2631000 | AV70: 3185000 | AW70: 2881000 | AX70: 2747000 | BD70: 3730000 | BE70: 71000 | BF70: 5110000 | BG70: 1847000 | BH70: 962000 | BN70: 9158000 | BO70: 2702000 | BP70: 8295000 | BQ70: 4728000 | BR70: 3709000 | BS70: 10101000 | BT70: 3261000 | BU70: 8685000 | BV70: 4800000 | BW70: 3781000 | BX70: 156000 | BY70: 156000 | BZ70: 156000 | CA70: 156000 | CB70: 156000 | CC70: 1146000 | CD70: 1146000 | CE70: 1146000 | CF70: 1146000 | CG70: 1146000 | CH70: -23062000 | CI70: -32063000 | CJ70: -30310000 | CK70: -32354000 | CL70: -33423000 | CM70: -17687000 | CN70: -26688000 | CO70: -24935000 | CP70: -26979000 | CQ70: -28048000 | CR70: 5105000 | CS70: 5105000 | CT70: 5105000 | DB70: 5105000 | DC70: 5105000 | DD70: 5105000 | DL70: 17781000 | DM70: 24777000 | DN70: 28515000 | DO70: 28017000 | DP70: 28101000 | DQ70: 4902000 | DR70: 67000 | DY70: 3762000 | DZ70: 3728000 | EA70: 22683000 | EB70: 24844000 | EC70: 28515000 | ED70: 31779000 | EE70: 31829000 | EF70: 13987000 | EG70: 13120000 | EH70: 1376000 | EI70: 8000 | EJ70: 7000 | EK70: 11526000 | EL70: 12879000 | EM70: 5446000 | EU70: 8751000 | EV70: 8655000 | EW70: 1182000 | EX70: 1021000 | EY70: 973000 | EZ70: 404000 | FA70: 209000 | FO70: 238000 | FP70: 643000 | FQ70: 18211000 | FT70: 192000 | FU70: 217000 | FV70: 442000 | FW70: 571000 | FX70: 64000 | FY70: -140000 | FZ70: -126000 | GA70: -776000 | GB70: -3000 | GC70: -1000 | GD70: -5980000 | GE70: -7905000 | GF70: 10788000 | GG70: -1726000 | GH70: -1069000
A71: 70 | B71: КОМПАНИЯ П.Р.З.К.-АВТОБАНСТРОЙ, ООО | C71: 1065907023270 | D71: 18 | E71: Строительство автомобильных дорог и автомагистралей | P71: 10599000 | AJ71: 10599000 | AO71: 125000 | AP71: 125000 | AT71: 44866000 | AU71: 26182000 | AV71: 23576000 | AW71: 21068000 | AX71: 9611000 | BD71: 858000 | BE71: 5029000 | BF71: 3432000 | BG71: 2663000 | BH71: 2014000 | BN71: 45849000 | BO71: 31336000 | BP71: 27008000 | BQ71: 23731000 | BR71: 11625000 | BS71: 56448000 | BT71: 31336000 | BU71: 27008000 | BV71: 23731000 | BW71: 11625000 | CM71: -69050000 | CN71: -71162000 | CO71: -74782000 | CP71: -78057000 | CQ71: -86244000 | CR71: 28983000 | CS71: 22455000 | CT71: 22455000 | CU71: 22455000 | CV71: 22455000 | DB71: 28983000 | DC71: 22455000 | DD71: 22455000 | DE71: 22455000 | DF71: 22455000 | DL71: 96515000 | DM71: 80043000 | DN71: 79335000 | DO71: 79333000 | DP71: 75414000 | EA71: 96515000 | EB71: 80043000 | EC71: 79335000 | ED71: 79333000 | EE71: 75414000 | EG71: 8314000 | EL71: 8433000 | FO71: 242000 | FP71: 17055000 | FQ71: 6000 | FR71: 1716000 | FS71: 10630000 | FT71: 66491000 | FU71: 19047000 | FV71: 3626000 | FW71: 4988000 | FX71: 18817000 | GD71: -66249000 | GE71: -2111000 | GF71: -3620000 | GG71: -3272000 | GH71: -8187000
A72: 71 | B72: КОМПАНИЯ ПРЗК, ООО | C72: 1025900916612 | D72: 24 | E72: Аренда и управление собственным или арендованным недвижимым имуществом | P72: 2930000 | Q72: 2323000 | R72: 1620000 | S72: 773000 | T72: 32000 | AJ72: 2930000 | AK72: 2323000 | AL72: 1620000 | AM72: 773000 | AN72: 32000 | AO72: 288000 | AP72: 288000 | AQ72: 288000 | AR72: 288000 | AS72: 288000 | AT72: 20183000 | AU72: 18683000 | AV72: 19403000 | AW72: 19480000 | AX72: 19052000 | BH72: 422000 | BN72: 20471000 | BO72: 18971000 | BP72: 19691000 | BQ72: 19768000 | BR72: 19762000 | BS72: 23401000 | BT72: 21294000 | BU72: 21311000 | BV72: 20541000 | BW72: 19794000 | CM72: 8417000 | CN72: 7824000 | CO72: 5147000 | CP72: 3959000 | CQ72: 2350000 | DL72: 14984000 | DM72: 13470000 | DN72: 16164000 | DO72: 16582000 | DP72: 17444000 | EA72: 14984000 | EB72: 13470000 | EC72: 16164000 | ED72: 16582000 | EE72: 17444000 | EL72: 593000 | EM72: 2007000 | EN72: 1074000 | EO72: 988000 | FR72: 1063000 | FS72: 28000 | FV72: 670000 | FW72: 583000 | FX72: 650000 | GE72: -593000 | GF72: -2677000 | GG72: -594000 | GH72: -1610000
A73: 72 | B73: КОМПАУНД ЖИВАГО, ООО | C73: 1145958053086 | D73: 11 | E73: Деятельность по предоставлению прочих вспомогательных услуг для бизнеса, не включенная в другие группировки | P73: 248054000 | AJ73: 248054000 | AT73: 47251000 | BN73: 47251000 | BS73: 295305000 | BX73: 10000 | BY73: 10000 | BZ73: 10000 | CA73: 10000 | CB73: 10000 | CH73: -798065000 | CI73: -844460000 | CJ73: -844730000 | CK73: -844730000 | CL73: -844730000 | CM73: -798055000 | CN73: -844450000 | CO73: -844720000 | CP73: -844720000 | CQ73: -844720000 | CR73: 27204000 | CS73: 27204000 | CT73: 27204000 | CU73: 27204000 | CV73: 27204000 | CW73: 130377000 | CX73: 130377000 | CY73: 130377000 | CZ73: 130377000 | DA73: 130377000 | DB73: 157749000 | DC73: 157749000 | DD73: 157749000 | DE73: 157749000 | DF73: 157749000 | DG73: 3808000 | DH73: 808000 | DI73: 808000 | DJ73: 808000 | DK73: 808000 | DL73: 589161000 | DM73: 343251000 | DN73: 343521000 | DO73: 343521000 | DP73: 343521000 | DV73: 342578000 | DW73: 342578000 | DX73: 342578000 | DY73: 342578000 | DZ73: 342578000 | EA73: 935611000 | EB73: 686701000 | EC73: 686971000 | ED73: 686971000 | EE73: 686971000 | FO73: 250570000 | FT73: 286265000 | FU73: 46395000 | FV73: 270000 | GD73: -35695000 | GE73: -46395000 | GF73: -270000
A74: 73 | B74: КОМФОРТ-СТРОЙ, ООО | C74: 1155836001617 | D74: 10 | E74: Производство прочих строительно-монтажных работ | F74: 995 | G74: 192896 | H74: 80082 | K74: 1115814 | L74: 284268 | M74: 3154381 | N74: 1584094 | O74: 528293 | P74: 10574000 | Q74: 17238000 | R74: 18787000 | S74: 11262000 | Z74: 2319000 | AA74: 29802000 | AB74: 74739000 | AJ74: 12893000 | AK74: 47040000 | AL74: 93526000 | AM74: 11262000 | AO74: 1557000 | AP74: 30496000 | AQ74: 109059000 | AR74: 339000 | AT74: 39987000 | AU74: 167621000 | AV74: 392877000 | AW74: 55923000 | BD74: 18985000 | BE74: 1133000 | BF74: 421000 | BG74: 1553000 | BN74: 60529000 | BO74: 199250000 | BP74: 502357000 | BQ74: 57815000 | BS74: 73422000 | BT74: 246290000 | BU74: 595883000 | BV74: 69077000 | CM74: 20000 | CN74: 38524000 | CO74: 49250000 | CP74: 49699000 | CW74: 11277000 | CX74: 28823000 | CY74: 70283000 | CZ74: 1367000 | DB74: 11277000 | DC74: 28823000 | DD74: 70283000 | DE74: 1367000 | DG74: 447000 | DH74: 1282000 | DI74: 4001000 | DJ74: 7116000 | DL74: 61678000 | DM74: 94245000 | DN74: 202879000 | DO74: 10895000 | DW74: 83416000 | DX74: 269470000 | EA74: 62125000 | EB74: 178943000 | EC74: 476350000 | ED74: 18011000 | EF74: 103441000 | EG74: 134381000 | EH74: 260155000 | EI74: 505987000 | EK74: 103077000 | EL74: 102004000 | EM74: 265371000 | EN74: 506028000 | FK74: 3000 | FL74: 37000 | FP74: 93000 | FQ74: 5367000 | FR74: 882000 | FT74: 379000 | FU74: 975000 | FV74: 8412000 | FW74: 393000 | FZ74: -7012000 | GA74: 2428000 | GB74: 90000 | GD74: -15000 | GE74: 38504000 | GF74: -10726000 | GG74: 358000
A75: 74 | B75: КОРПУСГРУПП УРАЛ, ООО | C75: 1076671021327 | D75: 18 | E75: Деятельность предприятий общественного питания по прочим видам организации питания | F75: 10812527 | G75: 17812054 | H75: 15546969 | I75: 6846349 | K75: 191818445 | L75: 160223630 | M75: 179763418 | N75: 86135356 | O75: 75905991 | P75: 11124000 | Q75: 25313000 | R75: 32916000 | S75: 12340000 | T75: 4154000 | AJ75: 11124000 | AK75: 25313000 | AL75: 32916000 | AM75: 12340000 | AN75: 115426000 | AO75: 175621000 | AP75: 311603000 | AQ75: 626056000 | AR75: 866477000 | AT75: 376301000 | AU75: 400596000 | AV75: 433257000 | AW75: 331430000 | AX75: 95094000 | AY75: 266558000 | AZ75: 411619000 | BA75: 455183000 | BB75: 622086000 | BC75: 574281000 | BD75: 13667000 | BE75: 14985000 | BF75: 4330000 | BG75: 9575000 | BH75: 63774000 | BI75: 49008000 | BJ75: 51708000 | BK75: 61388000 | BL75: 60746000 | BM75: 1018000 | BN75: 882766000 | BO75: 1192563000 | BP75: 1583738000 | BQ75: 1892741000 | BR75: 735166000 | BS75: 893890000 | BT75: 1217876000 | BU75: 1616654000 | BV75: 1905081000 | BW75: 850592000 | BX75: 500000 | BY75: 500000 | BZ75: 500000 | CA75: 500000 | CB75: 500000 | CH75: 121941000 | CI75: 253971000 | CJ75: 296636000 | CK75: 329842000 | CL75: -822445000 | CM75: 122441000 | CN75: 254471000 | CO75: 297136000 | CP75: 330342000 | CQ75: -821945000 | CR75: 532917000 | CS75: 455797000 | CT75: 865736000 | CU75: 1182029000 | CV75: 1139201000 | DB75: 532917000 | DC75: 455797000 | DD75: 865736000 | DE75: 1182029000 | DF75: 1139201000 | DG75: 31706000 | DH75: 33290000 | DI75: 39393000 | DJ75: 45939000 | DK75: 168833000 | DL75: 206826000 | DM75: 474318000 | DN75: 414016000 | DO75: 346771000 | DP75: 364503000 | DS75: 373000 | EA75: 238532000 | EB75: 507608000 | EC75: 453782000 | ED75: 392710000 | EE75: 533336000 | EF75: 2148293000 | EG75: 2557546000 | EH75: 2251574000 | EI75: 1765759000 | EJ75: 1055578000 | EK75: 1943662000 | EL75: 2303088000 | EM75: 2011850000 | EN75: 1511407000 | EO75: 1023101000 | EU75: 114889000 | EV75: 160185000 | EW75: 170150000 | EX75: 140109000 | EY75: 104352000 | FE75: 337000 | FI75: 1000 | FJ75: 44195000 | FK75: 41096000 | FL75: 54741000 | FM75: 88321000 | FN75: 155352000 | FO75: 968726000 | FP75: 1201805000 | FQ75: 291717000 | FR75: 68763000 | FS75: 67460000 | FT75: 962317000 | FU75: 1108690000 | FV75: 247354000 | FW75: 52471000 | FX75: 1118853000 | FY75: -11130000 | FZ75: -13438000 | GA75: -12872000 | GB75: -9008000 | GC75: 111269000 | GD75: 41156000 | GE75: 132028000 | GF75: 42972000 | GG75: 33206000 | GH75: -1167348000
A76: 75 | B76: КОСМОС СТРОЙ, ООО | C76: 1025900910155 | D76: 22 | E76: Строительство жилых и нежилых зданий | AJ76: 3127000 | AK76: 3121000 | AL76: 3115000 | AM76: 3109000 | AT76: 15000 | AU76: 37000 | BD76: 1207000 | BE76: 1038000 | BF76: 931000 | BG76: 764000 | BH76: 676000 | BN76: 1222000 | BO76: 1079000 | BP76: 931000 | BQ76: 764000 | BR76: 676000 | BS76: 4349000 | BT76: 4200000 | BU76: 4046000 | BV76: 3873000 | BW76: 676000 | BX76: 10000 | BY76: 10000 | BZ76: 10000 | CA76: 10000 | CB76: 10000 | CH76: -20150000 | CI76: -20332000 | CJ76: -20476000 | CK76: -20716000 | CL76: -23923000 | CM76: -20140000 | CN76: -20322000 | CO76: -20466000 | CP76: -20706000 | CQ76: -23913000 | CR76: 20731000 | DB76: 20731000 | DG76: 3129000 | DH76: 23860000 | DI76: 23860000 | DJ76: 23860000 | DK76: 23860000 | DL76: 591000 | DM76: 624000 | DN76: 652000 | DO76: 719000 | DP76: 729000 | DQ76: 38000 | DR76: 38000 | EA76: 3758000 | EB76: 24522000 | EC76: 24512000 | ED76: 24579000 | EE76: 24589000 | EF76: 4850000 | EK76: 4530000 | EP76: 173000 | EQ76: 25000 | EU76: 493000 | EV76: 167000 | EW76: 120000 | EX76: 170000 | EY76: 129000 | FO76: 27000 | FR76: 67000 | FS76: 42000 | FT76: 31000 | FU76: 16000 | FV76: 24000 | FW76: 137000 | FX76: 1000 | FY76: 62000 | FZ76: 26000 | GD76: -288000 | GE76: -182000 | GF76: -144000 | GG76: -240000 | GH76: -88000
A77: 76 | B77: КРОНА, ООО | C77: 1165958094631 | D77: 9 | E77: Производство пара и горячей воды (тепловой энергии) котельными | AT77: 7771000 | AU77: 15581000 | AV77: 15475000 | BE77: 3023000 | BF77: 787000 | BN77: 7771000 | BO77: 18604000 | BP77: 16262000 | BS77: 7771000 | BT77: 18604000 | BU77: 16263000 | CM77: -27821000 | CN77: -31121000 | CO77: -31800000 | DL77: 35592000 | DM77: 49725000 | DN77: 48063000 | EA77: 35592000 | EB77: 49725000 | EC77: 48063000 | FT77: 8595000 | FU77: 949000 | FV77: 680000 | GD77: -8595000 | GE77: -949000 | GF77: -680000
A78: 77 | B78: КУ, ООО | C78: 1075921000605 | D78: 18 | E78: Управление эксплуатацией жилого фонда за вознаграждение или на договорной основе | K78: 126177 | AT78: 29978000 | AU78: 40222000 | AV78: 39642000 | AW78: 37340000 | AX78: 35920000 | BD78: 1755000 | BE78: 1582000 | BF78: 1776000 | BG78: 1333000 | BH78: 563000 | BN78: 31733000 | BO78: 41804000 | BP78: 41418000 | BQ78: 38673000 | BR78: 36483000 | BS78: 31733000 | BT78: 41804000 | BU78: 41418000 | BV78: 38673000 | BW78: 36483000 | BX78: 10000 | BY78: 10000 | BZ78: 10000 | CA78: 10000 | CB78: 10000 | CH78: -67998000 | CI78: -13291000 | CJ78: -13291000 | CK78: -13291000 | CL78: -13291000 | CM78: -67988000 | CN78: -13281000 | CO78: -13281000 | CP78: -13281000 | CQ78: -13281000 | DG78: 99721000 | DM78: 55085000 | DN78: 54699000 | DO78: 51954000 | DP78: 49764000 | EA78: 99721000 | EB78: 55085000 | EC78: 54699000 | ED78: 51954000 | EE78: 49764000 | EV78: 1105000 | FT78: 373000 | GD78: -373000 | GE78: -1105000
A79: 78 | B79: КУНГУРСКАЯ БАЗА, ООО | C79: 1065917021180 | D79: 18 | E79: Деятельность по складированию и хранению | G79: 39259 | K79: 70233 | L79: 2344389 | M79: 3301796 | N79: 659959 | P79: 37161000 | Q79: 36738000 | R79: 22919000 | S79: 22824000 | U79: 44789000 | AE79: 6907000 | AF79: 6907000 | AG79: 9022000 | AH79: 8884000 | AI79: 863000 | AJ79: 88857000 | AK79: 43645000 | AL79: 38097000 | AM79: 37864000 | AN79: 863000 | AO79: 21919000 | AP79: 10008000 | AQ79: 3897000 | AR79: 2108000 | AS79: 14000 | AT79: 19937000 | AU79: 44891000 | AV79: 26682000 | AW79: 25305000 | AX79: 57987000 | AY79: 9981000 | AZ79: 10000 | BD79: 172000 | BE79: 21000 | BF79: 36000 | BG79: 2690000 | BH79: 11086000 | BI79: 21000 | BJ79: 10000 | BK79: 12000 | BN79: 59687000 | BO79: 54941000 | BP79: 30628000 | BQ79: 30103000 | BR79: 69087000 | BS79: 148544000 | BT79: 98586000 | BU79: 68725000 | BV79: 67967000 | BW79: 69950000 | BX79: 25000 | BY79: 25000 | BZ79: 25000 | CA79: 25000 | CB79: 25000 | CC79: 34671000 | CD79: 34671000 | CE79: 21231000 | CF79: 21231000 | CG79: 21231000 | CH79: -116310000 | CI79: -117503000 | CJ79: -130802000 | CK79: -130879000 | CL79: -129519000 | CM79: -45414000 | CN79: -46607000 | CO79: -73346000 | CP79: -73423000 | CQ79: -72063000 | CS79: 29693000 | CT79: 29693000 | CU79: 27733000 | CV79: 24975000 | DC79: 29693000 | DD79: 29693000 | DE79: 27733000 | DF79: 24975000 | DG79: 76452000 | DH79: 51409000 | DI79: 55850000 | DJ79: 56238000 | DK79: 56238000 | DL79: 117506000 | DM79: 64091000 | DN79: 56528000 | DO79: 57419000 | DP79: 60800000 | EA79: 193958000 | EB79: 115500000 | EC79: 112378000 | ED79: 113657000 | EE79: 117038000 | EF79: 66749000 | EG79: 302535000 | EH79: 53204000 | EI79: 5126000 | EJ79: 3131000 | EK79: 78808000 | EL79: 290189000 | EM79: 50749000 | EN79: 4938000 | EO79: 2492000 | ET79: 2000 | EU79: 3911000 | EV79: 4625000 | EW79: 3410000 | EX79: 2369000 | EY79: 1874000 | FE79: 121000 | FF79: 87000 | FJ79: 9432000 | FK79: 7602000 | FL79: 4702000 | FM79: 388000 | FO79: 1178000 | FP79: 37000 | FQ79: 10000 | FR79: 6973000 | FS79: 44148000 | FT79: 1248000 | FU79: 1426000 | FV79: 7651000 | FW79: 4483000 | FX79: 40749000 | GC79: -802000 | GD79: -26368000 | GE79: -1193000 | GF79: -13299000 | GG79: -79000 | GH79: 1360000
A80: 79 | B80: ЛДСУ, ООО | C80: 1115918000164 | D80: 32 | E80: Подготовка строительной площадки | F80: 151454 | H80: 978362 | I80: 2616109 | J80: 118150 | K80: 13361371 | L80: 159619 | M80: 1281836 | P80: 50332000 | Q80: 21264000 | R80: 8123000 | AB80: 5225000 | AJ80: 61409000 | AK80: 40589000 | AL80: 13348000 | AO80: 56451000 | AP80: 39145000 | AQ80: 117000 | AT80: 177539000 | AU80: 182346000 | AV80: 188389000 | AY80: 70000 | AZ80: 70000 | BE80: 5571000 | BF80: 2784000 | BI80: 1202000 | BJ80: 151000 | BN80: 236574000 | BO80: 228594000 | BP80: 191290000 | BS80: 297983000 | BT80: 269183000 | BU80: 204639000 | BX80: 2000000 | BY80: 2000000 | CC80: 8421000 | CD80: 8421000 | CH80: -2589000 | CI80: -24177000 | CM80: 7832000 | CN80: -13756000 | CO80: -49175000 | CR80: 119815000 | CS80: 102414000 | CT80: 71728000 | CW80: 6892000 | CX80: 1028000 | CY80: 2055000 | DB80: 138793000 | DC80: 105946000 | DD80: 73783000 | DL80: 151357000 | DM80: 176993000 | DN80: 180031000 | EA80: 151357000 | EB80: 176993000 | EC80: 180031000 | EF80: 53701000 | EG80: 4554000 | EK80: 57483000 | EL80: 14610000 | EM80: 4351000 | EU80: 5913000 | EV80: 16653000 | FJ80: 618000 | FO80: 67955000 | FP80: 24768000 | FQ80: 67600000 | FT80: 60231000 | FU80: 29095000 | FV80: 92202000 | FZ80: 5351000 | GA80: 6466000 | GD80: -2589000 | GE80: -21588000 | GF80: -35419000
A81: 80 | B81: ЛМЗ НОВЫЙ, ООО | C81: 1101828000647 | D81: 15 | E81: Покупка и продажа собственного недвижимого имущества | F81: 1177791 | G81: 1320471 | H81: 695479 | I81: 1935413 | K81: 7923324 | L81: 6616405 | M81: 9726176 | N81: 12346663 | O81: 688942 | P81: 53882000 | Q81: 175642000 | R81: 195577000 | S81: 333466000 | T81: 303046000 | AJ81: 54938000 | AK81: 176592000 | AL81: 196477000 | AM81: 339816000 | AN81: 319346000 | AO81: 26524000 | AP81: 43961000 | AQ81: 95507000 | AR81: 134907000 | AS81: 23307000 | AT81: 20654000 | AU81: 35584000 | AV81: 15237000 | AW81: 69272000 | AX81: 111728000 | AY81: 1110000 | AZ81: 3523000 | BA81: 3007000 | BB81: 2643000 | BC81: 2175000 | BD81: 105000 | BE81: 127000 | BF81: 292000 | BG81: 1524000 | BH81: 1000 | BL81: 238000 | BM81: 50000 | BN81: 55326000 | BO81: 94286000 | BP81: 124372000 | BQ81: 217894000 | BR81: 140627000 | BS81: 110264000 | BT81: 270878000 | BU81: 320849000 | BV81: 557710000 | BW81: 459973000 | BX81: 10000 | BY81: 10000 | BZ81: 10000 | CA81: 10000 | CB81: 10000 | CH81: 8353000 | CI81: 10913000 | CJ81: 21913000 | CK81: 24381000 | CL81: -145222000 | CM81: 8363000 | CN81: 10923000 | CO81: 21923000 | CP81: 24391000 | CQ81: -145212000 | CT81: 138380000 | CU81: 262756000 | CV81: 268006000 | DB81: 70000 | DD81: 138380000 | DE81: 262756000 | DF81: 268006000 | DG81: 12707000 | DH81: 140343000 | DI81: 1158000 | DJ81: 7702000 | DK81: 12747000 | DL81: 74124000 | DM81: 97869000 | DN81: 139388000 | DO81: 209782000 | DP81: 302264000 | DQ81: 15000000 | DR81: 21743000 | DS81: 20000000 | DT81: 20000000 | DU81: 20000000 | DY81: 33080000 | DZ81: 2168000 | EA81: 101831000 | EB81: 259955000 | EC81: 160546000 | ED81: 270563000 | EE81: 337179000 | EF81: 98235000 | EG81: 118347000 | EH81: 225414000 | EI81: 204459000 | EJ81: 30181000 | EK81: 83284000 | EL81: 91221000 | EM81: 183550000 | EN81: 173359000 | EO81: 51401000 | EP81: 4272000 | EU81: 6671000 | EV81: 15874000 | EW81: 13592000 | EX81: 9114000 | EY81: 13806000 | FE81: 36000 | FF81: 221000 | FG81: 284000 | FH81: 240000 | FI81: 85000 | FJ81: 135000 | FK81: 6386000 | FL81: 14787000 | FM81: 18240000 | FN81: 9768000 | FO81: 1591000 | FP81: 683000 | FQ81: 1749000 | FR81: 5537000 | FS81: 53915000 | FT81: 1090000 | FU81: 2491000 | FV81: 1737000 | FW81: 7056000 | FX81: 178810000 | FZ81: -732000 | GA81: -2780000 | GD81: 4410000 | GE81: 2547000 | GF81: 11001000 | GG81: 2467000 | GH81: -169604000
A82: 81 | B82: МАГИСТРАЛЬ, ООО | C82: 1155958049312 | D82: 10 | E82: Деятельность автомобильного грузового транспорта и услуги по перевозкам | F82: 2796571 | G82: 1808455 | H82: 324 | K82: 7414111 | L82: 5952640 | M82: 1521342 | P82: 48074000 | Q82: 37243000 | T82: 10000 | AJ82: 48074000 | AK82: 37243000 | AN82: 10000 | AT82: 50868000 | AU82: 18456000 | BD82: 4199000 | BE82: 5485000 | BF82: 10000 | BN82: 55067000 | BO82: 23941000 | BP82: 10000 | BS82: 103141000 | BT82: 61184000 | BU82: 10000 | BW82: 10000 | CM82: 3800000 | CN82: 1136000 | CO82: 10000 | CQ82: 10000 | CW82: 41701000 | CX82: 50620000 | DB82: 41701000 | DC82: 50620000 | DL82: 57009000 | DM82: 8536000 | DV82: 631000 | DW82: 892000 | EA82: 57640000 | EB82: 9428000 | EF82: 94629000 | EG82: 103260000 | EH82: 8100000 | EK82: 60082000 | EL82: 64236000 | EM82: 8100000 | FO82: 1200000 | FP82: 166000 | FT82: 31010000 | FU82: 33560000 | FY82: 947000 | FZ82: 1126000 | GD82: 3790000 | GE82: 4504000
A83: 82 | B83: МАГИСТРАЛЬСНАБ, ООО | C83: 1115905000595 | D83: 14 | E83: Торговля оптовая прочими строительными материалами и изделиями | F83: 277037 | G83: 488322 | H83: 714730 | J83: 35872 | K83: 1282998 | L83: 2372327 | M83: 638597 | N83: 717711 | O83: 2357991 | P83: 7065000 | Q83: 13004000 | R83: 7318000 | S83: 1635000 | T83: 383000 | Z83: 1105000 | AA83: 1105000 | AB83: 1105000 | AJ83: 8356000 | AK83: 14109000 | AL83: 8423000 | AM83: 1635000 | AN83: 383000 | AO83: 39210000 | AP83: 65329000 | AQ83: 37482000 | AR83: 6258000 | AT83: 17501000 | AU83: 37350000 | AV83: 28533000 | AW83: 25450000 | AX83: 13055000 | BD83: 1024000 | BE83: 146000 | BF83: 65000 | BG83: 16000 | BH83: 1000 | BI83: 2631000 | BJ83: 1905000 | BK83: 190000 | BL83: 149000 | BN83: 60367000 | BO83: 104730000 | BP83: 66270000 | BQ83: 31873000 | BR83: 13056000 | BS83: 68723000 | BT83: 118839000 | BU83: 74693000 | BV83: 33507000 | BW83: 13439000 | BX83: 10000 | BY83: 10000 | BZ83: 10000 | CA83: 10000 | CB83: 10000 | CH83: 1238000 | CI83: 280000 | CJ83: 1410000 | CK83: 1231000 | CL83: 934000 | CM83: 1248000 | CN83: 290000 | CO83: 1420000 | CP83: 1241000 | CQ83: 944000 | CV83: 311000 | CW83: 6972000 | CX83: 10434000 | CY83: 2881000 | CZ83: 1938000 | DB83: 7241000 | DC83: 10556000 | DD83: 3003000 | DE83: 1938000 | DF83: 311000 | DG83: 1784000 | DH83: 2312000 | DI83: 2312000 | DJ83: 1341000 | DK83: 1174000 | DL83: 58450000 | DM83: 105681000 | DN83: 67958000 | DO83: 28987000 | DP83: 11010000 | EA83: 60234000 | EB83: 107993000 | EC83: 70270000 | ED83: 30328000 | EE83: 12184000 | EF83: 95047000 | EG83: 199888000 | EH83: 66970000 | EI83: 20482000 | EJ83: 7933000 | EK83: 42039000 | EL83: 136121000 | EM83: 64095000 | EN83: 12907000 | EO83: 5636000 | EP83: 46993000 | EQ83: 46163000 | ER83: 3095000 | ES83: 770000 | ET83: 2242000 | EU83: 5177000 | EV83: 15499000 | EW83: 8216000 | EX83: 9023000 | EY83: 1688000 | FJ83: 7000 | FK83: 4438000 | FL83: 34000 | FO83: 692000 | FP83: 4262000 | FQ83: 14254000 | FR83: 2709000 | FS83: 1604000 | FT83: 1263000 | FU83: 2747000 | FV83: 4371000 | FW83: 670000 | FX83: 268000 | FY83: -144000 | FZ83: -295000 | GA83: -257000 | GD83: 138000 | GE83: -968000 | GF83: 1130000 | GG83: -179000 | GH83: -297000
A84: 83 | B84: МАЛАХИТ, ООО | C84: 1045901459185 | D84: 20 | E84: Управление эксплуатацией жилого фонда за вознаграждение или на договорной основе | AT84: 29931000 | AU84: 26551000 | AV84: 25385000 | AW84: 23563000 | AX84: 21295000 | BD84: 104000 | BE84: 1088000 | BF84: 345000 | BG84: 27000 | BH84: 82000 | BN84: 30035000 | BO84: 27639000 | BP84: 25730000 | BQ84: 23590000 | BR84: 21377000 | BS84: 30035000 | BT84: 27639000 | BU84: 25730000 | BV84: 23590000 | BW84: 21377000 | CM84: -23808000 | CN84: -25321000 | CO84: -26435000 | CP84: -27001000 | CQ84: -27372000 | DL84: 53843000 | DM84: 52960000 | DN84: 52165000 | DO84: 50591000 | DP84: 48749000 | EA84: 53843000 | EB84: 52960000 | EC84: 52165000 | ED84: 50591000 | EE84: 48749000 | EF84: 111000 | EK84: 127000 | FT84: 9587000 | FU84: 1513000 | FV84: 1114000 | FW84: 566000 | FX84: 371000 | FY84: 68000 | GD84: -9671000 | GE84: -1513000 | GF84: -1114000 | GG84: -566000 | GH84: -371000
A85: 84 | B85: МЗ КАМАСТАЛЬ, ООО | C85: 1025901382121 | D85: 25 | E85: Производство стали в слитках | I85: 13927553 | L85: 114033449 | M85: 183017000 | N85: 57030441 | P85: 159990000 | Q85: 159678000 | R85: 64000 | S85: 64000 | T85: 64000 | AJ85: 159990000 | AK85: 159678000 | AL85: 64000 | AM85: 64000 | AN85: 64000 | AO85: 57139000 | AP85: 36717000 | AQ85: 28240000 | AR85: 24874000 | AS85: 4245000 | AT85: 558738000 | AU85: 509638000 | AV85: 452620000 | AW85: 236132000 | AX85: 76854000 | BD85: 32000 | BE85: 32000 | BF85: 32000 | BG85: 122000 | BH85: 208000 | BI85: 1826000 | BJ85: 1826000 | BK85: 1826000 | BL85: 1826000 | BM85: 1526000 | BN85: 618007000 | BO85: 548308000 | BP85: 482813000 | BQ85: 262971000 | BR85: 82833000 | BS85: 777997000 | BT85: 707986000 | BU85: 482877000 | BV85: 263035000 | BW85: 82897000 | BX85: 210108000 | BY85: 210108000 | BZ85: 210108000 | CA85: 210108000 | CB85: 210108000 | CC85: 137000 | CD85: 137000 | CE85: 137000 | CF85: 137000 | CG85: 137000 | CH85: -5063307000 | CI85: -5084850000 | CJ85: -5139023000 | CK85: -4639525000 | CL85: -4781947000 | CM85: -4848684000 | CN85: -4870227000 | CO85: -4924400000 | CP85: -4424902000 | CQ85: -4567324000 | DB85: 2483000 | DC85: 2482000 | DD85: 2482000 | DE85: 2483000 | DF85: 2483000 | DG85: 90026000 | DH85: 90026000 | DI85: 90026000 | DJ85: 90026000 | DK85: 90026000 | DL85: 5495479000 | DM85: 5437254000 | DN85: 5260474000 | DO85: 4535288000 | DP85: 4491727000 | EA85: 5624198000 | EB85: 5575731000 | EC85: 5404795000 | ED85: 4685454000 | EE85: 4647738000 | EF85: 492000 | EG85: 11438000 | EH85: 3478000 | EI85: 350000 | EJ85: 9411000 | EK85: 1819000 | EL85: 25205000 | EM85: 8476000 | EN85: 3366000 | EO85: 19275000 | FO85: 16000 | FP85: 67804000 | FQ85: 133088000 | FR85: 519141000 | FS85: 199963000 | FT85: 8221000 | FU85: 31620000 | FV85: 158127000 | FW85: 16627000 | FX85: 332520000 | GD85: -43714000 | GE85: -21543000 | GF85: -54173000 | GG85: 499498000 | GH85: -142422000
A86: 85 | B86: МИР, ООО | C86: 1145958029733 | D86: 11 | E86: Торговля розничная прочая в неспециализированных магазинах | BF86: 254000 | BP86: 254000 | BU86: 254000 | CM86: -13140000 | CN86: -13140000 | CO86: -13641000 | CP86: -13899000 | CQ86: -14259000 | DL86: 13140000 | DM86: 13140000 | DN86: 13895000 | DO86: 13899000 | DP86: 14259000 | EA86: 13140000 | EB86: 13140000 | EC86: 13895000 | ED86: 13899000 | EE86: 14259000
A87: 86 | B87: МК ЮНИКС, ООО | C87: 1026605392923 | D87: 25 | E87: Торговля оптовая техникой, оборудованием и инструментами, применяемыми в медицинских целях | G87: 134843 | K87: 646402 | P87: 44884000 | Q87: 3126000 | R87: 3124000 | S87: 3122000 | T87: 3120000 | Z87: 129961000 | AA87: 129961000 | AB87: 129961000 | AC87: 125047000 | AD87: 125047000 | AE87: 1362000 | AF87: 1362000 | AG87: 1362000 | AH87: 1362000 | AI87: 1362000 | AJ87: 346665000 | AK87: 304907000 | AL87: 304905000 | AM87: 299989000 | AN87: 299987000 | AO87: 332660000 | AP87: 327623000 | AQ87: 271348000 | AR87: 235636000 | AS87: 235636000 | AT87: 1544265000 | AU87: 1522381000 | AV87: 1454858000 | AW87: 1448260000 | AX87: 1448260000 | AY87: 463000 | AZ87: 463000 | BA87: 463000 | BB87: 463000 | BC87: 463000 | BD87: 29529000 | BE87: 59995000 | BF87: 39489000 | BG87: 33155000 | BH87: 23368000 | BI87: 467262000 | BJ87: 37280000 | BK87: 37982000 | BL87: 37982000 | BM87: 37982000 | BN87: 2375109000 | BO87: 1948672000 | BP87: 1805070000 | BQ87: 1756426000 | BR87: 1746639000 | BS87: 2721774000 | BT87: 2253579000 | BU87: 2109975000 | BV87: 2056415000 | BW87: 2046626000 | BX87: 70000000 | BY87: 70000000 | BZ87: 70000000 | CA87: 70000000 | CB87: 70000000 | CC87: 70671000 | CD87: 70671000 | CE87: 70671000 | CF87: 70671000 | CG87: 70671000 | CH87: 194514000 | CI87: -248925000 | CJ87: -380653000 | CK87: -436034000 | CL87: -438631000 | CM87: 345685000 | CN87: -97754000 | CO87: -229482000 | CP87: -284863000 | CQ87: -287460000 | DG87: 1187063000 | DH87: 1182811000 | DI87: 1175022000 | DJ87: 1175022000 | DK87: 1168216000 | DL87: 1189026000 | DM87: 1168522000 | DN87: 1164435000 | DO87: 1166256000 | DP87: 1165870000 | EA87: 2376089000 | EB87: 2351333000 | EC87: 2339457000 | ED87: 2341278000 | EE87: 2334086000 | EF87: 21373000 | EG87: 45922000 | EH87: 9000000 | EK87: 29630000 | EL87: 40890000 | EM87: 123520000 | FF87: 152000 | FK87: 27000 | FO87: 6477000 | FP87: 53000 | FQ87: 674000 | FR87: 10769000 | FS87: 206000 | FT87: 30074000 | FU87: 448649000 | FV87: 17882000 | FW87: 66150000 | FX87: 2803000 | GD87: -31854000 | GE87: -443439000 | GF87: -131728000 | GG87: -55381000 | GH87: -2597000
A88: 87 | B88: МЭК, ООО | C88: 1145958031438 | D88: 11 | E88: Производство пара и горячей воды (тепловой энергии) котельными | P88: 103000 | Q88: 103000 | R88: 103000 | S88: 103000 | T88: 103000 | AJ88: 7236000 | AK88: 7236000 | AL88: 7236000 | AM88: 7236000 | AN88: 7236000 | AT88: 24187000 | AU88: 22198000 | AV88: 7356000 | AW88: 6881000 | AX88: 6881000 | BE88: 2641000 | BF88: 3232000 | BG88: 2197000 | BH88: 2197000 | BN88: 24494000 | BO88: 25146000 | BP88: 10895000 | BQ88: 9385000 | BR88: 9385000 | BS88: 31730000 | BT88: 32382000 | BU88: 18131000 | BV88: 16621000 | BW88: 16621000 | BX88: 10000 | BY88: 10000 | BZ88: 10000 | CA88: 10000 | CB88: 10000 | CH88: -38594000 | CI88: -39359000 | CJ88: -40199000 | CK88: -40559000 | CL88: -40559000 | CM88: -38584000 | CN88: -39349000 | CO88: -40189000 | CP88: -40549000 | CQ88: -40549000 | CR88: 543000 | CS88: 543000 | CT88: 543000 | CU88: 543000 | CV88: 543000 | DB88: 543000 | DC88: 543000 | DD88: 543000 | DE88: 543000 | DF88: 543000 | DL88: 69219000 | DM88: 70636000 | DN88: 57225000 | DO88: 56075000 | DP88: 56075000 | EA88: 69771000 | EB88: 71188000 | EC88: 57777000 | ED88: 56627000 | EE88: 56627000 | FE88: 27000 | FJ88: 16000 | FT88: 2791000 | FU88: 765000 | FV88: 840000 | FW88: 360000 | GD88: -2780000 | GE88: -765000 | GF88: -840000 | GG88: -360000
A89: 88 | B89: МЯСНОЙ ТРЕСТ В.Е.С., ООО | C89: 1065468009837 | D89: 19 | E89: Торговля розничная продуктами из мяса и мяса птицы в специализированных магазинах | L89: 439 | R89: 11838000 | S89: 11838000 | T89: 11838000 | AL89: 11838000 | AM89: 11838000 | AN89: 11838000 | AT89: 2558000 | AU89: 2558000 | AV89: 2558000 | AW89: 2558000 | AX89: 2558000 | BN89: 2558000 | BO89: 2558000 | BP89: 2558000 | BQ89: 2558000 | BR89: 2558000 | BS89: 2558000 | BT89: 2558000 | BU89: 14396000 | BV89: 14396000 | BW89: 14396000 | BX89: 121031000 | BY89: 121031000 | BZ89: 121031000 | CA89: 121031000 | CB89: 121031000 | CH89: -266006000 | CI89: -267183000 | CJ89: -255345000 | CK89: -255345000 | CL89: -257391000 | CM89: -144975000 | CN89: -146152000 | CO89: -134314000 | CP89: -134314000 | CQ89: -136360000 | DL89: 147533000 | DM89: 148710000 | DN89: 148710000 | DO89: 148710000 | DP89: 150756000 | EA89: 147533000 | EB89: 148710000 | EC89: 148710000 | ED89: 148710000 | EE89: 150756000 | EF89: 18993000 | FT89: 18996000 | FU89: 1187000 | FV89: 1320000 | FW89: 1320000 | FX89: 1320000 | GD89: -3000 | GE89: -1187000 | GF89: -1320000 | GG89: -1320000 | GH89: -1320000
A90: 89 | B90: НАДОМАРКЕТ, ООО | C90: 1025401916715 | D90: 24 | E90: Торговля розничная прочими бытовыми изделиями в специализированных магазинах | F90: 3185079 | G90: 5610604 | H90: 3285773 | I90: 5106549 | J90: 2953965 | K90: 74984846 | L90: 51449987 | M90: 47001196 | N90: 58323809 | O90: 52883953 | P90: 14016000 | Q90: 14759000 | R90: 282944000 | S90: 439288000 | T90: 370661000 | AE90: 3748000 | AF90: 2348000 | AG90: 1855000 | AH90: 1585000 | AI90: 677000 | AJ90: 17865000 | AK90: 17184000 | AL90: 284854000 | AM90: 440909000 | AN90: 371356000 | AO90: 591313000 | AP90: 618765000 | AQ90: 592607000 | AR90: 586718000 | AS90: 338042000 | AT90: 76543000 | AU90: 58086000 | AV90: 53439000 | AW90: 55332000 | AX90: 45934000 | BD90: 12162000 | BE90: 23876000 | BF90: 25167000 | BG90: 31468000 | BH90: 27697000 | BI90: 27196000 | BJ90: 26926000 | BK90: 29004000 | BL90: 29379000 | BM90: 25315000 | BN90: 707266000 | BO90: 727820000 | BP90: 700249000 | BQ90: 703154000 | BR90: 437037000 | BS90: 725131000 | BT90: 745004000 | BU90: 985103000 | BV90: 1144063000 | BW90: 808393000 | BX90: 20000 | BY90: 20000 | BZ90: 20000 | CA90: 20000 | CB90: 20000 | CH90: 145367000 | CI90: 163395000 | CJ90: 174867000 | CK90: 185627000 | CL90: -99926000 | CM90: 145387000 | CN90: 163415000 | CO90: 174887000 | CP90: 185647000 | CQ90: -99906000 | CR90: 128313000 | CS90: 75000000 | CT90: 95072000 | CU90: 105000000 | CV90: 137283000 | CW90: 49000 | CX90: 449000 | CY90: 269654000 | CZ90: 398933000 | DA90: 331300000 | DB90: 128362000 | DC90: 75449000 | DD90: 364726000 | DE90: 503933000 | DF90: 468583000 | DG90: 5627000 | DH90: 42211000 | DK90: 5300000 | DL90: 445755000 | DM90: 463929000 | DN90: 445490000 | DO90: 454484000 | DP90: 434417000 | EA90: 451382000 | EB90: 506140000 | EC90: 445490000 | ED90: 454484000 | EE90: 439717000 | EF90: 1046987000 | EG90: 941381000 | EH90: 858086000 | EI90: 752211000 | EJ90: 591349000 | EK90: 665981000 | EL90: 583857000 | EM90: 504924000 | EN90: 381565000 | EO90: 374650000 | EP90: 329316000 | EQ90: 317518000 | ER90: 307990000 | ES90: 313832000 | ET90: 356823000 | FE90: 274000 | FF90: 73000 | FG90: 686000 | FH90: 112000 | FJ90: 11207000 | FK90: 10155000 | FL90: 16481000 | FM90: 15360000 | FN90: 30303000 | FO90: 26004000 | FP90: 56678000 | FQ90: 35914000 | FR90: 6352000 | FS90: 16282000 | FT90: 48994000 | FU90: 64448000 | FV90: 43067000 | FW90: 32677000 | FX90: 131408000 | FY90: -4976000 | FZ90: -4126000 | GA90: -5252000 | GB90: -4481000 | GD90: 12791000 | GE90: 18028000 | GF90: 16972000 | GG90: 10760000 | GH90: -285553000
A91: 90 | B91: НАРАТАЙ ЭНЕРДЖИ, ООО ИК | C91: 1205400010584 | D91: 5 | E91: Производство электромонтажных работ | F91: 609122 | G91: 498347 | H91: 303956 | J91: 186405 | K91: 30431 | L91: 2451984 | M91: 266480 | N91: 1979156 | O91: 5266197 | P91: 1487000 | Q91: 1200000 | R91: 913000 | S91: 5320000 | T91: 2797000 | AG91: 29283000 | AH91: 6057000 | AJ91: 1487000 | AK91: 1200000 | AL91: 30196000 | AM91: 11377000 | AN91: 2797000 | AO91: 17743000 | AP91: 168287000 | AQ91: 236688000 | AR91: 124090000 | AS91: 13640000 | AT91: 52115000 | AU91: 149659000 | AV91: 1000000 | AW91: 6914000 | AX91: 131742000 | AY91: 6368000 | AZ91: 7321000 | BA91: 250000 | BC91: 327000 | BD91: 416000 | BE91: 12459000 | BF91: 7404000 | BG91: 12074000 | BH91: 436000 | BI91: 9000 | BJ91: 13245000 | BK91: 38142000 | BL91: 5172000 | BN91: 77708000 | BO91: 352704000 | BP91: 284270000 | BQ91: 151027000 | BR91: 146144000 | BS91: 79195000 | BT91: 353905000 | BU91: 314466000 | BV91: 162404000 | BW91: 148941000 | BX91: 20000 | BY91: 20000 | BZ91: 20000 | CA91: 20000 | CB91: 20000 | CH91: 3114000 | CI91: 3515000 | CJ91: 4740000 | CK91: 7216000 | CL91: 12627000 | CM91: 3134000 | CN91: 3535000 | CO91: 4760000 | CP91: 7236000 | CQ91: 12647000 | CW91: 58126000 | CX91: 169784000 | CY91: 110254000 | CZ91: 28881000 | DB91: 58126000 | DC91: 169784000 | DD91: 110254000 | DE91: 28881000 | DL91: 17935000 | DM91: 180586000 | DN91: 199453000 | DO91: 126287000 | DP91: 136295000 | EA91: 17935000 | EB91: 180586000 | EC91: 199453000 | ED91: 126287000 | EE91: 136295000 | EF91: 44333000 | EG91: 102261000 | EH91: 211994000 | EI91: 325800000 | EJ91: 47524000 | EK91: 37152000 | EL91: 50912000 | EM91: 117149000 | EN91: 216388000 | EO91: 11419000 | EU91: 6274000 | EV91: 46795000 | EW91: 96712000 | EX91: 103251000 | EY91: 36299000 | FO91: 29291000 | FP91: 7933000 | FQ91: 6682000 | FR91: 3792000 | FS91: 676000 | FT91: 26306000 | FU91: 11985000 | FV91: 3285000 | FW91: 6858000 | FX91: 128000 | FY91: -778000 | FZ91: -100000 | GA91: -306000 | GB91: -619000 | GC91: -71000 | GD91: 3114000 | GE91: 402000 | GF91: 1224000 | GG91: 2476000 | GH91: 283000
A92: 91 | B92: НИВА, ООО | C92: 1025902547098 | D92: 33 | E92: Разведение молочного крупного рогатого скота, производство сырого молока | F92: 600 | G92: 242 | J92: 71874 | K92: 1077060 | L92: 227240 | M92: 428619 | N92: 2691 | O92: 334899 | P92: 374303000 | Q92: 354156000 | R92: 337254000 | S92: 241143000 | T92: 120881000 | Z92: 180043000 | AA92: 180010000 | AB92: 180010000 | AJ92: 554346000 | AK92: 534166000 | AL92: 517264000 | AM92: 241143000 | AN92: 120881000 | AO92: 78127000 | AP92: 68695000 | AQ92: 104474000 | AR92: 14662000 | AS92: 10017000 | AT92: 34633000 | AU92: 3552000 | AV92: 6165000 | AW92: 1564000 | AX92: 398000 | AY92: 119580000 | AZ92: 119580000 | BA92: 119580000 | BB92: 33000 | BD92: 134000 | BE92: 1242000 | BF92: 306000 | BG92: 1298000 | BH92: 20895000 | BI92: 5966000 | BJ92: 10000 | BK92: 13000 | BN92: 238448000 | BO92: 193078000 | BP92: 230539000 | BQ92: 17557000 | BR92: 31310000 | BS92: 792794000 | BT92: 727244000 | BU92: 747802000 | BV92: 258700000 | BW92: 152191000 | BX92: 246358000 | BY92: 246358000 | BZ92: 246358000 | CA92: 246358000 | CB92: 246358000 | CH92: 131155000 | CI92: 98337000 | CJ92: 108430000 | CK92: -356628000 | CL92: -449501000 | CM92: 389393000 | CN92: 356575000 | CO92: 366668000 | CP92: -98390000 | CQ92: -191263000 | CR92: 121591000 | CS92: 120306000 | CT92: 120306000 | DB92: 121591000 | DC92: 120306000 | DD92: 120306000 | DG92: 78760000 | DH92: 55446000 | DI92: 55446000 | DL92: 203050000 | DM92: 194916000 | DN92: 205382000 | DO92: 357090000 | DP92: 343454000 | EA92: 281810000 | EB92: 250362000 | EC92: 260828000 | ED92: 357090000 | EE92: 343454000 | EF92: 131908000 | EG92: 115565000 | EH92: 57798000 | EI92: 17191000 | EJ92: 2700000 | EK92: 125976000 | EL92: 152127000 | EM92: 44797000 | EN92: 11687000 | EW92: 2504000 | EX92: 1462000 | FJ92: 24495000 | FK92: 1120000 | FO92: 18727000 | FP92: 13054000 | FR92: 2100000 | FS92: 32696000 | FT92: 1302000 | FU92: 8189000 | FV92: 405000 | FW92: 493000 | FX92: 145130000 | GD92: -1138000 | GE92: -32817000 | GF92: 10092000 | GG92: 5649000 | GH92: -109734000
A93: 92 | B93: НИИК, АО | C93: 1025201752597 | D93: 32 | E93: Деятельность в области инженерных изысканий, инженерно-технического проектирования, управления проектами строительства, выполнения строительного контроля и авторского надзора, предоставление технических консультаций в этих областях | F93: 13062098 | G93: 8772799 | H93: 1936258 | J93: 3774834 | L93: 135518944 | M93: 285884470 | N93: 8426257 | O93: 35361814 | P93: 198330000 | Q93: 156999000 | R93: 138579000 | Z93: 19500000 | AA93: 19500000 | AB93: 19500000 | AJ93: 229434000 | AK93: 177713000 | AL93: 177903000 | AO93: 3388562000 | AP93: 846489000 | AQ93: 600421000 | AT93: 14857882000 | AU93: 16923024000 | AV93: 3602373000 | AY93: 660081000 | AZ93: 19510000 | BA93: 5465000 | BD93: 44224000 | BE93: 23066000 | BF93: 103185000 | BI93: 73722000 | BJ93: 147778000 | BK93: 181458000 | BN93: 19034224000 | BO93: 17960149000 | BP93: 4492902000 | BS93: 19263658000 | BT93: 18137862000 | BU93: 4670805000 | BX93: 7000 | BY93: 7000 | BZ93: 7000 | CC93: 13939000 | CD93: 13939000 | CE93: 13939000 | CH93: 1218163000 | CI93: 1207582000 | CJ93: 1204812000 | CM93: 1232325000 | CN93: 1221744000 | CO93: 1218974000 | CR93: 86242000 | DB93: 86249000 | DC93: 7000 | DD93: 28594000 | DG93: 2330775000 | DH93: 1684073000 | DI93: 1690935000 | DL93: 15602742000 | DM93: 15231757000 | DN93: 1732302000 | DW93: 281000 | EA93: 17945084000 | EB93: 16916111000 | EC93: 3423237000 | EF93: 5527706000 | EG93: 4548439000 | EH93: 1204798000 | EK93: 5116159000 | EL93: 4149345000 | EM93: 1092947000 | EP93: 109560000 | EQ93: 52959000 | ER93: 14745000 | EV93: 34824000 | EW93: 31360000 | FE93: 32094000 | FF93: 16797000 | FG93: 1111000 | FJ93: 211234000 | FK93: 127483000 | FL93: 9613000 | FO93: 1385171000 | FP93: 678637000 | FQ93: 372324000 | FT93: 1460256000 | FU93: 883210000 | FV93: 419023000 | FY93: -20629000 | FZ93: -6502000 | GA93: -9827000 | GD93: 27133000 | GE93: -10450000 | GF93: 628000
A94: 93 | B94: НПО НОРТ, ООО | C94: 1021801158830 | D94: 32 | E94: Производство прочих красок, лаков, эмалей и аналогичных материалов для нанесения покрытий, художественных и полиграфических красок | F94: 719431 | G94: 1723591 | H94: 3042514 | I94: 20320726 | K94: 6300427 | L94: 19564187 | M94: 32655157 | N94: 2413915 | P94: 1551000 | Q94: 4480000 | R94: 2155000 | S94: 1200000 | Z94: 214000 | AA94: 145000 | AB94: 95000 | AC94: 1000 | AJ94: 1765000 | AK94: 4625000 | AL94: 2250000 | AM94: 1201000 | AO94: 250358000 | AP94: 217253000 | AQ94: 123074000 | AR94: 310000 | AT94: 52258000 | AU94: 43419000 | AV94: 99736000 | AW94: 74650000 | BD94: 4404000 | BE94: 7540000 | BF94: 1600000 | BG94: 334000 | BN94: 307020000 | BO94: 268212000 | BP94: 224410000 | BQ94: 75294000 | BS94: 308785000 | BT94: 272837000 | BU94: 226661000 | BV94: 76495000 | CM94: 93569000 | CN94: 95614000 | CO94: 96887000 | CP94: -110884000 | CZ94: 178000 | DE94: 178000 | DG94: 45035000 | DH94: 31095000 | DI94: 1375000 | DJ94: 1377000 | DL94: 170181000 | DM94: 146128000 | DN94: 128399000 | DO94: 185824000 | EA94: 215216000 | EB94: 177223000 | EC94: 129774000 | ED94: 187201000 | EF94: 319376000 | EG94: 324907000 | EH94: 371634000 | EI94: 6275000 | EK94: 306854000 | EL94: 324505000 | EM94: 351997000 | EN94: 115651000 | FJ94: 720000 | FK94: 2037000 | FL94: 786000 | FM94: 2000 | FO94: 3370000 | FP94: 19517000 | FQ94: 6528000 | FR94: 403000 | FT94: 3509000 | FU94: 14435000 | FV94: 24106000 | FW94: 97326000 | FY94: 2520000 | FZ94: 1402000 | GB94: 1470000 | GD94: 9143000 | GE94: 2045000 | GF94: 1273000 | GG94: -207771000
A95: 94 | B95: НФТ, АО | C95: 1125920002735 | D95: 13 | E95: Производство стальных труб, полых профилей и фитингов | K95: 855149 | L95: 79030 | P95: 3624804000 | Q95: 7068000 | R95: 49000 | S95: 49000 | T95: 49000 | AJ95: 4160432000 | AK95: 7221000 | AL95: 283000 | AM95: 174000 | AN95: 174000 | AO95: 450077000 | AP95: 382318000 | AV95: 252117000 | AW95: 251186000 | AX95: 1675000 | BE95: 71571000 | BF95: 74771000 | BI95: 80732000 | BN95: 530811000 | BO95: 453778000 | BP95: 326887000 | BQ95: 251186000 | BR95: 1675000 | BS95: 4691243000 | BT95: 460999000 | BU95: 327170000 | BV95: 251360000 | BW95: 1849000 | BX95: 100000 | BY95: 100000 | BZ95: 100000 | CA95: 100000 | CB95: 100000 | CH95: -3467255000 | CI95: -4065423000 | CJ95: -894107000 | CK95: -1420229000 | CL95: -1729194000 | CM95: -2267155000 | CN95: -2865323000 | CO95: -894007000 | CP95: -1420129000 | CQ95: -1729094000 | CR95: 5268916000 | CS95: 1800761000 | DB95: 5420837000 | DC95: 1800761000 | DG95: 698978000 | DH95: 698978000 | DL95: 838584000 | DM95: 826583000 | DN95: 1221177000 | DO95: 1671489000 | DP95: 1730943000 | EA95: 1537562000 | EB95: 1525561000 | EC95: 1221177000 | ED95: 1671489000 | EE95: 1730943000 | EF95: 1893000 | EK95: 24991000 | FF95: 1000 | FJ95: 84063000 | FO95: 338849000 | FP95: 1727137000 | FQ95: 116000 | FT95: 771022000 | FU95: 3551869000 | FV95: 4455000 | GD95: -539334000 | GE95: -1824731000 | GF95: -4339000
A96: 95 | B96: НЭС, ООО | C96: 1205900000778 | D96: 5 | E96: Строительство коммунальных объектов для обеспечения электроэнергией и телекоммуникациями | F96: 2515 | G96: 53034 | H96: 211783 | I96: 1322280 | J96: 321223 | K96: 139176 | L96: 258290 | M96: 2677830 | N96: 6355336 | O96: 4688233 | P96: 86000 | Q96: 10157000 | R96: 8598000 | S96: 6314000 | T96: 70000 | AJ96: 86000 | AK96: 10157000 | AL96: 8598000 | AM96: 6314000 | AN96: 70000 | AO96: 2355000 | AP96: 14378000 | AQ96: 14704000 | AR96: 77380000 | AS96: 105438000 | AT96: 5831000 | AU96: 12763000 | AV96: 21132000 | AW96: 38150000 | AX96: 37134000 | BD96: 1560000 | BE96: 67000 | BF96: 11434000 | BG96: 1889000 | BH96: 89000 | BN96: 9746000 | BO96: 27208000 | BP96: 47270000 | BQ96: 117419000 | BR96: 142661000 | BS96: 9832000 | BT96: 37365000 | BU96: 55868000 | BV96: 123733000 | BW96: 142731000 | CM96: 97000 | CN96: 1881000 | CO96: 16647000 | CP96: 20236000 | CQ96: 20783000 | CR96: 4000000 | CS96: 15915000 | CT96: 10665000 | CU96: 49388000 | CV96: 49211000 | CX96: 10419000 | CY96: 6366000 | DB96: 4000000 | DC96: 26334000 | DD96: 17031000 | DE96: 49388000 | DF96: 49211000 | DG96: 650000 | DH96: 1373000 | DI96: 1370000 | DL96: 5085000 | DM96: 7777000 | DN96: 20820000 | DO96: 54109000 | DP96: 72737000 | EA96: 5735000 | EB96: 9150000 | EC96: 22190000 | ED96: 54109000 | EE96: 72737000 | EF96: 28948000 | EG96: 47747000 | EH96: 93383000 | EI96: 133381000 | EJ96: 104332000 | EK96: 28781000 | EL96: 45487000 | EM96: 91694000 | EN96: 128465000 | EO96: 104154000 | FK96: 157000 | FL96: 684000 | FM96: 1753000 | FN96: 5021000 | FQ96: 30000 | FR96: 3821000 | FS96: 22652000 | FT96: 61000 | FU96: 134000 | FV96: 603000 | FW96: 4068000 | FX96: 17060000 | FY96: 20000 | FZ96: 185000 | GA96: 223000 | GB96: 762000 | GC96: 549000 | GD96: 86000 | GE96: 1784000 | GF96: 209000 | GG96: 2154000 | GH96: 200000
A97: 96 | B97: ОБОРОНЭКСПЕРТИЗА, ООО | C97: 1127746416379 | D97: 13 | E97: Деятельность в области архитектуры, инженерных изысканий и предоставление технических консультаций в этих областях | I97: 15435 | J97: 7 | K97: 31289 | N97: 688081 | O97: 978586 | R97: 72524000 | S97: 72524000 | T97: 72524000 | AL97: 72524000 | AM97: 72524000 | AN97: 72524000 | AT97: 10013000 | AY97: 81851000 | BD97: 220000 | BF97: 15000 | BH97: 628000 | BI97: 216846000 | BJ97: 298697000 | BK97: 226087000 | BN97: 308930000 | BO97: 298697000 | BP97: 226102000 | BR97: 628000 | BS97: 308930000 | BT97: 298697000 | BU97: 298626000 | BV97: 72524000 | BW97: 73152000 | BX97: 20000 | BY97: 20000 | BZ97: 20000 | CA97: 20000 | CB97: 20000 | CH97: -74194000 | CI97: -84916000 | CJ97: -85006000 | CK97: -309596000 | CL97: -308390000 | CM97: -74174000 | CN97: -84896000 | CO97: -84986000 | CP97: -309576000 | CQ97: -308370000 | CR97: 70000000 | CS97: 76608000 | CT97: 76608000 | CU97: 76608000 | CV97: 76608000 | DB97: 70000000 | DC97: 76608000 | DD97: 76608000 | DE97: 76608000 | DF97: 76608000 | DG97: 6608000 | DL97: 306496000 | DM97: 306985000 | DN97: 307004000 | DO97: 305492000 | DP97: 304914000 | EA97: 313104000 | EB97: 306985000 | EC97: 307004000 | ED97: 305492000 | EE97: 304914000 | EU97: 3167000 | FO97: 8333000 | FQ97: 2944000 | FR97: 5795000 | FS97: 6061000 | FT97: 80695000 | FU97: 10722000 | FV97: 3016000 | FW97: 230010000 | FX97: 4533000 | GA97: -18000 | GB97: -375000 | GC97: -322000 | GD97: -75529000 | GE97: -10722000 | GF97: -90000 | GG97: -224590000 | GH97: 1206000
A98: 97 | B98: ОБРАЗОВАНИЕ (АО), АКИБ | C98: 1027739265355 | D98: 34 | E98: Денежное посредничество прочее
A99: 98 | B99: ОЙЛ-СЕРВИС, ООО | C99: 1115906005093 | D99: 14 | E99: Перевозка грузов специализированными автотранспортными средствами | G99: 1006 | K99: 1836297 | L99: 94
A100: 99 | B100: ОП ПАРТНЕР, ООО | C100: 1105914000807 | D100: 14 | E100: Производство пара и горячей воды (тепловой энергии) котельными | K100: 51480 | L100: 144522 | M100: 12051 | AT100: 70626000 | AU100: 111667000 | AV100: 120998000 | AW100: 117837000 | AX100: 115394000 | BD100: 100000 | BE100: 455000 | BG100: 40000 | BN100: 70726000 | BO100: 112122000 | BP100: 120998000 | BQ100: 117877000 | BR100: 115394000 | BS100: 70726000 | BT100: 112122000 | BU100: 120998000 | BV100: 117877000 | BW100: 115394000 | BX100: 10000 | BY100: 10000 | BZ100: 10000 | CA100: 10000 | CB100: 10000 | CH100: 1063000 | CI100: 1159000 | CJ100: -801000 | CK100: -2310000 | CL100: -3569000 | CM100: 1073000 | CN100: 1169000 | CO100: -791000 | CP100: -2300000 | CQ100: -3559000 | DL100: 69653000 | DM100: 110953000 | DN100: 121789000 | DO100: 120177000 | DP100: 118953000 | EA100: 69653000 | EB100: 110953000 | EC100: 121789000 | ED100: 120177000 | EE100: 118953000 | EH100: 56137000 | EI100: 161000 | EM100: 57653000 | ET100: 1231000 | EX100: 1701000 | FR100: 62000 | FX100: 28000 | GA100: -444000 | GB100: -31000 | GF100: -1960000 | GG100: -1509000 | GH100: -1259000
...

Sheet Лист2
A3: Названия строк | B3: Количество по полю Вид деятельности/отрасль
A4: Аренда и лизинг грузовых транспортных средств | B4: 1
A5: Аренда и лизинг сельскохозяйственных машин и оборудования | B5: 1
A6: Аренда и управление собственным или арендованным недвижимым имуществом | B6: 2
A7: Аренда и управление собственным или арендованным нежилым недвижимым имуществом | B7: 1
A8: Денежное посредничество прочее | B8: 13
A9: Деятельность автомобильного грузового транспорта | B9: 2
A10: Деятельность автомобильного грузового транспорта и услуги по перевозкам | B10: 3
A11: Деятельность агентов по оптовой торговле радио- и телеаппаратурой, техническими носителями информации | B11: 1
A12: Деятельность агентов по оптовой торговле строительными материалами | B12: 1
A13: Деятельность административно-хозяйственная комплексная по обеспечению работы организации | B13: 1
A14: Деятельность в области архитектуры, инженерных изысканий и предоставление технических консультаций в этих областях | B14: 1
A15: Деятельность в области архитектуры, связанная с созданием архитектурного объекта | B15: 1
... A133: Общий итог | B133: 252

Sheet Выборка 1
A1: № | B1: Возраст компании, лет | C1: Вид деятельности/отрасль | D1: 2020, Основные средства , RUB | E1: 2021, Основные средства , RUB | F1: 2022, Основные средства , RUB | G1: 2023, Основные средства , RUB | H1: 2024, Основные средства , RUB | I1: 2020, Запасы, RUB | J1: 2021, Запасы, RUB | K1: 2022, Запасы, RUB | L1: 2023, Запасы, RUB | M1: 2024, Запасы, RUB | N1: 2020, Дебиторская задолженность, RUB | O1: 2021, Дебиторская задолженность, RUB | P1: 2022, Дебиторская задолженность, RUB | Q1: 2023, Дебиторская задолженность, RUB | R1: 2024, Дебиторская задолженность, RUB | S1: 2020, Денежные средства и денежные эквиваленты, RUB | T1: 2021, Денежные средства и денежные эквиваленты, RUB | U1: 2022, Денежные средства и денежные эквиваленты, RUB | V1: 2023, Денежные средства и денежные эквиваленты, RUB | W1: 2024, Денежные средства и денежные эквиваленты, RUB | X1: 2020, Нераспределенная прибыль (непокрытый убыток), RUB | Y1: 2021, Нераспределенная прибыль (непокрытый убыток), RUB | Z1: 2022, Нераспределенная прибыль (непокрытый убыток), RUB | AA1: 2023, Нераспределенная прибыль (непокрытый убыток), RUB | AB1: 2024, Нераспределенная прибыль (непокрытый убыток), RUB | AC1: 2020, Заёмные средства (краткосрочные), RUB | AD1: 2021, Заёмные средства (краткосрочные), RUB | AE1: 2022, Заёмные средства (краткосрочные), RUB | AF1: 2023, Заёмные средства (краткосрочные), RUB | AG1: 2024, Заёмные средства (краткосрочные), RUB | AH1: 2020, Кредиторская задолженность, RUB | AI1: 2021, Кредиторская задолженность, RUB | AJ1: 2022, Кредиторская задолженность, RUB | AK1: 2023, Кредиторская задолженность, RUB | AL1: 2024, Кредиторская задолженность, RUB | AM1: 2020, Выручка, RUB | AN1: 2021, Выручка, RUB | AO1: 2022, Выручка, RUB | AP1: 2023, Выручка, RUB | AQ1: 2024, Выручка, RUB | AR1: 2020, Себестоимость продаж, RUB | AS1: 2021, Себестоимость продаж, RUB | AT1: 2022, Себестоимость продаж, RUB | AU1: 2023, Себестоимость продаж, RUB | AV1: 2024, Себестоимость продаж, RUB | AW1: 2020, Коммерческие расходы, RUB | AX1: 2021, Коммерческие расходы, RUB | AY1: 2022, Коммерческие расходы, RUB | AZ1: 2023, Коммерческие расходы, RUB | BA1: 2024, Коммерческие расходы, RUB | BB1: 2020, Управленческие расходы, RUB | BC1: 2021, Управленческие расходы, RUB | BD1: 2022, Управленческие расходы, RUB | BE1: 2023, Управленческие расходы, RUB | BF1: 2024, Управленческие расходы, RUB | BG1: 2020, Прочие доходы, RUB | BH1: 2021, Прочие доходы, RUB | BI1: 2022, Прочие доходы, RUB | BJ1: 2023, Прочие доходы, RUB | BK1: 2024, Прочие доходы, RUB | BL1: 2020, Прочие расходы, RUB | BM1: 2021, Прочие расходы, RUB | BN1: 2022, Прочие расходы, RUB | BO1: 2023, Прочие расходы, RUB | BP1: 2024, Прочие расходы, RUB | BQ1: 2020, Чистая прибыль (убыток), RUB | BR1: 2021, Чистая прибыль (убыток), RUB | BS1: 2022, Чистая прибыль (убыток), RUB | BT1: 2023, Чистая прибыль (убыток), RUB | BU1: 2024, Чистая прибыль (убыток), RUB
A2: 211 | B2: 12 | C2: Управление эксплуатацией нежилого фонда за вознаграждение или на договорной основе | N2: 3679000 | O2: 4504000 | P2: 4254000 | Q2: 3207000 | R2: 2934000 | S2: 530000 | T2: 692000 | U2: 538000 | V2: 501000 | W2: 1000 | AC2: 2145000 | AI2: 45000 | AJ2: 62000 | AK2: 58000 | AL2: 58000 | AM2: 10962000 | AN2: 14691000 | AO2: 1920000 | AP2: 1612000 | AR2: 9598000 | AS2: 10237000 | AT2: 1974000 | AU2: 2505000 | AV2: 279000 | BG2: 27000 | BH2: 6000 | BI2: 7000 | BJ2: 11000 | BL2: 258000 | BM2: 130000 | BN2: 270000 | BO2: 56000 | BP2: 9000 | BQ2: 1133000 | BR2: 3826000 | BS2: -420000 | BT2: -1064000 | BU2: -795000
A3: 7 | B3: 17 | C3: Управление эксплуатацией жилого фонда за вознаграждение или на договорной основе | D3: 1496000 | E3: 7205000 | F3: 6909000 | I3: 2205000 | J3: 608000 | K3: 500000 | L3: 233000 | M3: 233000 | N3: 38472000 | O3: 14456000 | P3: 7610000 | Q3: 17806000 | R3: 14298000 | S3: 17451000 | T3: 12106000 | U3: 1009000 | V3: 307000 | W3: 1062000 | X3: 25831000 | Y3: -2719000 | Z3: -9356000 | AA3: 6816000 | AB3: -722000 | AH3: 13228000 | AI3: 25791000 | AJ3: 24330000 | AK3: 11515000 | AL3: 16300000 | AM3: 111609000 | AN3: 32742000 | AO3: 7778000 | AP3: 3700000 | AR3: 94923000 | AS3: 28040000 | AT3: 15221000 | AU3: 11887000 | AV3: 688000 | BG3: 168000 | BH3: 1626000 | BI3: 2486000 | BJ3: 19356000 | BK3: 11000 | BL3: 596000 | BM3: 26201000 | BN3: 545000 | BO3: 8256000 | BP3: 6749000 | BQ3: 14845000 | BR3: -20960000 | BS3: -5625000 | BT3: 2790000 | BU3: -7539000
A4: 39 | B4: 10 | C4: Управление эксплуатацией жилого фонда за вознаграждение или на договорной основе | E4: 39744000 | F4: 39744000 | I4: 34616000 | N4: 13496000 | O4: 13496000 | P4: 12511000 | Q4: 12511000 | R4: 12511000 | X4: -87698000 | Y4: -83796000 | Z4: -221452000 | AA4: -261792000 | AB4: -261792000 | AH4: 6554000 | AI4: 4563000 | BH4: 3902000 | BN4: 144918000 | BO4: 40340000 | BR4: 3902000 | BS4: -144918000 | BT4: -40340000
A5: 40 | B5: 18 | C5: Управление эксплуатацией жилого фонда за вознаграждение или на договорной основе | I5: 2000 | J5: 14000 | N5: 50798000 | O5: 62549000 | P5: 46980000 | Q5: 34234000 | R5: 26050000 | S5: 37003000 | T5: 131000 | U5: 519000 | V5: 488000 | W5: 1301000 | Y5: 560000 | Z5: 560000 | AA5: -9405000 | AB5: -15365000 | AH5: 47342000 | AI5: 12091000 | AJ5: 41779000 | AK5: 43967000 | AL5: 42556000 | AM5: 115998000 | AN5: 85622000 | AR5: 100954000 | AS5: 62571000 | BG5: 33510000 | BH5: 2063000 | BL5: 55671000 | BM5: 14375000 | BO5: 9405000 | BP5: 5960000 | BQ5: -7329000 | BR5: 8687000 | BT5: -9405000 | BU5: -5960000
A6: 54 | B6: 16 | C6: Управление эксплуатацией жилого фонда за вознаграждение или на договорной основе | I6: 67000 | N6: 3123000 | O6: 93386000 | S6: 270000 | T6: 4114000 | X6: -186261000 | Y6: -90345000 | AH6: 183559000 | AI6: 181748000 | AM6: 26517000 | AR6: 18849000 | BB6: 1353000 | BG6: 20425000 | BH6: 132179000 | BL6: 26550000 | BM6: 36250000 | BQ6: 190000 | BR6: 95929000
A7: 69 | B7: 30 | C7: Управление эксплуатацией жилого фонда за вознаграждение или на договорной основе | D7: 941000 | E7: 557000 | F7: 318000 | I7: 846000 | N7: 4582000 | O7: 2631000 | P7: 3185000 | Q7: 2881000 | R7: 2747000 | S7: 3730000 | T7: 71000 | U7: 5110000 | V7: 1847000 | W7: 962000 | X7: -23062000 | Y7: -32063000 | Z7: -30310000 | AA7: -32354000 | AB7: -33423000 | AH7: 17781000 | AI7: 24777000 | AJ7: 28515000 | AK7: 28017000 | AL7: 28101000 | AM7: 13987000 | AN7: 13120000 | AO7: 1376000 | AP7: 8000 | AQ7: 7000 | AR7: 11526000 | AS7: 12879000 | AT7: 5446000 | BB7: 8751000 | BC7: 8655000 | BD7: 1182000 | BE7: 1021000 | BF7: 973000 | BG7: 238000 | BH7: 643000 | BI7: 18211000 | BL7: 192000 | BM7: 217000 | BN7: 442000 | BO7: 571000 | BP7: 64000 | BQ7: -5980000 | BR7: -7905000 | BS7: 10788000 | BT7: -1726000 | BU7: -1069000
A8: 77 | B8: 18 | C8: Управление эксплуатацией жилого фонда за вознаграждение или на договорной основе | N8: 29978000 | O8: 40222000 | P8: 39642000 | Q8: 37340000 | R8: 35920000 | S8: 1755000 | T8: 1582000 | U8: 1776000 | V8: 1333000 | W8: 563000 | X8: -67998000 | Y8: -13291000 | Z8: -13291000 | AA8: -13291000 | AB8: -13291000 | AC8: 99721000 | AI8: 55085000 | AJ8: 54699000 | AK8: 51954000 | AL8: 49764000 | BC8: 1105000 | BL8: 373000 | BQ8: -373000 | BR8: -1105000
A9: 83 | B9: 20 | C9: Управление эксплуатацией жилого фонда за вознаграждение или на договорной основе | N9: 29931000 | O9: 26551000 | P9: 25385000 | Q9: 23563000 | R9: 21295000 | S9: 104000 | T9: 1088000 | U9: 345000 | V9: 27000 | W9: 82000 | AH9: 53843000 | AI9: 52960000 | AJ9: 52165000 | AK9: 50591000 | AL9: 48749000 | AM9: 111000 | AR9: 127000 | BL9: 9587000 | BM9: 1513000 | BN9: 1114000 | BO9: 566000 | BP9: 371000 | BQ9: -9671000 | BR9: -1513000 | BS9: -1114000 | BT9: -566000 | BU9: -371000
A10: 162 | B10: 14 | C10: Управление эксплуатацией жилого фонда за вознаграждение или на договорной основе | I10: 28000 | J10: 40000 | K10: 55000 | L10: 51000 | M10: 48000 | N10: 30317000 | O10: 36012000 | P10: 32511000 | Q10: 28476000 | R10: 15196000 | S10: 66000 | T10: 916000 | U10: 78000 | V10: 125000 | W10: 42000 | AH10: 21618000 | AI10: 25358000 | AJ10: 23016000 | AK10: 21916000 | AL10: 14648000 | AM10: 12855000 | AN10: 7744000 | AR10: 11697000 | AS10: 5443000 | AT10: 1347000 | AU10: 1166000 | AV10: 1197000 | BG10: 124000 | BH10: 98000 | BI10: 16000 | BJ10: 137000 | BK10: 129000 | BL10: 3000 | BM10: 143000 | BN10: 613000 | BO10: 1779000 | BP10: 4886000 | BQ10: 1150000 | BR10: 2083000 | BS10: -1964000 | BT10: -2854000 | BU10: -5993000
A11: 166 | B11: 14 | C11: Управление эксплуатацией жилого фонда за вознаграждение или на договорной основе | I11: 41000 | N11: 22978000 | O11: 15371000 | P11: 6136000 | Q11: 4639000 | R11: 1118000 | S11: 11335000 | X11: -9157000 | Y11: -10368000 | Z11: -12020000 | AA11: -12020000 | AB11: -12020000 | AH11: 23920000 | AI11: 16472000 | AJ11: 18146000 | AK11: 16649000 | AL11: 13128000 | AM11: 4808000 | AR11: 2081000 | BB11: 3038000 | BC11: 1211000 | BG11: 600000 | BL11: 835000 | BN11: 1652000 | BQ11: -546000 | BR11: -1211000 | BS11: -1652000
A12: 181 | B12: 10 | C12: Управление эксплуатацией жилого фонда за вознаграждение или на договорной основе | I12: 213000 | N12: 12528000 | P12: 11759000 | Q12: 10291000 | R12: 9934000 | W12: 26000 | X12: -5754000 | AE12: 144000 | AF12: 144000 | AG12: 237000 | AH12: 18341000 | AJ12: 19267000 | AK12: 18989000 | AL12: 19044000 | AM12: 23416000 | AR12: 20999000 | AT12: 1509000 | AU12: 1168000 | AV12: 473000 | BB12: 5609000 | BG12: 128000 | BL12: 2169000 | BN12: 4000 | BO12: 7000 | BP12: 3000 | BQ12: -5233000 | BS12: -1519000 | BT12: -1189000 | BU12: -480000
A13: 193 | B13: 13 | C13: Управление эксплуатацией жилого фонда за вознаграждение или на договорной основе
A14: 198 | B14: 13 | C14: Управление эксплуатацией жилого фонда за вознаграждение или на договорной основе | N14: 6583000 | O14: 5496000 | P14: 2008000 | Q14: 345000 | R14: 846000 | S14: 183000 | T14: 286000 | U14: 229000 | V14: 37000 | W14: 114000 | AH14: 29748000 | AI14: 29804000 | AJ14: 29104000 | AK14: 27535000 | AL14: 25389000 | AM14: 7800000 | AN14: 576000 | AR14: 8870000 | AS14: 364000 | BL14: 3682000 | BM14: 1616000 | BN14: 2845000 | BO14: 1286000 | BP14: 400000 | BQ14: -4752000 | BR14: -1404000 | BS14: -2845000 | BT14: -1286000 | BU14: -400000
A15: 200 | B15: 9 | C15: Управление эксплуатацией жилого фонда за вознаграждение или на договорной основе | K15: 10000 | N15: 48179000 | O15: 46471000 | P15: 43818000 | Q15: 43315000 | S15: 6205000 | T15: 1177000 | U15: 1130000 | V15: 123000 | X15: 1199000 | Y15: 42000 | Z15: -465000 | AA15: -1080000 | AH15: 40268000 | AI15: 40717000 | AJ15: 40108000 | AK15: 42016000 | AM15: 49196000 | AN15: 23407000 | AO15: 8664000 | AP15: 3349000 | AR15: 29601000 | AS15: 15977000 | AT15: 5411000 | AU15: 1945000 | BB15: 9318000 | BC15: 7036000 | BD15: 3791000 | BE15: 2372000 | BG15: 347000 | BH15: 1114000 | BJ15: 380000 | BL15: 5336000 | BM15: 2182000 | BN15: 9000 | BO15: 29000 | BQ15: 4480000 | BR15: -464000 | BS15: -507000 | BT15: -615000
A16: 203 | B16: 14 | C16: Управление эксплуатацией жилого фонда за вознаграждение или на договорной основе | I16: 3000 | J16: 572000 | N16: 123293000 | O16: 125411000 | P16: 98648000 | Q16: 88179000 | R16: 80125000 | S16: 4114000 | T16: 725000 | U16: 10000 | V16: 220000 | W16: 393000 | X16: -25488000 | Y16: -25929000 | Z16: -28969000 | AA16: -28969000 | AB16: -31963000 | AH16: 130630000 | AI16: 130417000 | AJ16: 127617000 | AK16: 117358000 | AL16: 112471000 | AM16: 21533000 | AN16: 384000 | AR16: 17112000 | AS16: 385000 | BB16: 9574000 | BC16: 133000 | BG16: 2452000 | BH16: 1000 | BL16: 3771000 | BM16: 308000 | BN16: 3040401000 | BP16: 2994000 | BQ16: -6472000 | BR16: -441000 | BS16: -3040401000 | BU16: -2994000
A17: 204 | B17: 17 | C17: Управление эксплуатацией жилого фонда за вознаграждение или на договорной основе | N17: 158606000 | O17: 140746000 | P17: 134494000 | Q17: 129797000 | R17: 129097000 | S17: 3045000 | T17: 5598000 | U17: 1280000 | V17: 1175000 | W17: 646000 | X17: -60975000 | Y17: -62543000 | Z17: -64062000 | AA17: -64062000 | AB17: -64062000 | AH17: 221616000 | AI17: 207877000 | AJ17: 198826000 | AK17: 194024000 | AL17: 192795000 | BL17: 1584000 | BM17: 1568000 | BN17: 1519000 | BQ17: -1584000 | BR17: -1568000 | BS17: -1519000
A18: 209 | B18: 12 | C18: Управление эксплуатацией жилого фонда за вознаграждение или на договорной основе | N18: 33551000 | O18: 28952000 | P18: 26481000 | Q18: 24906000 | R18: 23763000 | S18: 563000 | T18: 150000 | U18: 1356000 | V18: 1298000 | W18: 1088000 | AH18: 39642000 | AI18: 35806000 | AJ18: 35987000 | AK18: 35185000 | AL18: 34499000 | BL18: 1770000 | BM18: 1176000 | BN18: 1265000 | BO18: 831000 | BP18: 667000 | BQ18: -1822000 | BR18: -1176000 | BS18: -1446000 | BT18: -831000 | BU18: -667000
A19: 51 | B19: 19 | C19: Управление недвижимым имуществом за вознаграждение или на договорной основе
A20: 53 | B20: 16 | C20: Управление недвижимым имуществом за вознаграждение или на договорной основе | I20: 813000 | J20: 613000 | K20: 457000 | L20: 941000 | N20: 20211000 | O20: 24692000 | P20: 27641000 | Q20: 23567000 | R20: 17907000 | V20: 2000 | W20: 39000 | AB20: -165000 | AH20: 10000000 | AI20: 16781000 | AJ20: 21395000 | AK20: 18470000 | AL20: 18101000 | AM20: 42410000 | AN20: 43195000 | AO20: 41441000 | AP20: 42381000 | AQ20: 7775000 | AR20: 40295000 | AS20: 44511000 | AT20: 43733000 | AU20: 42621000 | AV20: 13210000 | BG20: 3263000 | BH20: 3462000 | BI20: 2787000 | BL20: 2016000 | BM20: 4214000 | BN20: 1885000 | BP20: 760000 | BQ20: 2969000 | BR20: -2500000 | BS20: -1821000 | BT20: -663000 | BU20: -6195000
A21: 55 | B21: 21 | C21: Управление недвижимым имуществом за вознаграждение или на договорной основе | AH21: 207619000 | AI21: 209797000 | AJ21: 211625000 | AK21: 212881000 | AL21: 213870000 | AR21: 2037000 | AS21: 1745000 | AT21: 1414000 | AU21: 856000 | AV21: 592000 | BL21: 2122000 | BM21: 433000 | BN21: 414000 | BO21: 400000 | BP21: 397000 | BQ21: -4159000 | BR21: -2178000 | BS21: -1828000 | BT21: -1256000 | BU21: -989000
A22: 199 | B22: 11 | C22: Управление недвижимым имуществом за вознаграждение или на договорной основе
A23: 201 | B23: 11 | C23: Управление недвижимым имуществом за вознаграждение или на договорной основе | S23: 1094000 | T23: 306000 | U23: 407000 | V23: 139000 | AH23: 50885000 | AI23: 55646000 | AJ23: 56279000 | AK23: 56463000 | AR23: 120000 | AS23: 107000 | AT23: 143000 | AU23: 62000 | BL23: 591000 | BM23: 5442000 | BN23: 389000 | BO23: 390000 | BQ23: -711000 | BR23: -5549000 | BS23: -532000 | BT23: -452000
A24: 202 | B24: 4 | C24: Управление недвижимым имуществом за вознаграждение или на договорной основе | J24: 10000 | K24: 10000 | L24: 10000 | M24: 10000 | P24: 32267000 | Q24: 71479000 | R24: 71479000 | V24: 5000 | W24: 5000 | AE24: 184000 | AF24: 234000 | AG24: 234000 | AI24: 2000 | AJ24: 28446000 | AK24: 63548000 | AL24: 63548000 | AO24: 32338000 | AP24: 39262000 | AT24: 28697000 | AU24: 35196000 | BM24: 2000 | BN24: 3000 | BR24: -2000 | BS24: 3638000 | BT24: 4065000
A25: 207 | B25: 14 | C25: Управление недвижимым имуществом за вознаграждение или на договорной основе | I25: 993000 | N25: 55857000 | O25: 51701000 | P25: 47893000 | Q25: 21396000 | R25: 20358000 | S25: 3929000 | X25: -15763000 | Y25: -55021000 | Z25: -56682000 | AA25: -83179000 | AB25: -83179000 | AH25: 77407000 | AI25: 106712000 | AJ25: 104565000 | AK25: 104565000 | AL25: 103527000 | AM25: 101000 | AR25: 2000 | BB25: 3692000 | BC25: 39258000 | BG25: 16000 | BL25: 22000 | BN25: 1661000 | BO25: 26498000 | BQ25: -3599000 | BR25: -39258000 | BS25: -1661000 | BT25: -26498000
A26: 208 | B26: 17 | C26: Управление недвижимым имуществом за вознаграждение или на договорной основе | F26: 20000 | I26: 13000 | J26: 11000 | K26: 9000 | N26: 200810000 | O26: 279592000 | P26: 273573000 | S26: 7249000 | T26: 506000 | U26: 156000 | X26: -2230000 | Y26: -219536000 | Z26: -224466000 | AH26: 226820000 | AI26: 516748000 | AJ26: 516306000 | AM26: 108190000 | AN26: 59010000 | AO26: 26298000 | AR26: 111821000 | AS26: 63240000 | AT26: 31809000 | BG26: 974000 | BH26: 51825000 | BI26: 1034000 | BL26: 2327000 | BM26: 329912000 | BN26: 1659000 | BQ26: -3958000 | BR26: -217306000 | BS26: -4957000
A27: 212 | B27: 12 | C27: Управление недвижимым имуществом за вознаграждение или на договорной основе | D27: 52000 | I27: 102000 | J27: 13000 | K27: 6000 | L27: 3000 | M27: 1000 | N27: 220906000 | O27: 191267000 | P27: 135934000 | Q27: 129999000 | R27: 114467000 | S27: 554000 | T27: 34000 | U27: 13000 | V27: 433000 | W27: 9187000 | X27: -41025000 | Y27: -52930000 | Z27: -66434000 | AA27: -69898000 | AB27: -88375000 | AC27: 1002000 | AE27: 5232000 | AF27: 12386000 | AG27: 12809000 | AH27: 232114000 | AI27: 236844000 | AJ27: 197479000 | AK27: 188506000 | AL27: 196375000 | AM27: 562247000 | AN27: 295436000 | AO27: 142275000 | AP27: 102835000 | AQ27: 22189000 | AR27: 529895000 | AS27: 283286000 | AT27: 130887000 | AU27: 96286000 | AV27: 17022000 | BB27: 29640000 | BC27: 21231000 | BD27: 14387000 | BE27: 11241000 | BF27: 4392000 | BG27: 17495000 | BH27: 26951000 | BI27: 75355000 | BJ27: 49107000 | BK27: 14147000 | BL27: 21096000 | BM27: 28912000 | BN27: 85555000 | BO27: 46475000 | BP27: 34397000 | BQ27: -4072000 | BR27: -11905000 | BS27: -13504000 | BT27: -3464000 | BU27: -18477000
A28: 214 | B28: 19 | C28: Управление недвижимым имуществом за вознаграждение или на договорной основе | AH28: 308469000 | AI28: 311472000 | AJ28: 314638000 | AK28: 316401000 | AL28: 317564000 | AR28: 2591000 | AS28: 2489000 | AT28: 2714000 | AU28: 1260000 | AV28: 740000 | BL28: 418000 | BM28: 514000 | BN28: 452000 | BO28: 503000 | BP28: 423000 | BQ28: -3009000 | BR28: -3003000 | BS28: -3166000 | BT28: -1763000 | BU28: -1163000
A29: 249 | B29: 13 | C29: Управление недвижимым имуществом за вознаграждение или на договорной основе
A30: 36 | B30: 6 | C30: Транспортная обработка грузов | D30: 29698000 | E30: 51507000 | F30: 34104000 | G30: 39432000 | H30: 133332000 | I30: 505000 | J30: 104000 | K30: 94000 | L30: 48000 | M30: 210000 | N30: 12233000 | O30: 13023000 | P30: 20933000 | Q30: 24929000 | R30: 24759000 | S30: 277000 | T30: 265000 | U30: 373000 | V30: 75000 | W30: 893000 | X30: 5348000 | Y30: -140000 | Z30: -7968000 | AA30: -5172000 | AB30: 9954000 | AC30: 14395000 | AD30: 19196000 | AE30: 16301000 | AF30: 17438000 | AG30: 5291000 | AH30: 9652000 | AI30: 8726000 | AJ30: 15209000 | AK30: 19488000 | AL30: 6303000 | AM30: 132408000 | AN30: 127412000 | AO30: 125394000 | AP30: 107752000 | AQ30: 147259000 | AR30: 89138000 | AS30: 97109000 | AT30: 106792000 | AU30: 90610000 | AV30: 117854000 | BB30: 29341000 | BC30: 33830000 | BD30: 16114000 | BE30: 13149000 | BF30: 24971000 | BG30: 11000 | BH30: 5139000 | BI30: 7931000 | BJ30: 2932000 | BK30: 20041000 | BL30: 1312000 | BM30: 5942000 | BN30: 17064000 | BO30: 6916000 | BP30: 5767000 | BQ30: 9882000 | BR30: -5505000 | BS30: -7968000 | BT30: -2796000 | BU30: 15049000
A31: 205 | B31: 9 | C31: Торговля электроэнергией | P31: 18718000 | Q31: 14170000 | R31: 10733000 | U31: 3326000 | V31: 241000 | W31: 225000 | AJ31: 18830000 | AK31: 11197000 | AL31: 14883000 | AO31: 23571000 | AT31: 15891000 | BI31: 203000 | BN31: 667000 | BP31: 7139000 | BS31: 6503000 | BU31: -7139000
A32: 142 | B32: 20 | C32: Торговля розничная телекоммуникационным оборудованием, включая розничную торговлю мобильными телефонами, в специализированных магазинах | D32: 945364000 | E32: 912455000 | F32: 8101090000 | G32: 425628000 | H32: 312210000 | I32: 14359920000 | J32: 15123264000 | K32: 4414615000 | L32: 3413685000 | M32: 3488787000 | N32: 27842542000 | O32: 32016168000 | P32: 4243988000 | Q32: 2385946000 | R32: 2357946000 | S32: 3297906000 | T32: 3760475000 | U32: 1224940000 | V32: 24524000 | W32: 55835000 | X32: 3612998000 | Y32: 3628277000 | Z32: -44916058000 | AA32: -48297330000 | AB32: -48652696000 | AC32: 17591345000 | AD32: 10542639000 | AF32: 8012792000 | AG32: 8013422000 | AH32: 48981006000 | AI32: 54041839000 | AJ32: 53532029000 | AK32: 47499363000 | AL32: 47530919000 | AM32: 102151702000 | AN32: 105462524000 | AO32: 56759628000 | AP32: 5460267000 | AQ32: 9889000 | AR32: 77585664000 | AS32: 81463799000 | AT32: 38316485000 | AU32: 4016869000 | AW32: 24126948000 | AX32: 20197306000 | AY32: 16003711000 | AZ32: 6648956000 | BA32: 506665000 | BG32: 2558364000 | BH32: 1214348000 | BI32: 352547000 | BJ32: 3511891000 | BK32: 78156000 | BL32: 4564922000 | BM32: 4227624000 | BN32: 46396282000 | BO32: 1848243000 | BP32: 28066000 | BQ32: -2156481000 | BR32: 15280000 | BS32: -48544335000 | BT32: -3039019000 | BU32: -355366000
A33: 89 | B33: 24 | C33: Торговля розничная прочими бытовыми изделиями в специализированных магазинах | D33: 14016000 | E33: 14759000 | F33: 282944000 | G33: 439288000 | H33: 370661000 | I33: 591313000 | J33: 618765000 | K33: 592607000 | L33: 586718000 | M33: 338042000 | N33: 76543000 | O33: 58086000 | P33: 53439000 | Q33: 55332000 | R33: 45934000 | S33: 12162000 | T33: 23876000 | U33: 25167000 | V33: 31468000 | W33: 27697000 | X33: 145367000 | Y33: 163395000 | Z33: 174867000 | AA33: 185627000 | AB33: -99926000 | AC33: 5627000 | AD33: 42211000 | AG33: 5300000 | AH33: 445755000 | AI33: 463929000 | AJ33: 445490000 | AK33: 454484000 | AL33: 434417000 | AM33: 1046987000 | AN33: 941381000 | AO33: 858086000 | AP33: 752211000 | AQ33: 591349000 | AR33: 665981000 | AS33: 583857000 | AT33: 504924000 | AU33: 381565000 | AV33: 374650000 | AW33: 329316000 | AX33: 317518000 | AY33: 307990000 | AZ33: 313832000 | BA33: 356823000 | BG33: 26004000 | BH33: 56678000 | BI33: 35914000 | BJ33: 6352000 | BK33: 16282000 | BL33: 48994000 | BM33: 64448000 | BN33: 43067000 | BO33: 32677000 | BP33: 131408000 | BQ33: 12791000 | BR33: 18028000 | BS33: 16972000 | BT33: 10760000 | BU33: -285553000
A34: 128 | B34: 5 | C34: Торговля розничная прочая вне магазинов, палаток, рынков | D34: 870000 | E34: 646000 | F34: 568000 | G34: 4216000 | H34: 4216000 | I34: 6885000 | J34: 7538000 | K34: 6550000 | L34: 11699000 | M34: 9713000 | N34: 1425000 | O34: 5307000 | P34: 11358000 | Q34: 14290000 | R34: 561000 | S34: 29000 | T34: 7000 | U34: 1190000 | V34: 138000 | AC34: 3000 | AF34: 9970000 | AG34: 5941000 | AH34: 8214000 | AI34: 11569000 | AJ34: 16519000 | AK34: 15594000 | AL34: 10798000 | AM34: 15414000 | AN34: 16327000 | AO34: 54929000 | AP34: 72361000 | AQ34: 33041000 | AR34: 14139000 | AS34: 15119000 | AT34: 53345000 | AU34: 69625000 | AV34: 32268000 | BL34: 47000 | BM34: 37000 | BN34: 62000 | BO34: 80000 | BP34: 6971000 | BQ34: 982000 | BR34: 937000 | BS34: 1218000 | BT34: 1632000 | BU34: -7028000
A35: 85 | B35: 11 | C35: Торговля розничная прочая в неспециализированных магазинах | U35: 254000 | AH35: 13140000 | AI35: 13140000 | AJ35: 13895000 | AK35: 13899000 | AL35: 14259000
A36: 88 | B36: 19 | C36: Торговля розничная продуктами из мяса и мяса птицы в специализированных магазинах | F36: 11838000 | G36: 11838000 | H36: 11838000 | N36: 2558000 | O36: 2558000 | P36: 2558000 | Q36: 2558000 | R36: 2558000 | X36: -266006000 | Y36: -267183000 | Z36: -255345000 | AA36: -255345000 | AB36: -257391000 | AH36: 147533000 | AI36: 148710000 | AJ36: 148710000 | AK36: 148710000 | AL36: 150756000 | AM36: 18993000 | BL36: 18996000 | BM36: 1187000 | BN36: 1320000 | BO36: 1320000 | BP36: 1320000 | BQ36: -3000 | BR36: -1187000 | BS36: -1320000 | BT36: -1320000 | BU36: -1320000
A37: 188 | B37: 6 | C37: Торговля розничная преимущественно пищевыми продуктами, включая напитки, и табачными изделиями в неспециализированных магазинах | I37: 6215000 | J37: 9982000 | K37: 10404000 | N37: 7918000 | O37: 18068000 | P37: 21414000 | Q37: 21946000 | R37: 21976000 | S37: 13481000 | T37: 4021000 | U37: 2515000 | V37: 18000 | AB37: -2920000 | AC37: 2473000 | AH37: 5998000 | AI37: 10128000 | AJ37: 11267000 | AK37: 22000 | AL37: 24896000 | AM37: 149055000 | AN37: 178225000 | AO37: 194580000 | AP37: 71347000 | AR37: 131347000 | AS37: 172464000 | AT37: 189744000 | AU37: 71401000 | BG37: 739000 | BH37: 1071000 | BI37: 209000 | BL37: 1358000 | BM37: 2114000 | BN37: 1955000 | BO37: 345000 | BQ37: 15091000 | BR37: 2799000 | BS37: 1123000 | BT37: -1124000
A38: 18 | B38: 10 | C38: Торговля розничная одеждой в специализированных магазинах | D38: 496000 | E38: 432000 | I38: 634520000 | J38: 443883000 | K38: 71992000 | L38: 37221000 | M38: 29783000 | N38: 65258000 | O38: 209011000 | P38: 263000000 | Q38: 257268000 | R38: 193444000 | S38: 9170000 | T38: 2858000 | U38: 3558000 | V38: 5195000 | W38: 458000 | X38: 40071000 | Y38: 35145000 | Z38: 1113000 | AA38: 2763000 | AB38: 3496000 | AC38: 5074000 | AD38: 3427000 | AE38: 7410000 | AF38: 33587000 | AG38: 5864000 | AH38: 667219000 | AI38: 625868000 | AJ38: 342506000 | AK38: 274902000 | AL38: 227191000 | AM38: 314616000 | AN38: 370254000 | AO38: 185892000 | AP38: 46513000 | AQ38: 26263000 | AR38: 205525000 | AS38: 322434000 | AT38: 160555000 | AU38: 43639000 | AV38: 10704000 | AW38: 136706000 | AX38: 154549000 | AY38: 84362000 | AZ38: 38783000 | BA38: 24548000 | BG38: 45294000 | BH38: 114977000 | BI38: 273160000 | BJ38: 61753000 | BK38: 23463000 | BL38: 17324000 | BM38: 14308000 | BN38: 244919000 | BO38: 21498000 | BP38: 13666000 | BQ38: -250000 | BR38: -4925000 | BS38: -33136000 | BT38: 2172000 | BU38: 731000
A39: 105 | B39: 8 | C39: Торговля розничная обувью и изделиями из кожи в специализированных магазинах | D39: 83671000 | I39: 728116000 | N39: 1354894000 | S39: 9321000 | X39: 45552000 | AC39: 1257150000 | AH39: 932303000 | AM39: 1842726000 | AR39: 1133488000 | AW39: 443515000 | BG39: 100328000 | BL39: 306500000 | BQ39: 9088000
A40: 100 | B40: 22 | C40: Торговля розничная обувью в специализированных магазинах | D40: 633546000 | E40: 590821000 | F40: 444509000 | G40: 379098000 | H40: 372785000 | I40: 18123730000 | J40: 15562098000 | K40: 416510000 | L40: 774000 | M40: 774000 | N40: 3924535000 | O40: 4201342000 | P40: 1668490000 | Q40: 1673314000 | R40: 1208574000 | S40: 143697000 | T40: 43761000 | U40: 43460000 | V40: 32126000 | W40: 8840000 | X40: 6481420000 | Y40: 2000516000 | Z40: -11637758000 | AA40: -14713232000 | AB40: -14778792000 | AC40: 3476438000 | AD40: 3879436000 | AE40: 10923707000 | AF40: 4859029000 | AG40: 4859029000 | AH40: 5073286000 | AI40: 6848820000 | AJ40: 3957423000 | AK40: 11939932000 | AL40: 13220190000 | AM40: 7296907000 | AN40: 5513600000 | AO40: 1867457000 | AP40: 229520000 | AQ40: 55742000 | AR40: 4296596000 | AS40: 3484867000 | AT40: 2049018000 | AU40: 333205000 | AV40: 39267000 | AW40: 1860899000 | AX40: 2028601000 | AY40: 1283469000 | AZ40: 366961000 | BB40: 287995000 | BC40: 297497000 | BD40: 191962000 | BE40: 66031000 | BF40: 34234000 | BG40: 465113000 | BH40: 2531376000 | BI40: 2063179000 | BJ40: 279514000 | BK40: 33982000 | BL40: 471811000 | BM40: 6547565000 | BN40: 16110339000 | BO40: 2387943000 | BQ40: -40383000 | BR40: -4351294000 | BS40: -13641847000 | BT40: -2883190000 | BU40: -65560000
A41: 175 | B41: 23 | C41: Торговля розничная лекарственными средствами в специализированных магазинах (аптеках) | D41: 4027000 | F41: 744000 | G41: 618000 | I41: 5310000 | J41: 5535000 | K41: 7638000 | L41: 2218000 | N41: 8639000 | O41: 14846000 | P41: 15253000 | Q41: 12922000 | S41: 263000 | T41: 447000 | U41: 468000 | V41: 120000 | X41: 16702000 | Y41: 19358000 | Z41: 22015000 | AA41: 14405000 | AC41: 1523000 | AI41: 1456000 | AJ41: 2074000 | AK41: 1459000 | AM41: 60187000 | AN41: 51655000 | AO41: 44893000 | AP41: 24778000 | AR41: 50384000 | AS41: 42886000 | AT41: 37947000 | AU41: 22693000 | AW41: 6439000 | AX41: 8673000 | AY41: 5793000 | AZ41: 9823000 | BG41: 4872000 | BH41: 3666000 | BI41: 2392000 | BJ41: 767000 | BL41: 571000 | BM41: 543000 | BN41: 385000 | BO41: 382000 | BQ41: 7239000 | BR41: 2656000 | BS41: 2657000 | BT41: -7610000
A42: 23 | B42: 8 | C42: Торговля розничная большим товарным ассортиментом с преобладанием непродовольственных товаров в неспециализированных магазинах | D42: 1291000 | E42: 111000 | I42: 664425000 | J42: 423415000 | L42: 5000 | M42: 5000 | N42: 1922091000 | O42: 1621127000 | Q42: 24000 | S42: 366000 | T42: 5550000 | V42: 101000 | W42: 107000 | X42: 37932000 | Y42: -226930000 | AA42: -2826678000 | AB42: -2836238000 | AC42: 439829000 | AD42: 489646000 | AH42: 2147151000 | AI42: 1928670000 | AK42: 2827888000 | AL42: 2836330000 | AM42: 1805986000 | AN42: 640098000 | AP42: 92000 | AQ42: 149000 | AR42: 1356738000 | AS42: 503785000 | AU42: 1420000 | AV42: 8518000 | AW42: 407832000 | AX42: 281605000 | BG42: 204103000 | BH42: 40770000 | BJ42: 2000000 | BL42: 175431000 | BM42: 139440000 | BO42: 901000 | BP42: 1191000 | BQ42: 36012000 | BR42: -235060000 | BT42: -229000 | BU42: -9560000
A43: 114 | B43: 8 | C43: Торговля розничная большим товарным ассортиментом с преобладанием непродовольственных товаров в неспециализированных магазинах | D43: 220074000 | E43: 52191000 | F43: 34217000 | G43: 17974000 | H43: 17974000 | I43: 3002589000 | J43: 2378795000 | K43: 773493000 | L43: 763493000 | M43: 761493000 | N43: 1582995000 | O43: 1547653000 | P43: 901436000 | Q43: 80919000 | R43: 80919000 | S43: 481555000 | T43: 550331000 | V43: 12815000 | W43: 47000 | X43: 236705000 | Y43: -507164000 | Z43: -1671570000 | AA43: -3889762000 | AB43: -3908476000 | AC43: 751964000 | AD43: 1510742000 | AE43: 865458000 | AF43: 3039105000 | AG43: 3039105000 | AH43: 4770627000 | AI43: 4211650000 | AJ43: 2588564000 | AK43: 1725838000 | AL43: 1729784000 | AM43: 11624287000 | AN43: 9939709000 | AO43: 1063592000 | AP43: 10371000 | AQ43: 4121000 | AR43: 8701033000 | AS43: 7097609000 | AT43: 972955000 | AU43: 35327000 | AV43: 2000000 | AW43: 2774188000 | AX43: 3193428000 | AY43: 1255043000 | AZ43: 24916000 | BA43: 20708000 | BG43: 1213642000 | BH43: 684906000 | BL43: 1245046000 | BM43: 765791000 | BO43: 2168320000 | BP43: 147000 | BQ43: 40592000 | BR43: -387431000 | BS43: -1164406000 | BT43: -2218192000 | BU43: -18734000
A44: 126 | B44: 15 | C44: Торговля оптовая чистящими средствами | D44: 25000 | E44: 1356000 | I44: 5799000 | J44: 22436000 | K44: 28633000 | N44: 65325000 | O44: 70272000 | P44: 66439000 | S44: 547000 | T44: 2086000 | U44: 223000 | V44: 1430000 | X44: 6391000 | Y44: 7370000 | AC44: 1750000 | AD44: 1751000 | AE44: 1446000 | AH44: 39722000 | AI44: 91299000 | AJ44: 34584000 | AK44: 561000 | AM44: 79428000 | AN44: 107430000 | AO44: 148719000 | AP44: 28790000 | AR44: 76377000 | AS44: 86290000 | AT44: 152649000 | AU44: 27816000 | BC44: 18464000 | BG44: 19000 | BH44: 33000 | BI44: 6823000 | BL44: 447000 | BM44: 1167000 | BN44: 746000 | BO44: 176000 | BQ44: 2075000 | BR44: 979000 | BS44: 1718000 | BT44: 798000
A45: 29 | B45: 18 | C45: Торговля оптовая фармацевтической продукцией | D45: 72041000 | E45: 52973000 | F45: 89410000 | G45: 12870000 | H45: 12870000 | I45: 6148227000 | J45: 5999859000 | K45: 6028868000 | L45: 15816000 | M45: 15816000 | N45: 2673379000 | O45: 3233937000 | P45: 5335774000 | Q45: 5062119000 | R45: 5038140000 | S45: 3402000 | T45: 1892000 | U45: 79059000 | V45: 4015000 | W45: 610000 | X45: 1230753000 | Y45: 1428233000 | Z45: 1636796000 | AA45: -3501497000 | AB45: -3518048000 | AC45: 2774000000 | AD45: 3304063000 | AE45: 4452075000 | AH45: 5777048000 | AI45: 5489957000 | AJ45: 6448950000 | AK45: 4585314000 | AL45: 4578356000 | AM45: 20322825000 | AN45: 17415422000 | AO45: 17414894000 | AP45: 7384425000 | AQ45: 242000 | AR45: 19891083000 | AS45: 16919131000 | AT45: 16655535000 | AU45: 7323049000 | AW45: 889453000 | AX45: 794697000 | AY45: 776373000 | AZ45: 558244000 | BA45: 20864000 | BG45: 1193766000 | BH45: 1166975000 | BI45: 1028320000 | BJ45: 507121000 | BK45: 1115000 | BL45: 268982000 | BM45: 360848000 | BN45: 245209000 | BO45: 729924000 | BP45: 781000 | BQ45: 185594000 | BR45: 197480000 | BS45: 198986000 | BT45: -5138293000 | BU45: -16549000
A46: 133 | B46: 22 | C46: Торговля оптовая фармацевтической продукцией | D46: 106059000 | N46: 426775000 | S46: 29496000 | X46: -24949906000 | Y46: -1000000 | AH46: 25511236000 | BL46: 11428997000 | BQ46: -11428997000
A47: 86 | B47: 25 | C47: Торговля оптовая техникой, оборудованием и инструментами, применяемыми в медицинских целях | D47: 44884000 | E47: 3126000 | F47: 3124000 | G47: 3122000 | H47: 3120000 | I47: 332660000 | J47: 327623000 | K47: 271348000 | L47: 235636000 | M47: 235636000 | N47: 1544265000 | O47: 1522381000 | P47: 1454858000 | Q47: 1448260000 | R47: 1448260000 | S47: 29529000 | T47: 59995000 | U47: 39489000 | V47: 33155000 | W47: 23368000 | X47: 194514000 | Y47: -248925000 | Z47: -380653000 | AA47: -436034000 | AB47: -438631000 | AC47: 1187063000 | AD47: 1182811000 | AE47: 1175022000 | AF47: 1175022000 | AG47: 1168216000 | AH47: 1189026000 | AI47: 1168522000 | AJ47: 1164435000 | AK47: 1166256000 | AL47: 1165870000 | AM47: 21373000 | AN47: 45922000 | AO47: 9000000 | AR47: 29630000 | AS47: 40890000 | AT47: 123520000 | BG47: 6477000 | BH47: 53000 | BI47: 674000 | BJ47: 10769000 | BK47: 206000 | BL47: 30074000 | BM47: 448649000 | BN47: 17882000 | BO47: 66150000 | BP47: 2803000 | BQ47: -31854000 | BR47: -443439000 | BS47: -131728000 | BT47: -55381000 | BU47: -2597000
A48: 132 | B48: 10 | C48: Торговля оптовая твердым, жидким и газообразным топливом и подобными продуктами | D48: 54413000 | X48: -156641000 | AH48: 66044000
A49: 241 | B49: 16 | C49: Торговля оптовая твердым, жидким и газообразным топливом и подобными продуктами
A50: 82 | B50: 14 | C50: Торговля оптовая прочими строительными материалами и изделиями | D50: 7065000 | E50: 13004000 | F50: 7318000 | G50: 1635000 | H50: 383000 | I50: 39210000 | J50: 65329000 | K50: 37482000 | L50: 6258000 | N50: 17501000 | O50: 37350000 | P50: 28533000 | Q50: 25450000 | R50: 13055000 | S50: 1024000 | T50: 146000 | U50: 65000 | V50: 16000 | W50: 1000 | X50: 1238000 | Y50: 280000 | Z50: 1410000 | AA50: 1231000 | AB50: 934000 | AC50: 1784000 | AD50: 2312000 | AE50: 2312000 | AF50: 1341000 | AG50: 1174000 | AH50: 58450000 | AI50: 105681000 | AJ50: 67958000 | AK50: 28987000 | AL50: 11010000 | AM50: 95047000 | AN50: 199888000 | AO50: 66970000 | AP50: 20482000 | AQ50: 7933000 | AR50: 42039000 | AS50: 136121000 | AT50: 64095000 | AU50: 12907000 | AV50: 5636000 | AW50: 46993000 | AX50: 46163000 | AY50: 3095000 | AZ50: 770000 | BA50: 2242000 | BB50: 5177000 | BC50: 15499000 | BD50: 8216000 | BE50: 9023000 | BF50: 1688000 | BG50: 692000 | BH50: 4262000 | BI50: 14254000 | BJ50: 2709000 | BK50: 1604000 | BL50: 1263000 | BM50: 2747000 | BN50: 4371000 | BO50: 670000 | BP50: 268000 | BQ50: 138000 | BR50: -968000 | BS50: 1130000 | BT50: -179000 | BU50: -297000
A51: 238 | B51: 20 | C51: Торговля оптовая прочими машинами, приборами, аппаратурой и оборудованием общепромышленного и специального назначения | D51: 6011000 | E51: 6011000 | F51: 6011000 | G51: 6011000 | I51: 287540000 | J51: 19181000 | K51: 1928000 | L51: 1928000 | M51: 1928000 | N51: 528496000 | O51: 378372000 | P51: 405434000 | Q51: 685748000 | R51: 457927000 | S51: 4830000 | T51: 1899000 | U51: 17387000 | V51: 15219000 | W51: 41031000 | X51: -2115172000 | Y51: -2828121000 | Z51: -2844245000 | AA51: -4972477000 | AB51: -5164664000 | AC51: 3165144000 | AD51: 3165144000 | AE51: 3165144000 | AF51: 3165144000 | AG51: 3165144000 | AH51: 329571000 | AI51: 83214000 | AJ51: 99361000 | AK51: 2505739000 | AL51: 2489906000 | AM51: 467052000 | AR51: 544775000 | AS51: 710908000 | AW51: 7264000 | AX51: 3241000 | AY51: 15284000 | BB51: 125095000 | BC51: 17178000 | BG51: 64590000 | BH51: 9844000 | BJ51: 12628000 | BK51: 35634000 | BL51: 437053000 | BM51: 25423000 | BN51: 3170000 | BO51: 12617000 | BP51: 227821000 | BQ51: -473982000 | BR51: -717425000 | BS51: -16124000 | BT51: 9000 | BU51: -192187000
A52: 124 | B52: 5 | C52: Торговля оптовая прочими машинами и оборудованием | D52: 48770000 | E52: 111869000 | F52: 218282000 | I52: 1316733000 | J52: 835197000 | K52: 952368000 | N52: 7325084000 | O52: 6562026000 | P52: 4220629000 | S52: 515442000 | T52: 1870923000 | U52: 2886181000 | X52: -339877000 | Y52: 1453586000 | Z52: 64625000 | AC52: 1101556000 | AD52: 1778000 | AH52: 8288544000 | AI52: 7579087000 | AJ52: 6253970000 | AM52: 23749524000 | AN52: 23129009000 | AO52: 6184671000 | AR52: 21362788000 | AS52: 19103021000 | AT52: 4703493000 | AW52: 840300000 | AX52: 843212000 | AY52: 688119000 | BB52: 630180000 | BC52: 651423000 | BD52: 523791000 | BG52: 11618000 | BH52: 598873000 | BI52: 68113000 | BL52: 1043994000 | BM52: 861733000 | BN52: 1806497000 | BQ52: -113526000 | BR52: 1793463000 | BS52: -1435653000
A53: 217 | B53: 14 | C53: Торговля оптовая прочими машинами и оборудованием | D53: 3867000 | I53: 46672000 | J53: 8791000 | K53: 5465000 | L53: 1414000 | M53: 724000 | N53: 189846000 | O53: 245004000 | P53: 175186000 | Q53: 206298000 | R53: 208501000 | S53: 35000 | T53: 14000 | U53: 14000 | V53: 14000 | W53: 39000 | X53: 9264000 | Y53: 4172000 | Z53: 5043000 | AA53: 6255000 | AB53: 5306000 | AC53: 13537000 | AF53: 220000 | AG53: 46000 | AH53: 180165000 | AI53: 234543000 | AJ53: 160357000 | AK53: 186014000 | AL53: 187211000 | AM53: 87137000 | AN53: 147986000 | AO53: 30547000 | AP53: 3738000 | AQ53: 738000 | AR53: 32874000 | AS53: 174832000 | AT53: 13563000 | AW53: 6898000 | AX53: 6757000 | AY53: 963000 | AZ53: 378000 | BA53: 180000 | BB53: 40267000 | BC53: 7540000 | BD53: 5786000 | BE53: 1804000 | BF53: 1734000 | BG53: 8808000 | BH53: 163505000 | BI53: 192302000 | BK53: 2888000 | BL53: 11081000 | BM53: 152853000 | BN53: 201426000 | BO53: 1134000 | BP53: 2032000 | BQ53: -5955000 | BR53: -27510000 | BS53: 872000 | BT53: 338000 | BU53: -950000
A54: 240 | B54: 20 | C54: Торговля оптовая прочими машинами и оборудованием | E54: 3405000 | I54: 2314000 | J54: 8228000 | N54: 342000 | O54: 3196000 | S54: 165000 | T54: 109000 | X54: 299000 | Y54: 595000 | AH54: 2577000 | AI54: 14471000 | AM54: 5034000 | AN54: 102643000 | AR54: 4433000 | AS54: 89844000 | AX54: 12154000 | BB54: 400000 | BL54: 33000 | BM54: 52000 | BQ54: 134000 | BR54: 474000
A55: 250 | B55: 18 | C55: Торговля оптовая производственным электротехническим оборудованием, машинами, аппаратурой и материалами | D55: 3256000 | I55: 63062000 | N55: 36402000 | S55: 34000 | X55: 5386000 | AC55: 10899000 | AH55: 44728000 | AM55: 139034000 | AR55: 134477000 | AW55: 67000 | BB55: 29481000 | BG55: 28197000 | BL55: 4359000 | BQ55: -4578000
A56: 118 | B56: 16 | C56: Торговля оптовая пищевыми продуктами, напитками и табачными изделиями | N56: 72901000 | X56: -161150000 | AC56: 143881000 | AH56: 90160000 | AM56: 180000 | BL56: 361000 | BQ56: -181000
A57: 110 | B57: 17 | C57: Торговля оптовая отходами и ломом | D57: 5862000 | I57: 1722000 | J57: 1534000 | N57: 10130000 | O57: 13126000 | AH57: 5184000 | AI57: 3875000 | AM57: 55229000 | AN57: 150000 | AR57: 54443000 | AS57: 150000 | BQ57: 247000
A58: 121 | B58: 20 | C58: Торговля оптовая отходами и ломом | D58: 850000 | E58: 435000 | N58: 21565000 | O58: 9132000 | P58: 552000 | Q58: 484000 | R58: 483000 | S58: 48000 | T58: 95000 | U58: 17000 | V58: 43000 | W58: 43000 | X58: -125908000 | Y58: -125109000 | Z58: -125779000 | AA58: -126020000 | AB58: -126369000 | AH58: 115112000 | AI58: 97717000 | AJ58: 90825000 | AK58: 90824000 | AL58: 90922000 | AM58: 486019000 | AN58: 690604000 | AO58: 3263000 | AR58: 484848000 | AS58: 689865000 | AT58: 3261000 | AW58: 2202000 | BB58: 3637000 | BC58: 558000 | BD58: 316000 | BE58: 215000 | BF58: 292000 | BG58: 244000 | BH58: 5519000 | BI58: 130000 | BJ58: 10000 | BL58: 5706000 | BM58: 3855000 | BN58: 486000 | BO58: 36000 | BP58: 61000 | BQ58: -9267000 | BR58: 799000 | BS58: -670000 | BT58: -241000 | BU58: -349000
A59: 119 | B59: 13 | C59: Торговля оптовая неспециализированная
A60: 160 | B60: 14 | C60: Торговля оптовая неспециализированная | E60: 444000 | I60: 39630000 | J60: 78843000 | K60: 19473000 | N60: 20536000 | O60: 8837000 | P60: 3702000 | S60: 2511000 | T60: 8600000 | U60: 2000 | X60: 1515000 | Y60: 3628000 | Z60: 6722000 | AC60: 6764000 | AD60: 4725000 | AE60: 466000 | AH60: 55212000 | AI60: 92900000 | AJ60: 16915000 | AM60: 110117000 | AN60: 134431000 | AO60: 174922000 | AR60: 95795000 | AS60: 91169000 | AT60: 167398000 | AW60: 12298000 | AX60: 40513000 | AY60: 3388000 | BL60: 132000 | BM60: 108000 | BN60: 268000 | BQ60: 1513000 | BR60: 2113000 | BS60: 3094000
A61: 58 | B61: 7 | C61: Торговля оптовая молочными продуктами, яйцами и пищевыми маслами и жирами | N61: 63720000 | O61: 25981000 | Q61: 1000000 | R61: 974000 | S61: 135000 | T61: 29000 | X61: 157000 | Y61: 186000 | Z61: -22311000 | AA61: -26036000 | AB61: -26627000 | AC61: 5000000 | AD61: 3000000 | AH61: 58648000 | AI61: 22774000 | AJ61: 22261000 | AK61: 26986000 | AL61: 27551000 | AM61: 1400000 | AN61: 1472000 | AR61: 1304000 | AS61: 1436000 | BN61: 380000 | BO61: 625000 | BP61: 490000 | BQ61: 77000 | BR61: 29000 | BS61: -380000 | BT61: -625000 | BU61: -490000
A62: 108 | B62: 19 | C62: Торговля оптовая масличными семенами и маслосодержащими плодами
A63: 178 | B63: 9 | C63: Торговля оптовая лесоматериалами, строительными материалами и санитарно-техническим оборудованием | D63: 18342000 | E63: 6988000 | F63: 7098000 | G63: 446000 | I63: 8224000 | J63: 13639000 | K63: 8222000 | L63: 423000 | N63: 63257000 | O63: 103852000 | P63: 127038000 | Q63: 89997000 | S63: 57000 | T63: 1672000 | U63: 8000 | V63: 14000 | X63: -36304000 | Y63: -40324000 | Z63: -61419000 | AA63: -127873000 | AC63: 4727000 | AD63: 4643000 | AE63: 84634000 | AF63: 84634000 | AH63: 118679000 | AI63: 163141000 | AJ63: 199538000 | AK63: 196564000 | AM63: 103555000 | AN63: 134066000 | AO63: 74731000 | AP63: 4346000 | AR63: 93983000 | AS63: 121978000 | AT63: 76343000 | AU63: 6141000 | AW63: 8756000 | AX63: 9781000 | AY63: 5519000 | AZ63: 594000 | BB63: 20964000 | BC63: 18471000 | BD63: 22395000 | BE63: 3179000 | BG63: 31774000 | BH63: 25563000 | BI63: 17718000 | BJ63: 4645000 | BL63: 19506000 | BM63: 11797000 | BN63: 9413000 | BO63: 65653000 | BQ63: -7189000 | BR63: -4020000 | BS63: -21095000 | BT63: -66454000
A64: 150 | B64: 15 | C64: Торговля оптовая легковыми автомобилями и легкими автотранспортными средствами
A65: 215 | B65: 17 | C65: Торговля оптовая легковыми автомобилями и легкими автотранспортными средствами | N65: 4261000 | O65: 4261000 | P65: 4261000 | X65: -527776000 | Y65: -527776000 | Z65: -527776000 | AA65: -532037000 | AB65: -532037000 | AC65: 196761000 | AD65: 196761000 | AE65: 196761000 | AF65: 196761000 | AG65: 196761000 | AH65: 149862000 | AI65: 149862000 | AJ65: 149862000 | AK65: 149862000 | AL65: 149862000 | AM65: 69000 | BJ65: 500000 | BK65: 1523000 | BL65: 69000 | BO65: 4761000 | BP65: 1523000 | BT65: -4261000
A66: 112 | B66: 6 | C66: Торговля оптовая зерном, необработанным табаком, семенами и кормами для сельскохозяйственных животных | E66: 15751000 | I66: 152000 | J66: 187000 | N66: 3184000 | O66: 3372000 | S66: 312000 | T66: 59000 | X66: -3812000 | Y66: -17555000 | AH66: 4590000 | AI66: 14050000 | AM66: 60515000 | AN66: 58252000 | AR66: 55571000 | AS66: 45794000 | AW66: 9234000 | AX66: 23475000 | BB66: 49000 | BC66: 271000 | BH66: 101000 | BL66: 125000 | BM66: 1344000 | BQ66: -3810000 | BR66: -13733000
A67: 195 | B67: 17 | C67: Торговля оптовая за вознаграждение или на договорной основе | D67: 4016000 | E67: 625000 | I67: 97000 | N67: 19811000 | O67: 13672000 | S67: 483000 | AC67: 240000 | AD67: 240000 | AH67: 21315000 | AI67: 19270000 | AM67: 31713000 | AN67: 30013000 | AR67: 29492000 | AS67: 34589000 | BG67: 12000 | BH67: 3000 | BL67: 1097000 | BM67: 3453000 | BQ67: 837000 | BR67: -8065000
A68: 197 | B68: 8 | C68: Торговля легковыми автомобилями и грузовыми автомобилями малой грузоподъемности | T68: 10000 | U68: 10000 | V68: 10000
A69: 28 | B69: 17 | C69: Торговля автомобильными деталями, узлами и принадлежностями | D69: 1098000 | E69: 751000 | F69: 73000 | K69: 150000 | N69: 6911000 | O69: 11908000 | P69: 13847000 | S69: 138000 | T69: 498000 | U69: 365000 | AD69: 5061000 | AE69: 2889000 | AH69: 6254000 | AI69: 3093000 | AJ69: 2715000 | AM69: 8464000 | AN69: 13152000 | AO69: 7768000 | AR69: 7205000 | AS69: 9149000 | AT69: 5604000 | BG69: 3044000 | BH69: 255000 | BI69: 150000 | BL69: 2238000 | BM69: 1176000 | BN69: 675000 | BQ69: 1500000 | BR69: 1708000 | BS69: 1252000
A70: 183 | B70: 17 | C70: Техническое обслуживание и ремонт автотранспортных средств | G70: 2217000 | H70: 1674000 | I70: 16590000 | J70: 17100000 | K70: 23443000 | L70: 2681000 | M70: 34470000 | N70: 3947000 | O70: 4122000 | P70: 5292000 | Q70: 2712000 | R70: 2050000 | S70: 323000 | T70: 215000 | U70: 925000 | V70: 714000 | W70: 712000 | X70: 6247000 | Y70: 6247000 | Z70: 6373000 | AA70: 5202000 | AB70: 4857000 | AC70: 1371000 | AD70: 1371000 | AE70: 1381000 | AF70: 1371000 | AG70: 1371000 | AH70: 11045000 | AI70: 12409000 | AJ70: 21281000 | AK70: 324000 | AL70: 31244000 | AM70: 10831000 | AN70: 12012000 | AO70: 8841000 | AP70: 14872000 | AQ70: 379000 | AR70: 6691000 | AS70: 7728000 | AT70: 4409000 | AU70: 13036000 | AV70: 133000 | AW70: 3684000 | AX70: 3948000 | AY70: 3994000 | AZ70: 8066000 | BA70: 843000 | BG70: 774000 | BH70: 39000 | BI70: 49000 | BJ70: 7088000 | BK70: 1117000 | BL70: 779000 | BM70: 111000 | BN70: 186000 | BO70: 2161000 | BP70: 1060000 | BQ70: 280000 | BR70: 5000 | BS70: 128000 | BT70: -1093000 | BU70: -330000
A71: 65 | B71: 28 | C71: Строительство электростанций | D71: 718000 | I71: 46304000 | J71: 10990000 | K71: 10990000 | L71: 10990000 | M71: 10990000 | N71: 4443000 | O71: 3866000 | P71: 3910000 | Q71: 3318000 | S71: 25178000 | T71: 1139000 | U71: 843000 | V71: 1532000 | W71: 969000 | X71: -772100000 | Y71: -792190000 | Z71: -792114000 | AA71: -720617000 | AB71: -724507000 | AH71: 805222000 | AI71: 765077000 | AJ71: 764733000 | AK71: 693300000 | AL71: 693280000 | AM71: 2846000 | BB71: 11523000 | BC71: 2985000 | BD71: 1169000 | BE71: 526000 | BG71: 603966000 | BH71: 15902000 | BI71: 1461000 | BJ71: 1037000 | BL71: 89234000 | BM71: 44710000 | BN71: 421000 | BO71: 451000 | BQ71: 508646000 | BR71: -31848000 | BS71: -129000 | BT71: 60000
A72: 156 | B72: 10 | C72: Строительство мостов и тоннелей | D72: 1743000 | E72: 2766000 | F72: 1770000 | G72: 643000 | H72: 156000 | I72: 117587000 | J72: 192391000 | K72: 43830000 | L72: 57687000 | M72: 53791000 | N72: 1191000 | O72: 73669000 | P72: 18251000 | Q72: 27072000 | R72: 21065000 | S72: 20572000 | T72: 10666000 | U72: 75000 | V72: 98000 | X72: 4532000 | Y72: 4773000 | Z72: -27906000 | AA72: -33735000 | AB72: -36201000 | AD72: 5804000 | AE72: 11971000 | AF72: 12832000 | AG72: 12382000 | AH72: 136551000 | AI72: 268960000 | AJ72: 79851000 | AK72: 106393000 | AL72: 98821000 | AM72: 288133000 | AN72: 195157000 | AO72: 370819000 | AP72: 24236000 | AQ72: 1305000 | AR72: 274761000 | AS72: 180954000 | AT72: 395275000 | AU72: 14653000 | AV72: 2358000 | BB72: 12871000 | BC72: 13601000 | BD72: 14683000 | BE72: 7189000 | BF72: 1218000 | BI72: 25019000 | BJ72: 4274000 | BL72: 122000 | BM72: 241000 | BN72: 21842000 | BO72: 8849000 | BP72: 205000 | BQ72: 379000 | BR72: 361000 | BS72: -35962000 | BT72: -2181000 | BU72: -2476000
A73: 6 | B73: 14 | C73: Строительство коммунальных объектов для обеспечения электроэнергией и телекоммуникациями | D73: 77566000 | E73: 67792000 | F73: 60290000 | G73: 57862000 | H73: 289000 | I73: 212209000 | J73: 226034000 | K73: 226034000 | L73: 223949000 | M73: 223949000 | N73: 91702000 | O73: 89118000 | P73: 107194000 | Q73: 72035000 | R73: 13317000 | U73: 286000 | V73: 23093000 | W73: 27251000 | X73: -64752000 | Y73: -86226000 | Z73: -64035000 | AA73: -77096000 | AB73: -129701000 | AC73: 12359000 | AD73: 12353000 | AE73: 12353000 | AF73: 12353000 | AG73: 12353000 | AH73: 444591000 | AI73: 467381000 | AJ73: 457150000 | AK73: 453323000 | AL73: 393793000 | AM73: 71835000 | AN73: 1145000 | AR73: 85733000 | BB73: 51679000 | BC73: 23897000 | BD73: 10117000 | BE73: 6140000 | BF73: 4098000 | BG73: 22490000 | BH73: 7031000 | BI73: 44789000 | BJ73: 3000000 | BK73: 9268000 | BL73: 57894000 | BM73: 3927000 | BN73: 6840000 | BO73: 9921000 | BP73: 57775000 | BQ73: -84328000 | BR73: -19648000 | BS73: 22190000 | BT73: -13061000 | BU73: -52605000
A74: 95 | B74: 5 | C74: Строительство коммунальных объектов для обеспечения электроэнергией и телекоммуникациями | D74: 86000 | E74: 10157000 | F74: 8598000 | G74: 6314000 | H74: 70000 | I74: 2355000 | J74: 14378000 | K74: 14704000 | L74: 77380000 | M74: 105438000 | N74: 5831000 | O74: 12763000 | P74: 21132000 | Q74: 38150000 | R74: 37134000 | S74: 1560000 | T74: 67000 | U74: 11434000 | V74: 1889000 | W74: 89000 | AC74: 650000 | AD74: 1373000 | AE74: 1370000 | AH74: 5085000 | AI74: 7777000 | AJ74: 20820000 | AK74: 54109000 | AL74: 72737000 | AM74: 28948000 | AN74: 47747000 | AO74: 93383000 | AP74: 133381000 | AQ74: 104332000 | AR74: 28781000 | AS74: 45487000 | AT74: 91694000 | AU74: 128465000 | AV74: 104154000 | BI74: 30000 | BJ74: 3821000 | BK74: 22652000 | BL74: 61000 | BM74: 134000 | BN74: 603000 | BO74: 4068000 | BP74: 17060000 | BQ74: 86000 | BR74: 1784000 | BS74: 209000 | BT74: 2154000 | BU74: 200000
A75: 25 | B75: 32 | C75: Строительство инженерных коммуникаций для водоснабжения и водоотведения, газоснабжения | D75: 367420000 | E75: 353701000 | F75: 298856000 | G75: 224123000 | H75: 112842000 | I75: 439645000 | J75: 445688000 | K75: 443054000 | L75: 435788000 | M75: 412956000 | N75: 1228777000 | O75: 1265599000 | P75: 1362357000 | Q75: 1798613000 | R75: 1660245000 | S75: 55117000 | T75: 283000 | U75: 9733000 | V75: 4162000 | W75: 2579000 | X75: -2445078000 | Y75: -2508018000 | Z75: -2800056000 | AA75: -2344725000 | AB75: -2000784000 | AC75: 297268000 | AD75: 307908000 | AE75: 318548000 | AF75: 329188000 | AG75: 270624000 | AH75: 3734172000 | AI75: 3791148000 | AJ75: 4201778000 | AK75: 4064303000 | AL75: 3585076000 | AM75: 319294000 | AN75: 119395000 | AO75: 171801000 | AP75: 30107000 | AQ75: 6124000 | AR75: 421764000 | AS75: 158353000 | AT75: 95185000 | AU75: 75580000 | BB75: 81594000 | BC75: 66180000 | BD75: 69427000 | BE75: 51367000 | BF75: 121350000 | BG75: 50773000 | BH75: 39541000 | BI75: 322160000 | BJ75: 908756000 | BK75: 583635000 | BL75: 26081000 | BM75: 12102000 | BN75: 220469000 | BO75: 260369000 | BP75: 139882000 | BQ75: -307791000 | BR75: -71066000 | BS75: -382876000 | BT75: 414586000 | BU75: 226364000
A76: 139 | B76: 32 | C76: Строительство инженерных коммуникаций для водоснабжения и водоотведения, газоснабжения | I76: 29000 | J76: 29000 | K76: 21000 | L76: 21000 | M76: 21000 | N76: 2512000 | O76: 302000 | P76: 476000 | Q76: 481000 | R76: 356000 | S76: 2752000 | T76: 2398000 | U76: 1508000 | V76: 2245000 | W76: 2585000 | X76: -330005000 | Y76: -319764000 | Z76: -319469000 | AA76: -316964000 | AB76: -317559000 | AH76: 38994000 | AI76: 34231000 | AJ76: 36581000 | AK76: 34969000 | AL76: 319280000 | AO76: 1000000 | AR76: 497000 | AT76: 1000 | BC76: 463000 | BD76: 490000 | BE76: 648000 | BF76: 451000 | BG76: 3373000 | BH76: 10984000 | BJ76: 3781000 | BK76: 1000 | BL76: 202000 | BM76: 154000 | BN76: 141000 | BO76: 173000 | BP76: 25000 | BQ76: 2674000 | BR76: 10241000 | BS76: 294000 | BT76: 2364000 | BU76: -475000
A77: 176 | B77: 8 | C77: Строительство инженерных коммуникаций для водоснабжения и водоотведения, газоснабжения | D77: 2704000 | E77: 1526000 | F77: 729000 | G77: 12652000 | H77: 9747000 | I77: 522000 | J77: 2866000 | K77: 3131000 | L77: 31909000 | M77: 6226000 | N77: 12611000 | O77: 11128000 | P77: 15832000 | Q77: 46818000 | R77: 47410000 | S77: 35000 | T77: 4295000 | U77: 898000 | V77: 3735000 | W77: 4000 | AE77: 46000 | AF77: 585000 | AG77: 2096000 | AH77: 4207000 | AI77: 6481000 | AJ77: 6906000 | AK77: 51154000 | AL77: 29552000 | AM77: 30975000 | AN77: 47862000 | AO77: 82674000 | AP77: 87627000 | AQ77: 49283000 | AR77: 29728000 | AS77: 45769000 | AT77: 72722000 | AU77: 84492000 | AV77: 49023000 | BH77: 826000 | BI77: 10383000 | BJ77: 951000 | BK77: 397000 | BL77: 295000 | BM77: 408000 | BN77: 16393000 | BO77: 3767000 | BP77: 2205000 | BQ77: 312000 | BR77: 1792000 | BS77: 1630000 | BT77: -1529000 | BU77: -4226000
A78: 210 | B78: 17 | C78: Строительство инженерных коммуникаций для водоснабжения и водоотведения, газоснабжения
A79: 245 | B79: 16 | C79: Строительство инженерных коммуникаций для водоснабжения и водоотведения, газоснабжения | D79: 746000 | E79: 317000 | F79: 17000 | I79: 29737000 | J79: 29260000 | K79: 20737000 | N79: 13876000 | O79: 1393000 | P79: 989000 | S79: 1000 | U79: 2000 | AC79: 367000 | AD79: 1010000 | AE79: 331000 | AH79: 32607000 | AI79: 23057000 | AJ79: 35131000 | AM79: 40576000 | AN79: 29759000 | AO79: 32789000 | AR79: 39475000 | AS79: 29114000 | AT79: 51535000 | BG79: 472000 | BH79: 805000 | BI79: 224000 | BL79: 360000 | BM79: 402000 | BN79: 354000 | BQ79: 103000 | BR79: 98000 | BS79: -19891000
A80: 2 | B80: 31 | C80: Строительство жилых и нежилых зданий
A81: 3 | B81: 14 | C81: Строительство жилых и нежилых зданий | N81: 13129000 | S81: 214000 | X81: 10654000 | AH81: 2679000 | AM81: 12939000 | AR81: 7399000 | BQ81: 4432000
A82: 16 | B82: 22 | C82: Строительство жилых и нежилых зданий | D82: 152000 | E82: 201000 | I82: 17768000 | J82: 86870000 | N82: 16542000 | O82: 20531000 | S82: 12879000 | X82: 1993000 | Y82: 2586000 | AC82: 2700000 | AD82: 16199000 | AH82: 45141000 | AI82: 93118000 | AM82: 5397000 | AN82: 31348000 | AR82: 5536000 | AS82: 29384000 | BB82: 3018000 | BG82: 8643000 | BL82: 5051000 | BM82: 918000 | BQ82: 345000 | BR82: -759000
A83: 27 | B83: 9 | C83: Строительство жилых и нежилых зданий | D83: 3628000 | E83: 2267000 | F83: 907000 | I83: 2342000 | J83: 5000 | N83: 2535000 | O83: 3869000 | P83: 3142000 | X83: -3837000 | Y83: -5321000 | Z83: -7417000 | AH83: 11053000 | AI83: 9239000 | AJ83: 9237000 | AK83: 7671000 | AM83: 1461000 | AN83: 2327000 | AR83: 1119000 | AS83: 2336000 | AT83: 1730000 | AW83: 2000 | BB83: 2372000 | BC83: 1470000 | BG83: 2549000 | BL83: 922000 | BN83: 366000 | BO83: 264000 | BQ83: -423000 | BR83: -1484000 | BS83: -2096000 | BT83: -264000
A84: 41 | B84: 29 | C84: Строительство жилых и нежилых зданий | N84: 6399000 | O84: 6239000 | P84: 6263000 | Q84: 6064000 | R84: 6028000 | S84: 10000 | T84: 9000 | U84: 4000 | V84: 5000 | AB84: -19060000 | AH84: 74000 | AI84: 104000 | AJ84: 374000 | AK84: 358000 | AL84: 25088000 | AN84: 600000 | AO84: 600000 | AP84: 622000 | AR84: 681000 | AS84: 694000 | AT84: 812000 | AU84: 750000 | BF84: 987000 | BG84: 4000 | BK84: 805000 | BL84: 321000 | BM84: 97000 | BN84: 33000 | BO84: 49000 | BQ84: -1002000 | BR84: -191000 | BS84: -251000 | BT84: -183000 | BU84: -182000
A85: 49 | B85: 12 | C85: Строительство жилых и нежилых зданий
A86: 60 | B86: 8 | C86: Строительство жилых и нежилых зданий | E86: 513000 | F86: 426000 | G86: 1514000 | H86: 441000 | I86: 37000 | K86: 19880000 | L86: 35544000 | M86: 1000 | N86: 1104000 | O86: 9854000 | P86: 5703000 | Q86: 9897000 | R86: 804000 | S86: 123000 | T86: 726000 | U86: 877000 | V86: 226000 | W86: 1000 | X86: 123000 | AH86: 333000 | AI86: 8951000 | AJ86: 16092000 | AK86: 19994000 | AL86: 15629000 | AM86: 581000 | AN86: 31542000 | AO86: 26051000 | AP86: 47837000 | AQ86: 25506000 | AR86: 319000 | AS86: 29861000 | AT86: 23759000 | AU86: 43265000 | AV86: 56970000 | BB86: 163000 | BH86: 25000 | BJ86: 25000 | BL86: 23000 | BM86: 305000 | BN86: 1105000 | BO86: 2454000 | BP86: 1078000 | BQ86: 61000 | BR86: 1150000 | BS86: 893000 | BT86: 1669000 | BU86: -33458000
A87: 61 | B87: 17 | C87: Строительство жилых и нежилых зданий | D87: 985000 | I87: 3026000 | J87: 3547000 | K87: 2964000 | L87: 2964000 | N87: 111235000 | O87: 111235000 | P87: 3252000 | Q87: 3252000 | R87: 3064000 | AC87: 10491000 | AD87: 10491000 | AH87: 142017000 | AI87: 142017000 | AJ87: 85481000 | AK87: 85481000 | AL87: 100071000 | AM87: 74616000 | AN87: 3528000 | AO87: 583000 | AQ87: 92000 | AR87: 82170000 | AS87: 3987000 | AT87: 38722000 | AV87: 17834000 | BG87: 22000 | BL87: 25186000 | BM87: 5000 | BQ87: -32718000 | BR87: -464000 | BS87: -38139000 | BU87: -17742000
A88: 63 | B88: 11 | C88: Строительство жилых и нежилых зданий | D88: 9494000 | E88: 9771000 | F88: 2970000 | G88: 2212000 | H88: 1659000 | I88: 54068000 | J88: 39070000 | K88: 24697000 | L88: 48933000 | M88: 39894000 | N88: 53492000 | O88: 53896000 | P88: 75901000 | Q88: 67410000 | R88: 113451000 | S88: 2745000 | T88: 95000 | U88: 1474000 | V88: 3588000 | W88: 882000 | X88: 57223000 | Y88: 69214000 | Z88: 61451000 | AA88: 1491000 | AB88: -41383000 | AH88: 47597000 | AI88: 32684000 | AJ88: 46730000 | AK88: 108274000 | AL88: 184316000 | AM88: 98500000 | AN88: 221469000 | AO88: 325832000 | AP88: 214938000 | AQ88: 62166000 | AR88: 87035000 | AS88: 204523000 | AT88: 271619000 | AU88: 214386000 | AV88: 60945000 | BB88: 1084000 | BC88: 3200000 | BD88: 2487000 | BE88: 2154000 | BF88: 1211000 | BG88: 2898000 | BH88: 4130000 | BI88: 4222000 | BJ88: 1700000 | BL88: 588000 | BM88: 3489000 | BN88: 4992000 | BQ88: 11230000 | BR88: 12399000 | BS88: 43771000 | BT88: 78000 | BU88: 10000
A89: 75 | B89: 22 | C89: Строительство жилых и нежилых зданий | N89: 15000 | O89: 37000 | S89: 1207000 | T89: 1038000 | U89: 931000 | V89: 764000 | W89: 676000 | X89: -20150000 | Y89: -20332000 | Z89: -20476000 | AA89: -20716000 | AB89: -23923000 | AC89: 3129000 | AD89: 23860000 | AE89: 23860000 | AF89: 23860000 | AG89: 23860000 | AH89: 591000 | AI89: 624000 | AJ89: 652000 | AK89: 719000 | AL89: 729000 | AM89: 4850000 | AR89: 4530000 | AW89: 173000 | AX89: 25000 | BB89: 493000 | BC89: 167000 | BD89: 120000 | BE89: 170000 | BF89: 129000 | BG89: 27000 | BJ89: 67000 | BK89: 42000 | BL89: 31000 | BM89: 16000 | BN89: 24000 | BO89: 137000 | BP89: 1000 | BQ89: -288000 | BR89: -182000 | BS89: -144000 | BT89: -240000 | BU89: -88000
A90: 102 | B90: 12 | C90: Строительство жилых и нежилых зданий | O90: 17776000 | P90: 12269000 | Q90: 11128000 | R90: 10692000 | T90: 451000 | U90: 944000 | V90: 1080000 | W90: 531000 | Z90: -5912000 | AA90: -6917000 | AB90: -7902000 | AI90: 17924000 | AJ90: 18822000 | AK90: 18822000 | AL90: 18822000 | BN90: 389000 | BO90: 595000 | BP90: 444000 | BS90: -389000 | BT90: -595000 | BU90: -444000
A91: 104 | B91: 14 | C91: Строительство жилых и нежилых зданий | D91: 1133000 | E91: 4486000 | F91: 3754000 | H91: 2068000 | I91: 3799000 | J91: 124000 | N91: 39273000 | O91: 47008000 | P91: 47008000 | R91: 3992000 | S91: 2304000 | X91: 17331000 | Y91: 19602000 | Z91: 18002000 | AB91: -76068000 | AC91: 17217000 | AD91: 3290000 | AE91: 4704000 | AH91: 10041000 | AI91: 7875000 | AJ91: 7205000 | AL91: 79128000 | AM91: 26099000 | AN91: 3871000 | AR91: 19343000 | AS91: 890000 | AY91: 1481000 | BB91: 751000 | BC91: 710000 | BG91: 31775000 | BL91: 29403000 | BN91: 118000 | BQ91: 8377000 | BR91: 2271000 | BS91: -1599000
A92: 106 | B92: 19 | C92: Строительство жилых и нежилых зданий | D92: 22818000 | E92: 54597000 | F92: 57804000 | I92: 58122000 | J92: 181340000 | K92: 155940000 | N92: 59459000 | O92: 98936000 | P92: 71288000 | S92: 4476000 | T92: 1261000 | X92: 28486000 | Y92: 27728000 | Z92: 33119000 | AD92: 3085000 | AH92: 26314000 | AI92: 168650000 | AJ92: 127938000 | AM92: 264237000 | AN92: 211842000 | AO92: 271311000 | AR92: 255129000 | AS92: 190456000 | AT92: 257743000 | AY92: 1067000 | BD92: 5763000 | BM92: 16084000 | BQ92: 7286000 | BR92: 4242000 | BS92: 5391000
A93: 127 | B93: 9 | C93: Строительство жилых и нежилых зданий | D93: 4531000 | E93: 2528000 | F93: 1800000 | G93: 1573000 | I93: 200060000 | J93: 145651000 | K93: 139493000 | L93: 140758000 | N93: 1586433000 | O93: 1239967000 | P93: 860852000 | Q93: 855375000 | S93: 59871000 | T93: 19264000 | U93: 2901000 | V93: 3084000 | X93: -40440000 | Y93: -107058000 | Z93: -482398000 | AA93: -491937000 | AC93: 37131000 | AD93: 39011000 | AE93: 39847000 | AF93: 41096000 | AH93: 1891175000 | AI93: 1513531000 | AJ93: 1483105000 | AK93: 1487191000 | AM93: 331119000 | AN93: 506271000 | AO93: 486713000 | AP93: 2664000 | AR93: 298564000 | AS93: 512586000 | AT93: 467907000 | AU93: 1235000 | BB93: 34343000 | BC93: 41161000 | BD93: 23512000 | BE93: 9163000 | BG93: 4415000 | BH93: 3378000 | BI93: 10844000 | BJ93: 1085000 | BL93: 9411000 | BM93: 29702000 | BN93: 22052000 | BO93: 4447000 | BQ93: -6965000 | BR93: -60612000 | BS93: -14221000 | BT93: -9538000
A94: 134 | B94: 17 | C94: Строительство жилых и нежилых зданий | D94: 1117000 | N94: 15372000 | AH94: 23552000
A95: 135 | B95: 20 | C95: Строительство жилых и нежилых зданий | D95: 47367000 | E95: 39920000 | F95: 31682000 | G95: 28631000 | H95: 307000 | I95: 306373000 | J95: 245384000 | K95: 134874000 | L95: 45313000 | M95: 33404000 | N95: 425434000 | O95: 460768000 | P95: 672561000 | Q95: 720899000 | R95: 657093000 | S95: 404070000 | T95: 78772000 | U95: 129246000 | V95: 17296000 | W95: 898000 | X95: 8796000 | Y95: 12755000 | Z95: 14712000 | AA95: 24104000 | AB95: -49618000 | AC95: 12198000 | AD95: 28028000 | AE95: 18528000 | AF95: 47759000 | AG95: 20988000 | AH95: 1169822000 | AI95: 786236000 | AJ95: 940016000 | AK95: 712304000 | AL95: 734598000 | AM95: 452204000 | AN95: 990182000 | AO95: 719678000 | AP95: 1424541000 | AQ95: 486692000 | AR95: 308668000 | AS95: 902629000 | AT95: 640363000 | AU95: 1223644000 | AV95: 447801000 | BB95: 96221000 | BC95: 85807000 | BD95: 75644000 | BE95: 77788000 | BF95: 46761000 | BG95: 43860000 | BH95: 75186000 | BI95: 50949000 | BJ95: 1214000 | BK95: 61596000 | BL95: 84057000 | BM95: 70377000 | BN95: 48356000 | BO95: 109430000 | BP95: 140956000 | BQ95: 4246000 | BR95: 3959000 | BS95: 2029000 | BT95: 9392000 | BU95: -73722000
A96: 146 | B96: 14 | C96: Строительство жилых и нежилых зданий | D96: 8189000 | E96: 2210000 | F96: 2210000 | G96: 2210000 | H96: 2210000 | N96: 1569788000 | O96: 68626000 | P96: 67469000 | Q96: 75300000 | R96: 75300000 | S96: 351000 | T96: 421000 | U96: 421000 | V96: 421000 | W96: 421000 | X96: -34641000 | Y96: -30224000 | Z96: -28282000 | AA96: -28542000 | AB96: -28542000 | AC96: 777000 | AD96: 1922000 | AE96: 1940000 | AF96: 10474000 | AG96: 10474000 | AH96: 21065000 | AI96: 60913000 | AJ96: 65488000 | AK96: 99649000 | AL96: 99649000 | AN96: 54589000 | AO96: 7935000 | AS96: 12948000 | BC96: 2082000 | BD96: 1735000 | BE96: 260000 | BG96: 4943000 | BH96: 7289000 | BI96: 2000 | BL96: 21447000 | BM96: 41290000 | BN96: 3775000 | BQ96: -16504000 | BR96: 4416000 | BS96: 1942000 | BT96: -260000
